Workbook

Sheet Sales Analysis
A1: Mobility Sales Analysis (all figures USD, after discounts)
A2: Summary tables are SUMIFS/COUNTIFS formulas over Clean Data, so they recalculate. No refund or expense data exists in the source, so Total Sales = Units x USD price x (1 - discount).
A4: 1. Sales by region
A5: Country | B5: Continent | C5: Units Sold | D5: Total Sales (USD) | E5: Share of Sales | F5: Rank
A6: India | B6: =INDEX(Lookups!$C$3:$C$6,MATCH(A6,Lookups!$B$3:$B$6,0)) -> Asia | C6: =SUMIFS('Clean Data'!$N$2:$N$145,'Clean Data'!$I$2:$I$145,A6) -> 11350 | D6: =SUMIFS('Clean Data'!$P$2:$P$145,'Clean Data'!$I$2:$I$145,A6) -> 3274230 | E6: =D6/D$10 -> 0.082029982 | F6: =RANK(D6,D$6:D$9) -> 4
A7: China | B7: =INDEX(Lookups!$C$3:$C$6,MATCH(A7,Lookups!$B$3:$B$6,0)) -> Asia | C7: =SUMIFS('Clean Data'!$N$2:$N$145,'Clean Data'!$I$2:$I$145,A7) -> 37450 | D7: =SUMIFS('Clean Data'!$P$2:$P$145,'Clean Data'!$I$2:$I$145,A7) -> 20302030 | E7: =D7/D$10 -> 0.50863108 | F7: =RANK(D7,D$6:D$9) -> 1
A8: France | B8: =INDEX(Lookups!$C$3:$C$6,MATCH(A8,Lookups!$B$3:$B$6,0)) -> Europe | C8: =SUMIFS('Clean Data'!$N$2:$N$145,'Clean Data'!$I$2:$I$145,A8) -> 8450 | D8: =SUMIFS('Clean Data'!$P$2:$P$145,'Clean Data'!$I$2:$I$145,A8) -> 8704557 | E8: =D8/D$10 -> 0.21807712 | F8: =RANK(D8,D$6:D$9) -> 2
A9: Germany | B9: =INDEX(Lookups!$C$3:$C$6,MATCH(A9,Lookups!$B$3:$B$6,0)) -> Europe | C9: =SUMIFS('Clean Data'!$N$2:$N$145,'Clean Data'!$I$2:$I$145,A9) -> 8230 | D9: =SUMIFS('Clean Data'!$P$2:$P$145,'Clean Data'!$I$2:$I$145,A9) -> 7634223 | E9: =D9/D$10 -> 0.19126182 | F9: =RANK(D9,D$6:D$9) -> 3
A10: Total | C10: =SUM(C6:C9) -> 65480 | D10: =SUM(D6:D9) -> 39915040 | E10: =SUM(E6:E9) -> 1
A12: By continent
A13: Continent | C13: Units Sold | D13: Total Sales (USD) | E13: Share of Sales
A14: Asia | C14: =SUMIFS('Clean Data'!$N$2:$N$145,'Clean Data'!$J$2:$J$145,A14) -> 48800 | D14: =SUMIFS('Clean Data'!$P$2:$P$145,'Clean Data'!$J$2:$J$145,A14) -> 23576260 | E14: =D14/D10 -> 0.59066106
A15: Europe | C15: =SUMIFS('Clean Data'!$N$2:$N$145,'Clean Data'!$J$2:$J$145,A15) -> 16680 | D15: =SUMIFS('Clean Data'!$P$2:$P$145,'Clean Data'!$J$2:$J$145,A15) -> 16338780 | E15: =D15/D10 -> 0.40933894
A17: 2. Monthly sales trend
A18: Month | B18: Quarter | C18: Units Sold | D18: Total Sales (USD) | E18: MoM Change
A19: January | B19: ="Q"&ROUNDUP(1/3,0) -> Q1 | C19: =SUMIFS('Clean Data'!$N$2:$N$145,'Clean Data'!$C$2:$C$145,A19) -> 3950 | D19: =SUMIFS('Clean Data'!$P$2:$P$145,'Clean Data'!$C$2:$C$145,A19) -> 2276478
A20: February | B20: ="Q"&ROUNDUP(2/3,0) -> Q1 | C20: =SUMIFS('Clean Data'!$N$2:$N$145,'Clean Data'!$C$2:$C$145,A20) -> 4410 | D20: =SUMIFS('Clean Data'!$P$2:$P$145,'Clean Data'!$C$2:$C$145,A20) -> 2798320 | E20: =D20/D19-1 -> 0.22923217
A21: March | B21: ="Q"&ROUNDUP(3/3,0) -> Q1 | C21: =SUMIFS('Clean Data'!$N$2:$N$145,'Clean Data'!$C$2:$C$145,A21) -> 4410 | D21: =SUMIFS('Clean Data'!$P$2:$P$145,'Clean Data'!$C$2:$C$145,A21) -> 2798320 | E21: =D21/D20-1 -> 0
A22: April | B22: ="Q"&ROUNDUP(4/3,0) -> Q2 | C22: =SUMIFS('Clean Data'!$N$2:$N$145,'Clean Data'!$C$2:$C$145,A22) -> 5550 | D22: =SUMIFS('Clean Data'!$P$2:$P$145,'Clean Data'!$C$2:$C$145,A22) -> 3474980 | E22: =D22/D21-1 -> 0.24180937
A23: May | B23: ="Q"&ROUNDUP(5/3,0) -> Q2 | C23: =SUMIFS('Clean Data'!$N$2:$N$145,'Clean Data'!$C$2:$C$145,A23) -> 5740 | D23: =SUMIFS('Clean Data'!$P$2:$P$145,'Clean Data'!$C$2:$C$145,A23) -> 3633440 | E23: =D23/D22-1 -> 0.045600262
A24: June | B24: ="Q"&ROUNDUP(6/3,0) -> Q2 | C24: =SUMIFS('Clean Data'!$N$2:$N$145,'Clean Data'!$C$2:$C$145,A24) -> 6650 | D24: =SUMIFS('Clean Data'!$P$2:$P$145,'Clean Data'!$C$2:$C$145,A24) -> 4175700 | E24: =D24/D23-1 -> 0.14924149
A25: July | B25: ="Q"&ROUNDUP(7/3,0) -> Q3 | C25: =SUMIFS('Clean Data'!$N$2:$N$145,'Clean Data'!$C$2:$C$145,A25) -> 6530 | D25: =SUMIFS('Clean Data'!$P$2:$P$145,'Clean Data'!$C$2:$C$145,A25) -> 4109420 | E25: =D25/D24-1 -> -0.015872788
A26: August | B26: ="Q"&ROUNDUP(8/3,0) -> Q3 | C26: =SUMIFS('Clean Data'!$N$2:$N$145,'Clean Data'!$C$2:$C$145,A26) -> 5730 | D26: =SUMIFS('Clean Data'!$P$2:$P$145,'Clean Data'!$C$2:$C$145,A26) -> 3630200 | E26: =D26/D25-1 -> -0.116615
A27: September | B27: ="Q"&ROUNDUP(9/3,0) -> Q3 | C27: =SUMIFS('Clean Data'!$N$2:$N$145,'Clean Data'!$C$2:$C$145,A27) -> 5290 | D27: =SUMIFS('Clean Data'!$P$2:$P$145,'Clean Data'!$C$2:$C$145,A27) -> 3390740 | E27: =D27/D26-1 -> -0.065963308
A28: October | B28: ="Q"&ROUNDUP(10/3,0) -> Q4 | C28: =SUMIFS('Clean Data'!$N$2:$N$145,'Clean Data'!$C$2:$C$145,A28) -> 4780 | D28: =SUMIFS('Clean Data'!$P$2:$P$145,'Clean Data'!$C$2:$C$145,A28) -> 3089540 | E28: =D28/D27-1 -> -0.088830167
A29: November | B29: ="Q"&ROUNDUP(11/3,0) -> Q4 | C29: =SUMIFS('Clean Data'!$N$2:$N$145,'Clean Data'!$C$2:$C$145,A29) -> 5300 | D29: =SUMIFS('Clean Data'!$P$2:$P$145,'Clean Data'!$C$2:$C$145,A29) -> 2895678 | E29: =D29/D28-1 -> -0.062747852
A30: December | B30: ="Q"&ROUNDUP(12/3,0) -> Q4 | C30: =SUMIFS('Clean Data'!$N$2:$N$145,'Clean Data'!$C$2:$C$145,A30) -> 7140 | D30: =SUMIFS('Clean Data'!$P$2:$P$145,'Clean Data'!$C$2:$C$145,A30) -> 3642224 | E30: =D30/D29-1 -> 0.25781389
A31: Total | C31: =SUM(C19:C30) -> 65480 | D31: =SUM(D19:D30) -> 39915040
A33: 3. Quarterly performance
A34: Quarter | C34: Units Sold | D34: Total Sales (USD) | E34: QoQ Change | F34: Share of Sales
A35: Q1 | C35: =SUMIFS('Clean Data'!$N$2:$N$145,'Clean Data'!$D$2:$D$145,A35) -> 12770 | D35: =SUMIFS('Clean Data'!$P$2:$P$145,'Clean Data'!$D$2:$D$145,A35) -> 7873118 | F35: =D35/D$39 -> 0.1972469
A36: Q2 | C36: =SUMIFS('Clean Data'!$N$2:$N$145,'Clean Data'!$D$2:$D$145,A36) -> 17940 | D36: =SUMIFS('Clean Data'!$P$2:$P$145,'Clean Data'!$D$2:$D$145,A36) -> 11284120 | E36: =D36/D35-1 -> 0.43324665 | F36: =D36/D$39 -> 0.28270346
A37: Q3 | C37: =SUMIFS('Clean Data'!$N$2:$N$145,'Clean Data'!$D$2:$D$145,A37) -> 17550 | D37: =SUMIFS('Clean Data'!$P$2:$P$145,'Clean Data'!$D$2:$D$145,A37) -> 11130360 | E37: =D37/D36-1 -> -0.013626229 | F37: =D37/D$39 -> 0.27885128
A38: Q4 | C38: =SUMIFS('Clean Data'!$N$2:$N$145,'Clean Data'!$D$2:$D$145,A38) -> 17220 | D38: =SUMIFS('Clean Data'!$P$2:$P$145,'Clean Data'!$D$2:$D$145,A38) -> 9627442 | E38: =D38/D37-1 -> -0.1350287 | F38: =D38/D$39 -> 0.24119836
A39: Total | C39: =SUM(C35:C38) -> 65480 | D39: =SUM(D35:D38) -> 39915040 | F39: =SUM(F35:F38) -> 1
A41: 4. Top product types
A42: Product Type | C42: Units Sold | D42: Total Sales (USD) | E42: Share of Sales | F42: Rank
A43: Electric Unicycle | C43: =SUMIFS('Clean Data'!$N$2:$N$145,'Clean Data'!$E$2:$E$145,A43) -> 13780 | D43: =SUMIFS('Clean Data'!$P$2:$P$145,'Clean Data'!$E$2:$E$145,A43) -> 9994124 | E43: =D43/D$46 -> 0.25038492 | F43: =RANK(D43,D$43:D$45) -> 3
A44: Electric Scooter | C44: =SUMIFS('Clean Data'!$N$2:$N$145,'Clean Data'!$E$2:$E$145,A44) -> 30610 | D44: =SUMIFS('Clean Data'!$P$2:$P$145,'Clean Data'!$E$2:$E$145,A44) -> 16384850 | E44: =D44/D$46 -> 0.41049314 | F44: =RANK(D44,D$43:D$45) -> 1
A45: Electric Skateboard | C45: =SUMIFS('Clean Data'!$N$2:$N$145,'Clean Data'!$E$2:$E$145,A45) -> 21090 | D45: =SUMIFS('Clean Data'!$P$2:$P$145,'Clean Data'!$E$2:$E$145,A45) -> 13536066 | E45: =D45/D$46 -> 0.33912195 | F45: =RANK(D45,D$43:D$45) -> 2
A46: Total | C46: =SUM(C43:C45) -> 65480 | D46: =SUM(D43:D45) -> 39915040 | E46: =SUM(E43:E45) -> 1
A48: 5. Total sales by product type and region (USD)
A49: Product Type | B49: India | C49: China | D49: France | E49: Germany | F49: Total
A50: Electric Unicycle | B50: =SUMIFS('Clean Data'!$P$2:$P$145,'Clean Data'!$E$2:$E$145,$A50,'Clean Data'!$I$2:$I$145,B$49) -> 805680 | C50: =SUMIFS('Clean Data'!$P$2:$P$145,'Clean Data'!$E$2:$E$145,$A50,'Clean Data'!$I$2:$I$145,C$49) -> 5285000 | D50: =SUMIFS('Clean Data'!$P$2:$P$145,'Clean Data'!$E$2:$E$145,$A50,'Clean Data'!$I$2:$I$145,D$49) -> 1868724 | E50: =SUMIFS('Clean Data'!$P$2:$P$145,'Clean Data'!$E$2:$E$145,$A50,'Clean Data'!$I$2:$I$145,E$49) -> 2034720 | F50: =SUM(B50:E50) -> 9994124
A51: Electric Scooter | B51: =SUMIFS('Clean Data'!$P$2:$P$145,'Clean Data'!$E$2:$E$145,$A51,'Clean Data'!$I$2:$I$145,B$49) -> 1524750 | C51: =SUMIFS('Clean Data'!$P$2:$P$145,'Clean Data'!$E$2:$E$145,$A51,'Clean Data'!$I$2:$I$145,C$49) -> 8513750 | D51: =SUMIFS('Clean Data'!$P$2:$P$145,'Clean Data'!$E$2:$E$145,$A51,'Clean Data'!$I$2:$I$145,D$49) -> 3381102 | E51: =SUMIFS('Clean Data'!$P$2:$P$145,'Clean Data'!$E$2:$E$145,$A51,'Clean Data'!$I$2:$I$145,E$49) -> 2965248 | F51: =SUM(B51:E51) -> 16384850
A52: Electric Skateboard | B52: =SUMIFS('Clean Data'!$P$2:$P$145,'Clean Data'!$E$2:$E$145,$A52,'Clean Data'!$I$2:$I$145,B$49) -> 943800 | C52: =SUMIFS('Clean Data'!$P$2:$P$145,'Clean Data'!$E$2:$E$145,$A52,'Clean Data'!$I$2:$I$145,C$49) -> 6503280 | D52: =SUMIFS('Clean Data'!$P$2:$P$145,'Clean Data'!$E$2:$E$145,$A52,'Clean Data'!$I$2:$I$145,D$49) -> 3454731 | E52: =SUMIFS('Clean Data'!$P$2:$P$145,'Clean Data'!$E$2:$E$145,$A52,'Clean Data'!$I$2:$I$145,E$49) -> 2634255 | F52: =SUM(B52:E52) -> 13536066
A53: Total | B53: =SUM(B50:B52) -> 3274230 | C53: =SUM(C50:C52) -> 20302030 | D53: =SUM(D50:D52) -> 8704557 | E53: =SUM(E50:E52) -> 7634223 | F53: =SUM(F50:F52) -> 39915040
A55: 6. Sales representative performance
A56: Rep Name | B56: Country | C56: Units Sold | D56: Total Sales (USD) | E56: Share of Sales | F56: Rank
A57: Bernard, Théo | B57: France | C57: =SUMIFS('Clean Data'!$N$2:$N$145,'Clean Data'!$B$2:$B$145,A57) -> 8450 | D57: =SUMIFS('Clean Data'!$P$2:$P$145,'Clean Data'!$B$2:$B$145,A57) -> 8704557 | E57: =D57/D$61 -> 0.21807712 | F57: =RANK(D57,D$57:D$60) -> 2
A58: Fischer, Jonas | B58: Germany | C58: =SUMIFS('Clean Data'!$N$2:$N$145,'Clean Data'!$B$2:$B$145,A58) -> 8230 | D58: =SUMIFS('Clean Data'!$P$2:$P$145,'Clean Data'!$B$2:$B$145,A58) -> 7634223 | E58: =D58/D$61 -> 0.19126182 | F58: =RANK(D58,D$57:D$60) -> 3
A59: Joshi, Sanya | B59: India | C59: =SUMIFS('Clean Data'!$N$2:$N$145,'Clean Data'!$B$2:$B$145,A59) -> 11350 | D59: =SUMIFS('Clean Data'!$P$2:$P$145,'Clean Data'!$B$2:$B$145,A59) -> 3274230 | E59: =D59/D$61 -> 0.082029982 | F59: =RANK(D59,D$57:D$60) -> 4
A60: Liu, Fang | B60: China | C60: =SUMIFS('Clean Data'!$N$2:$N$145,'Clean Data'!$B$2:$B$145,A60) -> 37450 | D60: =SUMIFS('Clean Data'!$P$2:$P$145,'Clean Data'!$B$2:$B$145,A60) -> 20302030 | E60: =D60/D$61 -> 0.50863108 | F60: =RANK(D60,D$57:D$60) -> 1
A61: Total | C61: =SUM(C57:C60) -> 65480 | D61: =SUM(D57:D60) -> 39915040 | E61: =SUM(E57:E60) -> 1
A62: Lowest-selling rep | B62: =INDEX(A57:A60,MATCH(MIN(D57:D60),D57:D60,0)) -> Joshi, Sanya
A63: Top-selling rep | B63: =INDEX(A57:A60,MATCH(MAX(D57:D60),D57:D60,0)) -> Liu, Fang
A65: 7. Impact of discounts on units sold
A66: Discount (%) | B66: Orders | C66: Units Sold | D66: Avg Units per Order | E66: Total Sales (USD)
A67: 0 | B67: =COUNTIFS('Clean Data'!$O$2:$O$145,A67) -> 108 | C67: =SUMIFS('Clean Data'!$N$2:$N$145,'Clean Data'!$O$2:$O$145,A67) -> 49090 | D67: =IF(B67=0,0,C67/B67) -> 454.53704 | E67: =SUMIFS('Clean Data'!$P$2:$P$145,'Clean Data'!$O$2:$O$145,A67) -> 31100660
A68: 10 | B68: =COUNTIFS('Clean Data'!$O$2:$O$145,A68) -> 12 | C68: =SUMIFS('Clean Data'!$N$2:$N$145,'Clean Data'!$O$2:$O$145,A68) -> 3950 | D68: =IF(B68=0,0,C68/B68) -> 329.16667 | E68: =SUMIFS('Clean Data'!$P$2:$P$145,'Clean Data'!$O$2:$O$145,A68) -> 2276478
A69: 15 | B69: =COUNTIFS('Clean Data'!$O$2:$O$145,A69) -> 12 | C69: =SUMIFS('Clean Data'!$N$2:$N$145,'Clean Data'!$O$2:$O$145,A69) -> 5300 | D69: =IF(B69=0,0,C69/B69) -> 441.66667 | E69: =SUMIFS('Clean Data'!$P$2:$P$145,'Clean Data'!$O$2:$O$145,A69) -> 2895678
A70: 20 | B70: =COUNTIFS('Clean Data'!$O$2:$O$145,A70) -> 12 | C70: =SUMIFS('Clean Data'!$N$2:$N$145,'Clean Data'!$O$2:$O$145,A70) -> 7140 | D70: =IF(B70=0,0,C70/B70) -> 595 | E70: =SUMIFS('Clean Data'!$P$2:$P$145,'Clean Data'!$O$2:$O$145,A70) -> 3642224
A71: Total | B71: =SUM(B67:B70) -> 144 | C71: =SUM(C67:C70) -> 65480 | E71: =SUM(E67:E70) -> 39915040
A72: Note: no expense data in the source, so a revenue-vs-expenses chart is not possible; quarterly revenue is shown in section 3.

Sheet Clean Data
A1: Sales Rep ID | B1: Rep Name (Last, First) | C1: Month | D1: Quarter | E1: Product Type | F1: Street | G1: City | H1: Postal Code | I1: Country | J1: Continent | K1: Currency | L1: Unit Price (Local) | M1: Unit Price (USD) | N1: Units Sold | O1: Discount (%) | P1: Total Sales (USD) | Q1: Speed Range (km/h) | R1: Distance (km) | S1: Rep First Name | T1: Rep Last Name | U1: Min Speed (orig) | V1: Speed (orig) | W1: Distance (orig) | X1: Shipping Address (orig) | Y1: Country Code (orig) | Z1: Unit Price (orig) | AA1: Min Speed (mph, filled) | AB1: Top Speed (mph) | AD1: Legend
A2: 1 | B2: =T2&", "&S2 -> Joshi, Sanya | C2: January | D2: ="Q"&ROUNDUP(MATCH(C2,Lookups!$L$3:$L$14,0)/3,0) -> Q1 | E2: Electric Unicycle | F2: 456 Brigade Road | G2: Bengaluru | H2: 560001 | I2: =INDEX(Lookups!$B$3:$B$6,MATCH(Y2,Lookups!$A$3:$A$6,0)) -> India | J2: =INDEX(Lookups!$C$3:$C$6,MATCH(Y2,Lookups!$A$3:$A$6,0)) -> Asia | K2: =INDEX(Lookups!$D$3:$D$6,MATCH(Y2,Lookups!$A$3:$A$6,0)) -> INR | L2: 30000 | M2: =ROUND(L2*INDEX(Lookups!$G$3:$G$5,MATCH(K2,Lookups!$F$3:$F$5,0)),0) -> 360 | N2: 150 | O2: 10 | P2: =ROUND(N2*M2*(1-O2/100),0) -> 48600 | Q2: =ROUND(AA2*Lookups!$O$3,0)&" - "&ROUND(AB2*Lookups!$O$3,0)&" km/h" -> 24 - 48 km/h | R2: =IF(ISNUMBER(SEARCH("meters",W2)),ROUND(VALUE(SUBSTITUTE(LEFT(W2,FIND(" ",W2)-1),",",""))/Lookups!$O$4,0),ROUND(VALUE(LEFT(W2,FIND(" ",W2)-1))*Lookups!$O$3,0)) -> 48 | S2: Sanya | T2: Joshi | U2: 15 mph | V2: 30 mph | W2: 30 miles | X2: 456 Brigade Road, Bengaluru, 560001 | Y2: IN | Z2: ₹30,000 | AA2: =IF(U2="",INDEX(Lookups!$J$3:$J$5,MATCH(E2,Lookups!$I$3:$I$5,0)),VALUE(LEFT(U2,FIND(" ",U2)-1))) -> 15 | AB2: =VALUE(LEFT(V2,FIND(" ",V2)-1)) -> 30 | AD2: Orange speed range = Min Speed was blank; filled with the standard for that product type
A3: 2 | B3: =T3&", "&S3 -> Joshi, Sanya | C3: January | D3: ="Q"&ROUNDUP(MATCH(C3,Lookups!$L$3:$L$14,0)/3,0) -> Q1 | E3: Electric Scooter | F3: 457 Brigade Road | G3: Bengaluru | H3: 560001 | I3: =INDEX(Lookups!$B$3:$B$6,MATCH(Y3,Lookups!$A$3:$A$6,0)) -> India | J3: =INDEX(Lookups!$C$3:$C$6,MATCH(Y3,Lookups!$A$3:$A$6,0)) -> Asia | K3: =INDEX(Lookups!$D$3:$D$6,MATCH(Y3,Lookups!$A$3:$A$6,0)) -> INR | L3: 25000 | M3: =ROUND(L3*INDEX(Lookups!$G$3:$G$5,MATCH(K3,Lookups!$F$3:$F$5,0)),0) -> 300 | N3: 300 | O3: 10 | P3: =ROUND(N3*M3*(1-O3/100),0) -> 81000 | Q3: =ROUND(AA3*Lookups!$O$3,0)&" - "&ROUND(AB3*Lookups!$O$3,0)&" km/h" -> 32 - 56 km/h | R3: =IF(ISNUMBER(SEARCH("meters",W3)),ROUND(VALUE(SUBSTITUTE(LEFT(W3,FIND(" ",W3)-1),",",""))/Lookups!$O$4,0),ROUND(VALUE(LEFT(W3,FIND(" ",W3)-1))*Lookups!$O$3,0)) -> 64 | S3: Sanya | T3: Joshi | U3: 20 mph | V3: 35 mph | W3: 40 miles | X3: 457 Brigade Road, Bengaluru, 560001 | Y3: IN | Z3: ₹25,000 | AA3: =IF(U3="",INDEX(Lookups!$J$3:$J$5,MATCH(E3,Lookups!$I$3:$I$5,0)),VALUE(LEFT(U3,FIND(" ",U3)-1))) -> 20 | AB3: =VALUE(LEFT(V3,FIND(" ",V3)-1)) -> 35 | AD3: Yellow discount = 15% or more
A4: 3 | B4: =T4&", "&S4 -> Joshi, Sanya | C4: January | D4: ="Q"&ROUNDUP(MATCH(C4,Lookups!$L$3:$L$14,0)/3,0) -> Q1 | E4: Electric Skateboard | F4: 458 Brigade Road | G4: Bengaluru | H4: 560001 | I4: =INDEX(Lookups!$B$3:$B$6,MATCH(Y4,Lookups!$A$3:$A$6,0)) -> India | J4: =INDEX(Lookups!$C$3:$C$6,MATCH(Y4,Lookups!$A$3:$A$6,0)) -> Asia | K4: =INDEX(Lookups!$D$3:$D$6,MATCH(Y4,Lookups!$A$3:$A$6,0)) -> INR | L4: 22000 | M4: =ROUND(L4*INDEX(Lookups!$G$3:$G$5,MATCH(K4,Lookups!$F$3:$F$5,0)),0) -> 264 | N4: 200 | O4: 10 | P4: =ROUND(N4*M4*(1-O4/100),0) -> 47520 | Q4: =ROUND(AA4*Lookups!$O$3,0)&" - "&ROUND(AB4*Lookups!$O$3,0)&" km/h" -> 29 - 45 km/h | R4: =IF(ISNUMBER(SEARCH("meters",W4)),ROUND(VALUE(SUBSTITUTE(LEFT(W4,FIND(" ",W4)-1),",",""))/Lookups!$O$4,0),ROUND(VALUE(LEFT(W4,FIND(" ",W4)-1))*Lookups!$O$3,0)) -> 40 | S4: Sanya | T4: Joshi | U4: 18 mph | V4: 28 mph | W4: 25 miles | X4: 458 Brigade Road, Bengaluru, 560001 | Y4: IN | Z4: ₹22,000 | AA4: =IF(U4="",INDEX(Lookups!$J$3:$J$5,MATCH(E4,Lookups!$I$3:$I$5,0)),VALUE(LEFT(U4,FIND(" ",U4)-1))) -> 18 | AB4: =VALUE(LEFT(V4,FIND(" ",V4)-1)) -> 28 | AD4: Hidden columns S:AB hold the original fields and conversion helpers (unhide to audit)
A5: 4 | B5: =T5&", "&S5 -> Liu, Fang | C5: January | D5: ="Q"&ROUNDUP(MATCH(C5,Lookups!$L$3:$L$14,0)/3,0) -> Q1 | E5: Electric Unicycle | F5: 99 Nanjing Road | G5: Shanghai | H5: 200001 | I5: =INDEX(Lookups!$B$3:$B$6,MATCH(Y5,Lookups!$A$3:$A$6,0)) -> China | J5: =INDEX(Lookups!$C$3:$C$6,MATCH(Y5,Lookups!$A$3:$A$6,0)) -> Asia | K5: =INDEX(Lookups!$D$3:$D$6,MATCH(Y5,Lookups!$A$3:$A$6,0)) -> CNY | L5: 5000 | M5: =ROUND(L5*INDEX(Lookups!$G$3:$G$5,MATCH(K5,Lookups!$F$3:$F$5,0)),0) -> 700 | N5: 500 | O5: 10 | P5: =ROUND(N5*M5*(1-O5/100),0) -> 315000 | Q5: =ROUND(AA5*Lookups!$O$3,0)&" - "&ROUND(AB5*Lookups!$O$3,0)&" km/h" -> 24 - 48 km/h | R5: =IF(ISNUMBER(SEARCH("meters",W5)),ROUND(VALUE(SUBSTITUTE(LEFT(W5,FIND(" ",W5)-1),",",""))/Lookups!$O$4,0),ROUND(VALUE(LEFT(W5,FIND(" ",W5)-1))*Lookups!$O$3,0)) -> 48 | S5: Fang | T5: Liu | U5: 15 mph | V5: 30 mph | W5: 30 miles | X5: 99 Nanjing Road, Shanghai, 200001 | Y5: CN | Z5: ¥5,000 | AA5: =IF(U5="",INDEX(Lookups!$J$3:$J$5,MATCH(E5,Lookups!$I$3:$I$5,0)),VALUE(LEFT(U5,FIND(" ",U5)-1))) -> 15 | AB5: =VALUE(LEFT(V5,FIND(" ",V5)-1)) -> 30
A6: 5 | B6: =T6&", "&S6 -> Liu, Fang | C6: January | D6: ="Q"&ROUNDUP(MATCH(C6,Lookups!$L$3:$L$14,0)/3,0) -> Q1 | E6: Electric Scooter | F6: 100 Nanjing Road | G6: Shanghai | H6: 200001 | I6: =INDEX(Lookups!$B$3:$B$6,MATCH(Y6,Lookups!$A$3:$A$6,0)) -> China | J6: =INDEX(Lookups!$C$3:$C$6,MATCH(Y6,Lookups!$A$3:$A$6,0)) -> Asia | K6: =INDEX(Lookups!$D$3:$D$6,MATCH(Y6,Lookups!$A$3:$A$6,0)) -> CNY | L6: 3500 | M6: =ROUND(L6*INDEX(Lookups!$G$3:$G$5,MATCH(K6,Lookups!$F$3:$F$5,0)),0) -> 490 | N6: 1000 | O6: 10 | P6: =ROUND(N6*M6*(1-O6/100),0) -> 441000 | Q6: =ROUND(AA6*Lookups!$O$3,0)&" - "&ROUND(AB6*Lookups!$O$3,0)&" km/h" -> 32 - 56 km/h | R6: =IF(ISNUMBER(SEARCH("meters",W6)),ROUND(VALUE(SUBSTITUTE(LEFT(W6,FIND(" ",W6)-1),",",""))/Lookups!$O$4,0),ROUND(VALUE(LEFT(W6,FIND(" ",W6)-1))*Lookups!$O$3,0)) -> 64 | S6: Fang | T6: Liu | U6: 20 mph | V6: 35 mph | W6: 40 miles | X6: 100 Nanjing Road, Shanghai, 200001 | Y6: CN | Z6: ¥3,500 | AA6: =IF(U6="",INDEX(Lookups!$J$3:$J$5,MATCH(E6,Lookups!$I$3:$I$5,0)),VALUE(LEFT(U6,FIND(" ",U6)-1))) -> 20 | AB6: =VALUE(LEFT(V6,FIND(" ",V6)-1)) -> 35
A7: 6 | B7: =T7&", "&S7 -> Liu, Fang | C7: January | D7: ="Q"&ROUNDUP(MATCH(C7,Lookups!$L$3:$L$14,0)/3,0) -> Q1 | E7: Electric Skateboard | F7: 101 Nanjing Road | G7: Shanghai | H7: 200001 | I7: =INDEX(Lookups!$B$3:$B$6,MATCH(Y7,Lookups!$A$3:$A$6,0)) -> China | J7: =INDEX(Lookups!$C$3:$C$6,MATCH(Y7,Lookups!$A$3:$A$6,0)) -> Asia | K7: =INDEX(Lookups!$D$3:$D$6,MATCH(Y7,Lookups!$A$3:$A$6,0)) -> CNY | L7: 4200 | M7: =ROUND(L7*INDEX(Lookups!$G$3:$G$5,MATCH(K7,Lookups!$F$3:$F$5,0)),0) -> 588 | N7: 800 | O7: 10 | P7: =ROUND(N7*M7*(1-O7/100),0) -> 423360 | Q7: =ROUND(AA7*Lookups!$O$3,0)&" - "&ROUND(AB7*Lookups!$O$3,0)&" km/h" -> 29 - 45 km/h | R7: =IF(ISNUMBER(SEARCH("meters",W7)),ROUND(VALUE(SUBSTITUTE(LEFT(W7,FIND(" ",W7)-1),",",""))/Lookups!$O$4,0),ROUND(VALUE(LEFT(W7,FIND(" ",W7)-1))*Lookups!$O$3,0)) -> 40 | S7: Fang | T7: Liu | V7: 28 mph | W7: 40,230 meters | X7: 101 Nanjing Road, Shanghai, 200001 | Y7: CN | Z7: ¥4,200 | AA7: =IF(U7="",INDEX(Lookups!$J$3:$J$5,MATCH(E7,Lookups!$I$3:$I$5,0)),VALUE(LEFT(U7,FIND(" ",U7)-1))) -> 18 | AB7: =VALUE(LEFT(V7,FIND(" ",V7)-1)) -> 28
A8: 7 | B8: =T8&", "&S8 -> Fischer, Jonas | C8: January | D8: ="Q"&ROUNDUP(MATCH(C8,Lookups!$L$3:$L$14,0)/3,0) -> Q1 | E8: Electric Unicycle | F8: 303 Ringstraße | G8: Hamburg | H8: 20095 | I8: =INDEX(Lookups!$B$3:$B$6,MATCH(Y8,Lookups!$A$3:$A$6,0)) -> Germany | J8: =INDEX(Lookups!$C$3:$C$6,MATCH(Y8,Lookups!$A$3:$A$6,0)) -> Europe | K8: =INDEX(Lookups!$D$3:$D$6,MATCH(Y8,Lookups!$A$3:$A$6,0)) -> EUR | L8: 1000 | M8: =ROUND(L8*INDEX(Lookups!$G$3:$G$5,MATCH(K8,Lookups!$F$3:$F$5,0)),0) -> 1080 | N8: 120 | O8: 10 | P8: =ROUND(N8*M8*(1-O8/100),0) -> 116640 | Q8: =ROUND(AA8*Lookups!$O$3,0)&" - "&ROUND(AB8*Lookups!$O$3,0)&" km/h" -> 24 - 48 km/h | R8: =IF(ISNUMBER(SEARCH("meters",W8)),ROUND(VALUE(SUBSTITUTE(LEFT(W8,FIND(" ",W8)-1),",",""))/Lookups!$O$4,0),ROUND(VALUE(LEFT(W8,FIND(" ",W8)-1))*Lookups!$O$3,0)) -> 48 | S8: Jonas | T8: Fischer | U8: 15 mph | V8: 30 mph | W8: 48,280 meters | X8: 303 Ringstraße, Hamburg, 20095 | Y8: DE | Z8: €1000 | AA8: =IF(U8="",INDEX(Lookups!$J$3:$J$5,MATCH(E8,Lookups!$I$3:$I$5,0)),VALUE(LEFT(U8,FIND(" ",U8)-1))) -> 15 | AB8: =VALUE(LEFT(V8,FIND(" ",V8)-1)) -> 30
A9: 8 | B9: =T9&", "&S9 -> Fischer, Jonas | C9: January | D9: ="Q"&ROUNDUP(MATCH(C9,Lookups!$L$3:$L$14,0)/3,0) -> Q1 | E9: Electric Scooter | F9: 304 Ringstraße | G9: Hamburg | H9: 20095 | I9: =INDEX(Lookups!$B$3:$B$6,MATCH(Y9,Lookups!$A$3:$A$6,0)) -> Germany | J9: =INDEX(Lookups!$C$3:$C$6,MATCH(Y9,Lookups!$A$3:$A$6,0)) -> Europe | K9: =INDEX(Lookups!$D$3:$D$6,MATCH(Y9,Lookups!$A$3:$A$6,0)) -> EUR | L9: 800 | M9: =ROUND(L9*INDEX(Lookups!$G$3:$G$5,MATCH(K9,Lookups!$F$3:$F$5,0)),0) -> 864 | N9: 200 | O9: 10 | P9: =ROUND(N9*M9*(1-O9/100),0) -> 155520 | Q9: =ROUND(AA9*Lookups!$O$3,0)&" - "&ROUND(AB9*Lookups!$O$3,0)&" km/h" -> 32 - 56 km/h | R9: =IF(ISNUMBER(SEARCH("meters",W9)),ROUND(VALUE(SUBSTITUTE(LEFT(W9,FIND(" ",W9)-1),",",""))/Lookups!$O$4,0),ROUND(VALUE(LEFT(W9,FIND(" ",W9)-1))*Lookups!$O$3,0)) -> 64 | S9: Jonas | T9: Fischer | U9: 20 mph | V9: 35 mph | W9: 40 miles | X9: 304 Ringstraße, Hamburg, 20095 | Y9: DE | Z9: €800 | AA9: =IF(U9="",INDEX(Lookups!$J$3:$J$5,MATCH(E9,Lookups!$I$3:$I$5,0)),VALUE(LEFT(U9,FIND(" ",U9)-1))) -> 20 | AB9: =VALUE(LEFT(V9,FIND(" ",V9)-1)) -> 35
A10: 9 | B10: =T10&", "&S10 -> Fischer, Jonas | C10: January | D10: ="Q"&ROUNDUP(MATCH(C10,Lookups!$L$3:$L$14,0)/3,0) -> Q1 | E10: Electric Skateboard | F10: 305 Ringstraße | G10: Hamburg | H10: 20095 | I10: =INDEX(Lookups!$B$3:$B$6,MATCH(Y10,Lookups!$A$3:$A$6,0)) -> Germany | J10: =INDEX(Lookups!$C$3:$C$6,MATCH(Y10,Lookups!$A$3:$A$6,0)) -> Europe | K10: =INDEX(Lookups!$D$3:$D$6,MATCH(Y10,Lookups!$A$3:$A$6,0)) -> EUR | L10: 950 | M10: =ROUND(L10*INDEX(Lookups!$G$3:$G$5,MATCH(K10,Lookups!$F$3:$F$5,0)),0) -> 1026 | N10: 150 | O10: 10 | P10: =ROUND(N10*M10*(1-O10/100),0) -> 138510 | Q10: =ROUND(AA10*Lookups!$O$3,0)&" - "&ROUND(AB10*Lookups!$O$3,0)&" km/h" -> 29 - 45 km/h | R10: =IF(ISNUMBER(SEARCH("meters",W10)),ROUND(VALUE(SUBSTITUTE(LEFT(W10,FIND(" ",W10)-1),",",""))/Lookups!$O$4,0),ROUND(VALUE(LEFT(W10,FIND(" ",W10)-1))*Lookups!$O$3,0)) -> 40 | S10: Jonas | T10: Fischer | U10: 18 mph | V10: 28 mph | W10: 25 miles | X10: 305 Ringstraße, Hamburg, 20095 | Y10: DE | Z10: €950 | AA10: =IF(U10="",INDEX(Lookups!$J$3:$J$5,MATCH(E10,Lookups!$I$3:$I$5,0)),VALUE(LEFT(U10,FIND(" ",U10)-1))) -> 18 | AB10: =VALUE(LEFT(V10,FIND(" ",V10)-1)) -> 28
A11: 10 | B11: =T11&", "&S11 -> Bernard, Théo | C11: January | D11: ="Q"&ROUNDUP(MATCH(C11,Lookups!$L$3:$L$14,0)/3,0) -> Q1 | E11: Electric Unicycle | F11: 56 Boulevard Saint-Germain | G11: Paris | H11: 75005 | I11: =INDEX(Lookups!$B$3:$B$6,MATCH(Y11,Lookups!$A$3:$A$6,0)) -> France | J11: =INDEX(Lookups!$C$3:$C$6,MATCH(Y11,Lookups!$A$3:$A$6,0)) -> Europe | K11: =INDEX(Lookups!$D$3:$D$6,MATCH(Y11,Lookups!$A$3:$A$6,0)) -> EUR | L11: 1100 | M11: =ROUND(L11*INDEX(Lookups!$G$3:$G$5,MATCH(K11,Lookups!$F$3:$F$5,0)),0) -> 1188 | N11: 100 | O11: 10 | P11: =ROUND(N11*M11*(1-O11/100),0) -> 106920 | Q11: =ROUND(AA11*Lookups!$O$3,0)&" - "&ROUND(AB11*Lookups!$O$3,0)&" km/h" -> 24 - 48 km/h | R11: =IF(ISNUMBER(SEARCH("meters",W11)),ROUND(VALUE(SUBSTITUTE(LEFT(W11,FIND(" ",W11)-1),",",""))/Lookups!$O$4,0),ROUND(VALUE(LEFT(W11,FIND(" ",W11)-1))*Lookups!$O$3,0)) -> 48 | S11: Théo | T11: Bernard | U11: 15 mph | V11: 30 mph | W11: 30 miles | X11: 56 Boulevard Saint-Germain, Paris, 75005 | Y11: FR | Z11: €1100 | AA11: =IF(U11="",INDEX(Lookups!$J$3:$J$5,MATCH(E11,Lookups!$I$3:$I$5,0)),VALUE(LEFT(U11,FIND(" ",U11)-1))) -> 15 | AB11: =VALUE(LEFT(V11,FIND(" ",V11)-1)) -> 30
A12: 11 | B12: =T12&", "&S12 -> Bernard, Théo | C12: January | D12: ="Q"&ROUNDUP(MATCH(C12,Lookups!$L$3:$L$14,0)/3,0) -> Q1 | E12: Electric Scooter | F12: 57 Boulevard Saint-Germain | G12: Paris | H12: 75005 | I12: =INDEX(Lookups!$B$3:$B$6,MATCH(Y12,Lookups!$A$3:$A$6,0)) -> France | J12: =INDEX(Lookups!$C$3:$C$6,MATCH(Y12,Lookups!$A$3:$A$6,0)) -> Europe | K12: =INDEX(Lookups!$D$3:$D$6,MATCH(Y12,Lookups!$A$3:$A$6,0)) -> EUR | L12: 900 | M12: =ROUND(L12*INDEX(Lookups!$G$3:$G$5,MATCH(K12,Lookups!$F$3:$F$5,0)),0) -> 972 | N12: 250 | O12: 10 | P12: =ROUND(N12*M12*(1-O12/100),0) -> 218700 | Q12: =ROUND(AA12*Lookups!$O$3,0)&" - "&ROUND(AB12*Lookups!$O$3,0)&" km/h" -> 32 - 56 km/h | R12: =IF(ISNUMBER(SEARCH("meters",W12)),ROUND(VALUE(SUBSTITUTE(LEFT(W12,FIND(" ",W12)-1),",",""))/Lookups!$O$4,0),ROUND(VALUE(LEFT(W12,FIND(" ",W12)-1))*Lookups!$O$3,0)) -> 64 | S12: Théo | T12: Bernard | U12: 20 mph | V12: 35 mph | W12: 64,370 meters | X12: 57 Boulevard Saint-Germain, Paris, 75005 | Y12: FR | Z12: €900 | AA12: =IF(U12="",INDEX(Lookups!$J$3:$J$5,MATCH(E12,Lookups!$I$3:$I$5,0)),VALUE(LEFT(U12,FIND(" ",U12)-1))) -> 20 | AB12: =VALUE(LEFT(V12,FIND(" ",V12)-1)) -> 35
A13: 12 | B13: =T13&", "&S13 -> Bernard, Théo | C13: January | D13: ="Q"&ROUNDUP(MATCH(C13,Lookups!$L$3:$L$14,0)/3,0) -> Q1 | E13: Electric Skateboard | F13: 58 Boulevard Saint-Germain | G13: Paris | H13: 75005 | I13: =INDEX(Lookups!$B$3:$B$6,MATCH(Y13,Lookups!$A$3:$A$6,0)) -> France | J13: =INDEX(Lookups!$C$3:$C$6,MATCH(Y13,Lookups!$A$3:$A$6,0)) -> Europe | K13: =INDEX(Lookups!$D$3:$D$6,MATCH(Y13,Lookups!$A$3:$A$6,0)) -> EUR | L13: 1050 | M13: =ROUND(L13*INDEX(Lookups!$G$3:$G$5,MATCH(K13,Lookups!$F$3:$F$5,0)),0) -> 1134 | N13: 180 | O13: 10 | P13: =ROUND(N13*M13*(1-O13/100),0) -> 183708 | Q13: =ROUND(AA13*Lookups!$O$3,0)&" - "&ROUND(AB13*Lookups!$O$3,0)&" km/h" -> 29 - 45 km/h | R13: =IF(ISNUMBER(SEARCH("meters",W13)),ROUND(VALUE(SUBSTITUTE(LEFT(W13,FIND(" ",W13)-1),",",""))/Lookups!$O$4,0),ROUND(VALUE(LEFT(W13,FIND(" ",W13)-1))*Lookups!$O$3,0)) -> 40 | S13: Théo | T13: Bernard | U13: 18 mph | V13: 28 mph | W13: 25 miles | X13: 58 Boulevard Saint-Germain, Paris, 75005 | Y13: FR | Z13: €1050 | AA13: =IF(U13="",INDEX(Lookups!$J$3:$J$5,MATCH(E13,Lookups!$I$3:$I$5,0)),VALUE(LEFT(U13,FIND(" ",U13)-1))) -> 18 | AB13: =VALUE(LEFT(V13,FIND(" ",V13)-1)) -> 28
A14: 13 | B14: =T14&", "&S14 -> Joshi, Sanya | C14: February | D14: ="Q"&ROUNDUP(MATCH(C14,Lookups!$L$3:$L$14,0)/3,0) -> Q1 | E14: Electric Unicycle | F14: 456 Brigade Road | G14: Bengaluru | H14: 560001 | I14: =INDEX(Lookups!$B$3:$B$6,MATCH(Y14,Lookups!$A$3:$A$6,0)) -> India | J14: =INDEX(Lookups!$C$3:$C$6,MATCH(Y14,Lookups!$A$3:$A$6,0)) -> Asia | K14: =INDEX(Lookups!$D$3:$D$6,MATCH(Y14,Lookups!$A$3:$A$6,0)) -> INR | L14: 30000 | M14: =ROUND(L14*INDEX(Lookups!$G$3:$G$5,MATCH(K14,Lookups!$F$3:$F$5,0)),0) -> 360 | N14: 160 | O14: 0 | P14: =ROUND(N14*M14*(1-O14/100),0) -> 57600 | Q14: =ROUND(AA14*Lookups!$O$3,0)&" - "&ROUND(AB14*Lookups!$O$3,0)&" km/h" -> 24 - 48 km/h | R14: =IF(ISNUMBER(SEARCH("meters",W14)),ROUND(VALUE(SUBSTITUTE(LEFT(W14,FIND(" ",W14)-1),",",""))/Lookups!$O$4,0),ROUND(VALUE(LEFT(W14,FIND(" ",W14)-1))*Lookups!$O$3,0)) -> 48 | S14: Sanya | T14: Joshi | U14: 15 mph | V14: 30 mph | W14: 30 miles | X14: 456 Brigade Road, Bengaluru, 560001 | Y14: IN | Z14: ₹30,000 | AA14: =IF(U14="",INDEX(Lookups!$J$3:$J$5,MATCH(E14,Lookups!$I$3:$I$5,0)),VALUE(LEFT(U14,FIND(" ",U14)-1))) -> 15 | AB14: =VALUE(LEFT(V14,FIND(" ",V14)-1)) -> 30
A15: 14 | B15: =T15&", "&S15 -> Joshi, Sanya | C15: February | D15: ="Q"&ROUNDUP(MATCH(C15,Lookups!$L$3:$L$14,0)/3,0) -> Q1 | E15: Electric Scooter | F15: 457 Brigade Road | G15: Bengaluru | H15: 560001 | I15: =INDEX(Lookups!$B$3:$B$6,MATCH(Y15,Lookups!$A$3:$A$6,0)) -> India | J15: =INDEX(Lookups!$C$3:$C$6,MATCH(Y15,Lookups!$A$3:$A$6,0)) -> Asia | K15: =INDEX(Lookups!$D$3:$D$6,MATCH(Y15,Lookups!$A$3:$A$6,0)) -> INR | L15: 25000 | M15: =ROUND(L15*INDEX(Lookups!$G$3:$G$5,MATCH(K15,Lookups!$F$3:$F$5,0)),0) -> 300 | N15: 350 | O15: 0 | P15: =ROUND(N15*M15*(1-O15/100),0) -> 105000 | Q15: =ROUND(AA15*Lookups!$O$3,0)&" - "&ROUND(AB15*Lookups!$O$3,0)&" km/h" -> 32 - 56 km/h | R15: =IF(ISNUMBER(SEARCH("meters",W15)),ROUND(VALUE(SUBSTITUTE(LEFT(W15,FIND(" ",W15)-1),",",""))/Lookups!$O$4,0),ROUND(VALUE(LEFT(W15,FIND(" ",W15)-1))*Lookups!$O$3,0)) -> 64 | S15: Sanya | T15: Joshi | V15: 35 mph | W15: 40 miles | X15: 457 Brigade Road, Bengaluru, 560001 | Y15: IN | Z15: ₹25,000 | AA15: =IF(U15="",INDEX(Lookups!$J$3:$J$5,MATCH(E15,Lookups!$I$3:$I$5,0)),VALUE(LEFT(U15,FIND(" ",U15)-1))) -> 20 | AB15: =VALUE(LEFT(V15,FIND(" ",V15)-1)) -> 35
A16: 15 | B16: =T16&", "&S16 -> Joshi, Sanya | C16: February | D16: ="Q"&ROUNDUP(MATCH(C16,Lookups!$L$3:$L$14,0)/3,0) -> Q1 | E16: Electric Skateboard | F16: 458 Brigade Road | G16: Bengaluru | H16: 560001 | I16: =INDEX(Lookups!$B$3:$B$6,MATCH(Y16,Lookups!$A$3:$A$6,0)) -> India | J16: =INDEX(Lookups!$C$3:$C$6,MATCH(Y16,Lookups!$A$3:$A$6,0)) -> Asia | K16: =INDEX(Lookups!$D$3:$D$6,MATCH(Y16,Lookups!$A$3:$A$6,0)) -> INR | L16: 22000 | M16: =ROUND(L16*INDEX(Lookups!$G$3:$G$5,MATCH(K16,Lookups!$F$3:$F$5,0)),0) -> 264 | N16: 220 | O16: 0 | P16: =ROUND(N16*M16*(1-O16/100),0) -> 58080 | Q16: =ROUND(AA16*Lookups!$O$3,0)&" - "&ROUND(AB16*Lookups!$O$3,0)&" km/h" -> 29 - 45 km/h | R16: =IF(ISNUMBER(SEARCH("meters",W16)),ROUND(VALUE(SUBSTITUTE(LEFT(W16,FIND(" ",W16)-1),",",""))/Lookups!$O$4,0),ROUND(VALUE(LEFT(W16,FIND(" ",W16)-1))*Lookups!$O$3,0)) -> 40 | S16: Sanya | T16: Joshi | U16: 18 mph | V16: 28 mph | W16: 25 miles | X16: 458 Brigade Road, Bengaluru, 560001 | Y16: IN | Z16: ₹22,000 | AA16: =IF(U16="",INDEX(Lookups!$J$3:$J$5,MATCH(E16,Lookups!$I$3:$I$5,0)),VALUE(LEFT(U16,FIND(" ",U16)-1))) -> 18 | AB16: =VALUE(LEFT(V16,FIND(" ",V16)-1)) -> 28
A17: 16 | B17: =T17&", "&S17 -> Liu, Fang | C17: February | D17: ="Q"&ROUNDUP(MATCH(C17,Lookups!$L$3:$L$14,0)/3,0) -> Q1 | E17: Electric Unicycle | F17: 99 Nanjing Road | G17: Shanghai | H17: 200001 | I17: =INDEX(Lookups!$B$3:$B$6,MATCH(Y17,Lookups!$A$3:$A$6,0)) -> China | J17: =INDEX(Lookups!$C$3:$C$6,MATCH(Y17,Lookups!$A$3:$A$6,0)) -> Asia | K17: =INDEX(Lookups!$D$3:$D$6,MATCH(Y17,Lookups!$A$3:$A$6,0)) -> CNY | L17: 5000 | M17: =ROUND(L17*INDEX(Lookups!$G$3:$G$5,MATCH(K17,Lookups!$F$3:$F$5,0)),0) -> 700 | N17: 550 | O17: 0 | P17: =ROUND(N17*M17*(1-O17/100),0) -> 385000 | Q17: =ROUND(AA17*Lookups!$O$3,0)&" - "&ROUND(AB17*Lookups!$O$3,0)&" km/h" -> 24 - 48 km/h | R17: =IF(ISNUMBER(SEARCH("meters",W17)),ROUND(VALUE(SUBSTITUTE(LEFT(W17,FIND(" ",W17)-1),",",""))/Lookups!$O$4,0),ROUND(VALUE(LEFT(W17,FIND(" ",W17)-1))*Lookups!$O$3,0)) -> 48 | S17: Fang | T17: Liu | U17: 15 mph | V17: 30 mph | W17: 48,280 meters | X17: 99 Nanjing Road, Shanghai, 200001 | Y17: CN | Z17: ¥5,000 | AA17: =IF(U17="",INDEX(Lookups!$J$3:$J$5,MATCH(E17,Lookups!$I$3:$I$5,0)),VALUE(LEFT(U17,FIND(" ",U17)-1))) -> 15 | AB17: =VALUE(LEFT(V17,FIND(" ",V17)-1)) -> 30
A18: 17 | B18: =T18&", "&S18 -> Liu, Fang | C18: February | D18: ="Q"&ROUNDUP(MATCH(C18,Lookups!$L$3:$L$14,0)/3,0) -> Q1 | E18: Electric Scooter | F18: 100 Nanjing Road | G18: Shanghai | H18: 200001 | I18: =INDEX(Lookups!$B$3:$B$6,MATCH(Y18,Lookups!$A$3:$A$6,0)) -> China | J18: =INDEX(Lookups!$C$3:$C$6,MATCH(Y18,Lookups!$A$3:$A$6,0)) -> Asia | K18: =INDEX(Lookups!$D$3:$D$6,MATCH(Y18,Lookups!$A$3:$A$6,0)) -> CNY | L18: 3500 | M18: =ROUND(L18*INDEX(Lookups!$G$3:$G$5,MATCH(K18,Lookups!$F$3:$F$5,0)),0) -> 490 | N18: 1200 | O18: 0 | P18: =ROUND(N18*M18*(1-O18/100),0) -> 588000 | Q18: =ROUND(AA18*Lookups!$O$3,0)&" - "&ROUND(AB18*Lookups!$O$3,0)&" km/h" -> 32 - 56 km/h | R18: =IF(ISNUMBER(SEARCH("meters",W18)),ROUND(VALUE(SUBSTITUTE(LEFT(W18,FIND(" ",W18)-1),",",""))/Lookups!$O$4,0),ROUND(VALUE(LEFT(W18,FIND(" ",W18)-1))*Lookups!$O$3,0)) -> 64 | S18: Fang | T18: Liu | U18: 20 mph | V18: 35 mph | W18: 40 miles | X18: 100 Nanjing Road, Shanghai, 200001 | Y18: CN | Z18: ¥3,500 | AA18: =IF(U18="",INDEX(Lookups!$J$3:$J$5,MATCH(E18,Lookups!$I$3:$I$5,0)),VALUE(LEFT(U18,FIND(" ",U18)-1))) -> 20 | AB18: =VALUE(LEFT(V18,FIND(" ",V18)-1)) -> 35
A19: 18 | B19: =T19&", "&S19 -> Liu, Fang | C19: February | D19: ="Q"&ROUNDUP(MATCH(C19,Lookups!$L$3:$L$14,0)/3,0) -> Q1 | E19: Electric Skateboard | F19: 101 Nanjing Road | G19: Shanghai | H19: 200001 | I19: =INDEX(Lookups!$B$3:$B$6,MATCH(Y19,Lookups!$A$3:$A$6,0)) -> China | J19: =INDEX(Lookups!$C$3:$C$6,MATCH(Y19,Lookups!$A$3:$A$6,0)) -> Asia | K19: =INDEX(Lookups!$D$3:$D$6,MATCH(Y19,Lookups!$A$3:$A$6,0)) -> CNY | L19: 4200 | M19: =ROUND(L19*INDEX(Lookups!$G$3:$G$5,MATCH(K19,Lookups!$F$3:$F$5,0)),0) -> 588 | N19: 850 | O19: 0 | P19: =ROUND(N19*M19*(1-O19/100),0) -> 499800 | Q19: =ROUND(AA19*Lookups!$O$3,0)&" - "&ROUND(AB19*Lookups!$O$3,0)&" km/h" -> 29 - 45 km/h | R19: =IF(ISNUMBER(SEARCH("meters",W19)),ROUND(VALUE(SUBSTITUTE(LEFT(W19,FIND(" ",W19)-1),",",""))/Lookups!$O$4,0),ROUND(VALUE(LEFT(W19,FIND(" ",W19)-1))*Lookups!$O$3,0)) -> 40 | S19: Fang | T19: Liu | U19: 18 mph | V19: 28 mph | W19: 25 miles | X19: 101 Nanjing Road, Shanghai, 200001 | Y19: CN | Z19: ¥4,200 | AA19: =IF(U19="",INDEX(Lookups!$J$3:$J$5,MATCH(E19,Lookups!$I$3:$I$5,0)),VALUE(LEFT(U19,FIND(" ",U19)-1))) -> 18 | AB19: =VALUE(LEFT(V19,FIND(" ",V19)-1)) -> 28
A20: 19 | B20: =T20&", "&S20 -> Fischer, Jonas | C20: February | D20: ="Q"&ROUNDUP(MATCH(C20,Lookups!$L$3:$L$14,0)/3,0) -> Q1 | E20: Electric Unicycle | F20: 303 Ringstraße | G20: Hamburg | H20: 20095 | I20: =INDEX(Lookups!$B$3:$B$6,MATCH(Y20,Lookups!$A$3:$A$6,0)) -> Germany | J20: =INDEX(Lookups!$C$3:$C$6,MATCH(Y20,Lookups!$A$3:$A$6,0)) -> Europe | K20: =INDEX(Lookups!$D$3:$D$6,MATCH(Y20,Lookups!$A$3:$A$6,0)) -> EUR | L20: 1000 | M20: =ROUND(L20*INDEX(Lookups!$G$3:$G$5,MATCH(K20,Lookups!$F$3:$F$5,0)),0) -> 1080 | N20: 130 | O20: 0 | P20: =ROUND(N20*M20*(1-O20/100),0) -> 140400 | Q20: =ROUND(AA20*Lookups!$O$3,0)&" - "&ROUND(AB20*Lookups!$O$3,0)&" km/h" -> 24 - 48 km/h | R20: =IF(ISNUMBER(SEARCH("meters",W20)),ROUND(VALUE(SUBSTITUTE(LEFT(W20,FIND(" ",W20)-1),",",""))/Lookups!$O$4,0),ROUND(VALUE(LEFT(W20,FIND(" ",W20)-1))*Lookups!$O$3,0)) -> 48 | S20: Jonas | T20: Fischer | U20: 15 mph | V20: 30 mph | W20: 30 miles | X20: 303 Ringstraße, Hamburg, 20095 | Y20: DE | Z20: €1000 | AA20: =IF(U20="",INDEX(Lookups!$J$3:$J$5,MATCH(E20,Lookups!$I$3:$I$5,0)),VALUE(LEFT(U20,FIND(" ",U20)-1))) -> 15 | AB20: =VALUE(LEFT(V20,FIND(" ",V20)-1)) -> 30
A21: 20 | B21: =T21&", "&S21 -> Fischer, Jonas | C21: February | D21: ="Q"&ROUNDUP(MATCH(C21,Lookups!$L$3:$L$14,0)/3,0) -> Q1 | E21: Electric Scooter | F21: 304 Ringstraße | G21: Hamburg | H21: 20095 | I21: =INDEX(Lookups!$B$3:$B$6,MATCH(Y21,Lookups!$A$3:$A$6,0)) -> Germany | J21: =INDEX(Lookups!$C$3:$C$6,MATCH(Y21,Lookups!$A$3:$A$6,0)) -> Europe | K21: =INDEX(Lookups!$D$3:$D$6,MATCH(Y21,Lookups!$A$3:$A$6,0)) -> EUR | L21: 800 | M21: =ROUND(L21*INDEX(Lookups!$G$3:$G$5,MATCH(K21,Lookups!$F$3:$F$5,0)),0) -> 864 | N21: 220 | O21: 0 | P21: =ROUND(N21*M21*(1-O21/100),0) -> 190080 | Q21: =ROUND(AA21*Lookups!$O$3,0)&" - "&ROUND(AB21*Lookups!$O$3,0)&" km/h" -> 32 - 56 km/h | R21: =IF(ISNUMBER(SEARCH("meters",W21)),ROUND(VALUE(SUBSTITUTE(LEFT(W21,FIND(" ",W21)-1),",",""))/Lookups!$O$4,0),ROUND(VALUE(LEFT(W21,FIND(" ",W21)-1))*Lookups!$O$3,0)) -> 64 | S21: Jonas | T21: Fischer | U21: 20 mph | V21: 35 mph | W21: 40 miles | X21: 304 Ringstraße, Hamburg, 20095 | Y21: DE | Z21: €800 | AA21: =IF(U21="",INDEX(Lookups!$J$3:$J$5,MATCH(E21,Lookups!$I$3:$I$5,0)),VALUE(LEFT(U21,FIND(" ",U21)-1))) -> 20 | AB21: =VALUE(LEFT(V21,FIND(" ",V21)-1)) -> 35
A22: 21 | B22: =T22&", "&S22 -> Fischer, Jonas | C22: February | D22: ="Q"&ROUNDUP(MATCH(C22,Lookups!$L$3:$L$14,0)/3,0) -> Q1 | E22: Electric Skateboard | F22: 305 Ringstraße | G22: Hamburg | H22: 20095 | I22: =INDEX(Lookups!$B$3:$B$6,MATCH(Y22,Lookups!$A$3:$A$6,0)) -> Germany | J22: =INDEX(Lookups!$C$3:$C$6,MATCH(Y22,Lookups!$A$3:$A$6,0)) -> Europe | K22: =INDEX(Lookups!$D$3:$D$6,MATCH(Y22,Lookups!$A$3:$A$6,0)) -> EUR | L22: 950 | M22: =ROUND(L22*INDEX(Lookups!$G$3:$G$5,MATCH(K22,Lookups!$F$3:$F$5,0)),0) -> 1026 | N22: 160 | O22: 0 | P22: =ROUND(N22*M22*(1-O22/100),0) -> 164160 | Q22: =ROUND(AA22*Lookups!$O$3,0)&" - "&ROUND(AB22*Lookups!$O$3,0)&" km/h" -> 29 - 45 km/h | R22: =IF(ISNUMBER(SEARCH("meters",W22)),ROUND(VALUE(SUBSTITUTE(LEFT(W22,FIND(" ",W22)-1),",",""))/Lookups!$O$4,0),ROUND(VALUE(LEFT(W22,FIND(" ",W22)-1))*Lookups!$O$3,0)) -> 40 | S22: Jonas | T22: Fischer | U22: 18 mph | V22: 28 mph | W22: 25 miles | X22: 305 Ringstraße, Hamburg, 20095 | Y22: DE | Z22: €950 | AA22: =IF(U22="",INDEX(Lookups!$J$3:$J$5,MATCH(E22,Lookups!$I$3:$I$5,0)),VALUE(LEFT(U22,FIND(" ",U22)-1))) -> 18 | AB22: =VALUE(LEFT(V22,FIND(" ",V22)-1)) -> 28
A23: 22 | B23: =T23&", "&S23 -> Bernard, Théo | C23: February | D23: ="Q"&ROUNDUP(MATCH(C23,Lookups!$L$3:$L$14,0)/3,0) -> Q1 | E23: Electric Unicycle | F23: 56 Boulevard Saint-Germain | G23: Paris | H23: 75005 | I23: =INDEX(Lookups!$B$3:$B$6,MATCH(Y23,Lookups!$A$3:$A$6,0)) -> France | J23: =INDEX(Lookups!$C$3:$C$6,MATCH(Y23,Lookups!$A$3:$A$6,0)) -> Europe | K23: =INDEX(Lookups!$D$3:$D$6,MATCH(Y23,Lookups!$A$3:$A$6,0)) -> EUR | L23: 1100 | M23: =ROUND(L23*INDEX(Lookups!$G$3:$G$5,MATCH(K23,Lookups!$F$3:$F$5,0)),0) -> 1188 | N23: 110 | O23: 0 | P23: =ROUND(N23*M23*(1-O23/100),0) -> 130680 | Q23: =ROUND(AA23*Lookups!$O$3,0)&" - "&ROUND(AB23*Lookups!$O$3,0)&" km/h" -> 24 - 48 km/h | R23: =IF(ISNUMBER(SEARCH("meters",W23)),ROUND(VALUE(SUBSTITUTE(LEFT(W23,FIND(" ",W23)-1),",",""))/Lookups!$O$4,0),ROUND(VALUE(LEFT(W23,FIND(" ",W23)-1))*Lookups!$O$3,0)) -> 48 | S23: Théo | T23: Bernard | U23: 15 mph | V23: 30 mph | W23: 30 miles | X23: 56 Boulevard Saint-Germain, Paris, 75005 | Y23: FR | Z23: €1100 | AA23: =IF(U23="",INDEX(Lookups!$J$3:$J$5,MATCH(E23,Lookups!$I$3:$I$5,0)),VALUE(LEFT(U23,FIND(" ",U23)-1))) -> 15 | AB23: =VALUE(LEFT(V23,FIND(" ",V23)-1)) -> 30
A24: 23 | B24: =T24&", "&S24 -> Bernard, Théo | C24: February | D24: ="Q"&ROUNDUP(MATCH(C24,Lookups!$L$3:$L$14,0)/3,0) -> Q1 | E24: Electric Scooter | F24: 57 Boulevard Saint-Germain | G24: Paris | H24: 75005 | I24: =INDEX(Lookups!$B$3:$B$6,MATCH(Y24,Lookups!$A$3:$A$6,0)) -> France | J24: =INDEX(Lookups!$C$3:$C$6,MATCH(Y24,Lookups!$A$3:$A$6,0)) -> Europe | K24: =INDEX(Lookups!$D$3:$D$6,MATCH(Y24,Lookups!$A$3:$A$6,0)) -> EUR | L24: 900 | M24: =ROUND(L24*INDEX(Lookups!$G$3:$G$5,MATCH(K24,Lookups!$F$3:$F$5,0)),0) -> 972 | N24: 260 | O24: 0 | P24: =ROUND(N24*M24*(1-O24/100),0) -> 252720 | Q24: =ROUND(AA24*Lookups!$O$3,0)&" - "&ROUND(AB24*Lookups!$O$3,0)&" km/h" -> 32 - 56 km/h | R24: =IF(ISNUMBER(SEARCH("meters",W24)),ROUND(VALUE(SUBSTITUTE(LEFT(W24,FIND(" ",W24)-1),",",""))/Lookups!$O$4,0),ROUND(VALUE(LEFT(W24,FIND(" ",W24)-1))*Lookups!$O$3,0)) -> 64 | S24: Théo | T24: Bernard | U24: 20 mph | V24: 35 mph | W24: 40 miles | X24: 57 Boulevard Saint-Germain, Paris, 75005 | Y24: FR | Z24: €900 | AA24: =IF(U24="",INDEX(Lookups!$J$3:$J$5,MATCH(E24,Lookups!$I$3:$I$5,0)),VALUE(LEFT(U24,FIND(" ",U24)-1))) -> 20 | AB24: =VALUE(LEFT(V24,FIND(" ",V24)-1)) -> 35
A25: 24 | B25: =T25&", "&S25 -> Bernard, Théo | C25: February | D25: ="Q"&ROUNDUP(MATCH(C25,Lookups!$L$3:$L$14,0)/3,0) -> Q1 | E25: Electric Skateboard | F25: 58 Boulevard Saint-Germain | G25: Paris | H25: 75005 | I25: =INDEX(Lookups!$B$3:$B$6,MATCH(Y25,Lookups!$A$3:$A$6,0)) -> France | J25: =INDEX(Lookups!$C$3:$C$6,MATCH(Y25,Lookups!$A$3:$A$6,0)) -> Europe | K25: =INDEX(Lookups!$D$3:$D$6,MATCH(Y25,Lookups!$A$3:$A$6,0)) -> EUR | L25: 1050 | M25: =ROUND(L25*INDEX(Lookups!$G$3:$G$5,MATCH(K25,Lookups!$F$3:$F$5,0)),0) -> 1134 | N25: 200 | O25: 0 | P25: =ROUND(N25*M25*(1-O25/100),0) -> 226800 | Q25: =ROUND(AA25*Lookups!$O$3,0)&" - "&ROUND(AB25*Lookups!$O$3,0)&" km/h" -> 29 - 45 km/h | R25: =IF(ISNUMBER(SEARCH("meters",W25)),ROUND(VALUE(SUBSTITUTE(LEFT(W25,FIND(" ",W25)-1),",",""))/Lookups!$O$4,0),ROUND(VALUE(LEFT(W25,FIND(" ",W25)-1))*Lookups!$O$3,0)) -> 40 | S25: Théo | T25: Bernard | U25: 18 mph | V25: 28 mph | W25: 40,230 meters | X25: 58 Boulevard Saint-Germain, Paris, 75005 | Y25: FR | Z25: €1050 | AA25: =IF(U25="",INDEX(Lookups!$J$3:$J$5,MATCH(E25,Lookups!$I$3:$I$5,0)),VALUE(LEFT(U25,FIND(" ",U25)-1))) -> 18 | AB25: =VALUE(LEFT(V25,FIND(" ",V25)-1)) -> 28
A26: 25 | B26: =T26&", "&S26 -> Joshi, Sanya | C26: March | D26: ="Q"&ROUNDUP(MATCH(C26,Lookups!$L$3:$L$14,0)/3,0) -> Q1 | E26: Electric Unicycle | F26: 456 Brigade Road | G26: Bengaluru | H26: 560001 | I26: =INDEX(Lookups!$B$3:$B$6,MATCH(Y26,Lookups!$A$3:$A$6,0)) -> India | J26: =INDEX(Lookups!$C$3:$C$6,MATCH(Y26,Lookups!$A$3:$A$6,0)) -> Asia | K26: =INDEX(Lookups!$D$3:$D$6,MATCH(Y26,Lookups!$A$3:$A$6,0)) -> INR | L26: 30000 | M26: =ROUND(L26*INDEX(Lookups!$G$3:$G$5,MATCH(K26,Lookups!$F$3:$F$5,0)),0) -> 360 | N26: 160 | O26: 0 | P26: =ROUND(N26*M26*(1-O26/100),0) -> 57600 | Q26: =ROUND(AA26*Lookups!$O$3,0)&" - "&ROUND(AB26*Lookups!$O$3,0)&" km/h" -> 24 - 48 km/h | R26: =IF(ISNUMBER(SEARCH("meters",W26)),ROUND(VALUE(SUBSTITUTE(LEFT(W26,FIND(" ",W26)-1),",",""))/Lookups!$O$4,0),ROUND(VALUE(LEFT(W26,FIND(" ",W26)-1))*Lookups!$O$3,0)) -> 48 | S26: Sanya | T26: Joshi | U26: 15 mph | V26: 30 mph | W26: 30 miles | X26: 456 Brigade Road, Bengaluru, 560001 | Y26: IN | Z26: ₹30,000 | AA26: =IF(U26="",INDEX(Lookups!$J$3:$J$5,MATCH(E26,Lookups!$I$3:$I$5,0)),VALUE(LEFT(U26,FIND(" ",U26)-1))) -> 15 | AB26: =VALUE(LEFT(V26,FIND(" ",V26)-1)) -> 30
A27: 26 | B27: =T27&", "&S27 -> Joshi, Sanya | C27: March | D27: ="Q"&ROUNDUP(MATCH(C27,Lookups!$L$3:$L$14,0)/3,0) -> Q1 | E27: Electric Scooter | F27: 457 Brigade Road | G27: Bengaluru | H27: 560001 | I27: =INDEX(Lookups!$B$3:$B$6,MATCH(Y27,Lookups!$A$3:$A$6,0)) -> India | J27: =INDEX(Lookups!$C$3:$C$6,MATCH(Y27,Lookups!$A$3:$A$6,0)) -> Asia | K27: =INDEX(Lookups!$D$3:$D$6,MATCH(Y27,Lookups!$A$3:$A$6,0)) -> INR | L27: 25000 | M27: =ROUND(L27*INDEX(Lookups!$G$3:$G$5,MATCH(K27,Lookups!$F$3:$F$5,0)),0) -> 300 | N27: 350 | O27: 0 | P27: =ROUND(N27*M27*(1-O27/100),0) -> 105000 | Q27: =ROUND(AA27*Lookups!$O$3,0)&" - "&ROUND(AB27*Lookups!$O$3,0)&" km/h" -> 32 - 56 km/h | R27: =IF(ISNUMBER(SEARCH("meters",W27)),ROUND(VALUE(SUBSTITUTE(LEFT(W27,FIND(" ",W27)-1),",",""))/Lookups!$O$4,0),ROUND(VALUE(LEFT(W27,FIND(" ",W27)-1))*Lookups!$O$3,0)) -> 64 | S27: Sanya | T27: Joshi | V27: 35 mph | W27: 40 miles | X27: 457 Brigade Road, Bengaluru, 560001 | Y27: IN | Z27: ₹25,000 | AA27: =IF(U27="",INDEX(Lookups!$J$3:$J$5,MATCH(E27,Lookups!$I$3:$I$5,0)),VALUE(LEFT(U27,FIND(" ",U27)-1))) -> 20 | AB27: =VALUE(LEFT(V27,FIND(" ",V27)-1)) -> 35
A28: 27 | B28: =T28&", "&S28 -> Joshi, Sanya | C28: March | D28: ="Q"&ROUNDUP(MATCH(C28,Lookups!$L$3:$L$14,0)/3,0) -> Q1 | E28: Electric Skateboard | F28: 458 Brigade Road | G28: Bengaluru | H28: 560001 | I28: =INDEX(Lookups!$B$3:$B$6,MATCH(Y28,Lookups!$A$3:$A$6,0)) -> India | J28: =INDEX(Lookups!$C$3:$C$6,MATCH(Y28,Lookups!$A$3:$A$6,0)) -> Asia | K28: =INDEX(Lookups!$D$3:$D$6,MATCH(Y28,Lookups!$A$3:$A$6,0)) -> INR | L28: 22000 | M28: =ROUND(L28*INDEX(Lookups!$G$3:$G$5,MATCH(K28,Lookups!$F$3:$F$5,0)),0) -> 264 | N28: 220 | O28: 0 | P28: =ROUND(N28*M28*(1-O28/100),0) -> 58080 | Q28: =ROUND(AA28*Lookups!$O$3,0)&" - "&ROUND(AB28*Lookups!$O$3,0)&" km/h" -> 29 - 45 km/h | R28: =IF(ISNUMBER(SEARCH("meters",W28)),ROUND(VALUE(SUBSTITUTE(LEFT(W28,FIND(" ",W28)-1),",",""))/Lookups!$O$4,0),ROUND(VALUE(LEFT(W28,FIND(" ",W28)-1))*Lookups!$O$3,0)) -> 40 | S28: Sanya | T28: Joshi | U28: 18 mph | V28: 28 mph | W28: 25 miles | X28: 458 Brigade Road, Bengaluru, 560001 | Y28: IN | Z28: ₹22,000 | AA28: =IF(U28="",INDEX(Lookups!$J$3:$J$5,MATCH(E28,Lookups!$I$3:$I$5,0)),VALUE(LEFT(U28,FIND(" ",U28)-1))) -> 18 | AB28: =VALUE(LEFT(V28,FIND(" ",V28)-1)) -> 28
A29: 28 | B29: =T29&", "&S29 -> Liu, Fang | C29: March | D29: ="Q"&ROUNDUP(MATCH(C29,Lookups!$L$3:$L$14,0)/3,0) -> Q1 | E29: Electric Unicycle | F29: 99 Nanjing Road | G29: Shanghai | H29: 200001 | I29: =INDEX(Lookups!$B$3:$B$6,MATCH(Y29,Lookups!$A$3:$A$6,0)) -> China | J29: =INDEX(Lookups!$C$3:$C$6,MATCH(Y29,Lookups!$A$3:$A$6,0)) -> Asia | K29: =INDEX(Lookups!$D$3:$D$6,MATCH(Y29,Lookups!$A$3:$A$6,0)) -> CNY | L29: 5000 | M29: =ROUND(L29*INDEX(Lookups!$G$3:$G$5,MATCH(K29,Lookups!$F$3:$F$5,0)),0) -> 700 | N29: 550 | O29: 0 | P29: =ROUND(N29*M29*(1-O29/100),0) -> 385000 | Q29: =ROUND(AA29*Lookups!$O$3,0)&" - "&ROUND(AB29*Lookups!$O$3,0)&" km/h" -> 24 - 48 km/h | R29: =IF(ISNUMBER(SEARCH("meters",W29)),ROUND(VALUE(SUBSTITUTE(LEFT(W29,FIND(" ",W29)-1),",",""))/Lookups!$O$4,0),ROUND(VALUE(LEFT(W29,FIND(" ",W29)-1))*Lookups!$O$3,0)) -> 48 | S29: Fang | T29: Liu | U29: 15 mph | V29: 30 mph | W29: 30 miles | X29: 99 Nanjing Road, Shanghai, 200001 | Y29: CN | Z29: ¥5,000 | AA29: =IF(U29="",INDEX(Lookups!$J$3:$J$5,MATCH(E29,Lookups!$I$3:$I$5,0)),VALUE(LEFT(U29,FIND(" ",U29)-1))) -> 15 | AB29: =VALUE(LEFT(V29,FIND(" ",V29)-1)) -> 30
A30: 29 | B30: =T30&", "&S30 -> Liu, Fang | C30: March | D30: ="Q"&ROUNDUP(MATCH(C30,Lookups!$L$3:$L$14,0)/3,0) -> Q1 | E30: Electric Scooter | F30: 100 Nanjing Road | G30: Shanghai | H30: 200001 | I30: =INDEX(Lookups!$B$3:$B$6,MATCH(Y30,Lookups!$A$3:$A$6,0)) -> China | J30: =INDEX(Lookups!$C$3:$C$6,MATCH(Y30,Lookups!$A$3:$A$6,0)) -> Asia | K30: =INDEX(Lookups!$D$3:$D$6,MATCH(Y30,Lookups!$A$3:$A$6,0)) -> CNY | L30: 3500 | M30: =ROUND(L30*INDEX(Lookups!$G$3:$G$5,MATCH(K30,Lookups!$F$3:$F$5,0)),0) -> 490 | N30: 1200 | O30: 0 | P30: =ROUND(N30*M30*(1-O30/100),0) -> 588000 | Q30: =ROUND(AA30*Lookups!$O$3,0)&" - "&ROUND(AB30*Lookups!$O$3,0)&" km/h" -> 32 - 56 km/h | R30: =IF(ISNUMBER(SEARCH("meters",W30)),ROUND(VALUE(SUBSTITUTE(LEFT(W30,FIND(" ",W30)-1),",",""))/Lookups!$O$4,0),ROUND(VALUE(LEFT(W30,FIND(" ",W30)-1))*Lookups!$O$3,0)) -> 64 | S30: Fang | T30: Liu | U30: 20 mph | V30: 35 mph | W30: 64,370 meters | X30: 100 Nanjing Road, Shanghai, 200001 | Y30: CN | Z30: ¥3,500 | AA30: =IF(U30="",INDEX(Lookups!$J$3:$J$5,MATCH(E30,Lookups!$I$3:$I$5,0)),VALUE(LEFT(U30,FIND(" ",U30)-1))) -> 20 | AB30: =VALUE(LEFT(V30,FIND(" ",V30)-1)) -> 35
A31: 30 | B31: =T31&", "&S31 -> Liu, Fang | C31: March | D31: ="Q"&ROUNDUP(MATCH(C31,Lookups!$L$3:$L$14,0)/3,0) -> Q1 | E31: Electric Skateboard | F31: 101 Nanjing Road | G31: Shanghai | H31: 200001 | I31: =INDEX(Lookups!$B$3:$B$6,MATCH(Y31,Lookups!$A$3:$A$6,0)) -> China | J31: =INDEX(Lookups!$C$3:$C$6,MATCH(Y31,Lookups!$A$3:$A$6,0)) -> Asia | K31: =INDEX(Lookups!$D$3:$D$6,MATCH(Y31,Lookups!$A$3:$A$6,0)) -> CNY | L31: 4200 | M31: =ROUND(L31*INDEX(Lookups!$G$3:$G$5,MATCH(K31,Lookups!$F$3:$F$5,0)),0) -> 588 | N31: 850 | O31: 0 | P31: =ROUND(N31*M31*(1-O31/100),0) -> 499800 | Q31: =ROUND(AA31*Lookups!$O$3,0)&" - "&ROUND(AB31*Lookups!$O$3,0)&" km/h" -> 29 - 45 km/h | R31: =IF(ISNUMBER(SEARCH("meters",W31)),ROUND(VALUE(SUBSTITUTE(LEFT(W31,FIND(" ",W31)-1),",",""))/Lookups!$O$4,0),ROUND(VALUE(LEFT(W31,FIND(" ",W31)-1))*Lookups!$O$3,0)) -> 40 | S31: Fang | T31: Liu | U31: 18 mph | V31: 28 mph | W31: 25 miles | X31: 101 Nanjing Road, Shanghai, 200001 | Y31: CN | Z31: ¥4,200 | AA31: =IF(U31="",INDEX(Lookups!$J$3:$J$5,MATCH(E31,Lookups!$I$3:$I$5,0)),VALUE(LEFT(U31,FIND(" ",U31)-1))) -> 18 | AB31: =VALUE(LEFT(V31,FIND(" ",V31)-1)) -> 28
A32: 31 | B32: =T32&", "&S32 -> Fischer, Jonas | C32: March | D32: ="Q"&ROUNDUP(MATCH(C32,Lookups!$L$3:$L$14,0)/3,0) -> Q1 | E32: Electric Unicycle | F32: 303 Ringstraße | G32: Hamburg | H32: 20095 | I32: =INDEX(Lookups!$B$3:$B$6,MATCH(Y32,Lookups!$A$3:$A$6,0)) -> Germany | J32: =INDEX(Lookups!$C$3:$C$6,MATCH(Y32,Lookups!$A$3:$A$6,0)) -> Europe | K32: =INDEX(Lookups!$D$3:$D$6,MATCH(Y32,Lookups!$A$3:$A$6,0)) -> EUR | L32: 1000 | M32: =ROUND(L32*INDEX(Lookups!$G$3:$G$5,MATCH(K32,Lookups!$F$3:$F$5,0)),0) -> 1080 | N32: 130 | O32: 0 | P32: =ROUND(N32*M32*(1-O32/100),0) -> 140400 | Q32: =ROUND(AA32*Lookups!$O$3,0)&" - "&ROUND(AB32*Lookups!$O$3,0)&" km/h" -> 24 - 48 km/h | R32: =IF(ISNUMBER(SEARCH("meters",W32)),ROUND(VALUE(SUBSTITUTE(LEFT(W32,FIND(" ",W32)-1),",",""))/Lookups!$O$4,0),ROUND(VALUE(LEFT(W32,FIND(" ",W32)-1))*Lookups!$O$3,0)) -> 48 | S32: Jonas | T32: Fischer | U32: 15 mph | V32: 30 mph | W32: 30 miles | X32: 303 Ringstraße, Hamburg, 20095 | Y32: DE | Z32: €1000 | AA32: =IF(U32="",INDEX(Lookups!$J$3:$J$5,MATCH(E32,Lookups!$I$3:$I$5,0)),VALUE(LEFT(U32,FIND(" ",U32)-1))) -> 15 | AB32: =VALUE(LEFT(V32,FIND(" ",V32)-1)) -> 30
A33: 32 | B33: =T33&", "&S33 -> Fischer, Jonas | C33: March | D33: ="Q"&ROUNDUP(MATCH(C33,Lookups!$L$3:$L$14,0)/3,0) -> Q1 | E33: Electric Scooter | F33: 304 Ringstraße | G33: Hamburg | H33: 20095 | I33: =INDEX(Lookups!$B$3:$B$6,MATCH(Y33,Lookups!$A$3:$A$6,0)) -> Germany | J33: =INDEX(Lookups!$C$3:$C$6,MATCH(Y33,Lookups!$A$3:$A$6,0)) -> Europe | K33: =INDEX(Lookups!$D$3:$D$6,MATCH(Y33,Lookups!$A$3:$A$6,0)) -> EUR | L33: 800 | M33: =ROUND(L33*INDEX(Lookups!$G$3:$G$5,MATCH(K33,Lookups!$F$3:$F$5,0)),0) -> 864 | N33: 220 | O33: 0 | P33: =ROUND(N33*M33*(1-O33/100),0) -> 190080 | Q33: =ROUND(AA33*Lookups!$O$3,0)&" - "&ROUND(AB33*Lookups!$O$3,0)&" km/h" -> 32 - 56 km/h | R33: =IF(ISNUMBER(SEARCH("meters",W33)),ROUND(VALUE(SUBSTITUTE(LEFT(W33,FIND(" ",W33)-1),",",""))/Lookups!$O$4,0),ROUND(VALUE(LEFT(W33,FIND(" ",W33)-1))*Lookups!$O$3,0)) -> 64 | S33: Jonas | T33: Fischer | U33: 20 mph | V33: 35 mph | W33: 40 miles | X33: 304 Ringstraße, Hamburg, 20095 | Y33: DE | Z33: €800 | AA33: =IF(U33="",INDEX(Lookups!$J$3:$J$5,MATCH(E33,Lookups!$I$3:$I$5,0)),VALUE(LEFT(U33,FIND(" ",U33)-1))) -> 20 | AB33: =VALUE(LEFT(V33,FIND(" ",V33)-1)) -> 35
A34: 33 | B34: =T34&", "&S34 -> Fischer, Jonas | C34: March | D34: ="Q"&ROUNDUP(MATCH(C34,Lookups!$L$3:$L$14,0)/3,0) -> Q1 | E34: Electric Skateboard | F34: 305 Ringstraße | G34: Hamburg | H34: 20095 | I34: =INDEX(Lookups!$B$3:$B$6,MATCH(Y34,Lookups!$A$3:$A$6,0)) -> Germany | J34: =INDEX(Lookups!$C$3:$C$6,MATCH(Y34,Lookups!$A$3:$A$6,0)) -> Europe | K34: =INDEX(Lookups!$D$3:$D$6,MATCH(Y34,Lookups!$A$3:$A$6,0)) -> EUR | L34: 950 | M34: =ROUND(L34*INDEX(Lookups!$G$3:$G$5,MATCH(K34,Lookups!$F$3:$F$5,0)),0) -> 1026 | N34: 160 | O34: 0 | P34: =ROUND(N34*M34*(1-O34/100),0) -> 164160 | Q34: =ROUND(AA34*Lookups!$O$3,0)&" - "&ROUND(AB34*Lookups!$O$3,0)&" km/h" -> 29 - 45 km/h | R34: =IF(ISNUMBER(SEARCH("meters",W34)),ROUND(VALUE(SUBSTITUTE(LEFT(W34,FIND(" ",W34)-1),",",""))/Lookups!$O$4,0),ROUND(VALUE(LEFT(W34,FIND(" ",W34)-1))*Lookups!$O$3,0)) -> 40 | S34: Jonas | T34: Fischer | U34: 18 mph | V34: 28 mph | W34: 25 miles | X34: 305 Ringstraße, Hamburg, 20095 | Y34: DE | Z34: €950 | AA34: =IF(U34="",INDEX(Lookups!$J$3:$J$5,MATCH(E34,Lookups!$I$3:$I$5,0)),VALUE(LEFT(U34,FIND(" ",U34)-1))) -> 18 | AB34: =VALUE(LEFT(V34,FIND(" ",V34)-1)) -> 28
A35: 34 | B35: =T35&", "&S35 -> Bernard, Théo | C35: March | D35: ="Q"&ROUNDUP(MATCH(C35,Lookups!$L$3:$L$14,0)/3,0) -> Q1 | E35: Electric Unicycle | F35: 56 Boulevard Saint-Germain | G35: Paris | H35: 75005 | I35: =INDEX(Lookups!$B$3:$B$6,MATCH(Y35,Lookups!$A$3:$A$6,0)) -> France | J35: =INDEX(Lookups!$C$3:$C$6,MATCH(Y35,Lookups!$A$3:$A$6,0)) -> Europe | K35: =INDEX(Lookups!$D$3:$D$6,MATCH(Y35,Lookups!$A$3:$A$6,0)) -> EUR | L35: 1100 | M35: =ROUND(L35*INDEX(Lookups!$G$3:$G$5,MATCH(K35,Lookups!$F$3:$F$5,0)),0) -> 1188 | N35: 110 | O35: 0 | P35: =ROUND(N35*M35*(1-O35/100),0) -> 130680 | Q35: =ROUND(AA35*Lookups!$O$3,0)&" - "&ROUND(AB35*Lookups!$O$3,0)&" km/h" -> 24 - 48 km/h | R35: =IF(ISNUMBER(SEARCH("meters",W35)),ROUND(VALUE(SUBSTITUTE(LEFT(W35,FIND(" ",W35)-1),",",""))/Lookups!$O$4,0),ROUND(VALUE(LEFT(W35,FIND(" ",W35)-1))*Lookups!$O$3,0)) -> 48 | S35: Théo | T35: Bernard | U35: 15 mph | V35: 30 mph | W35: 48,280 meters | X35: 56 Boulevard Saint-Germain, Paris, 75005 | Y35: FR | Z35: €1100 | AA35: =IF(U35="",INDEX(Lookups!$J$3:$J$5,MATCH(E35,Lookups!$I$3:$I$5,0)),VALUE(LEFT(U35,FIND(" ",U35)-1))) -> 15 | AB35: =VALUE(LEFT(V35,FIND(" ",V35)-1)) -> 30
A36: 35 | B36: =T36&", "&S36 -> Bernard, Théo | C36: March | D36: ="Q"&ROUNDUP(MATCH(C36,Lookups!$L$3:$L$14,0)/3,0) -> Q1 | E36: Electric Scooter | F36: 57 Boulevard Saint-Germain | G36: Paris | H36: 75005 | I36: =INDEX(Lookups!$B$3:$B$6,MATCH(Y36,Lookups!$A$3:$A$6,0)) -> France | J36: =INDEX(Lookups!$C$3:$C$6,MATCH(Y36,Lookups!$A$3:$A$6,0)) -> Europe | K36: =INDEX(Lookups!$D$3:$D$6,MATCH(Y36,Lookups!$A$3:$A$6,0)) -> EUR | L36: 900 | M36: =ROUND(L36*INDEX(Lookups!$G$3:$G$5,MATCH(K36,Lookups!$F$3:$F$5,0)),0) -> 972 | N36: 260 | O36: 0 | P36: =ROUND(N36*M36*(1-O36/100),0) -> 252720 | Q36: =ROUND(AA36*Lookups!$O$3,0)&" - "&ROUND(AB36*Lookups!$O$3,0)&" km/h" -> 32 - 56 km/h | R36: =IF(ISNUMBER(SEARCH("meters",W36)),ROUND(VALUE(SUBSTITUTE(LEFT(W36,FIND(" ",W36)-1),",",""))/Lookups!$O$4,0),ROUND(VALUE(LEFT(W36,FIND(" ",W36)-1))*Lookups!$O$3,0)) -> 64 | S36: Théo | T36: Bernard | U36: 20 mph | V36: 35 mph | W36: 40 miles | X36: 57 Boulevard Saint-Germain, Paris, 75005 | Y36: FR | Z36: €900 | AA36: =IF(U36="",INDEX(Lookups!$J$3:$J$5,MATCH(E36,Lookups!$I$3:$I$5,0)),VALUE(LEFT(U36,FIND(" ",U36)-1))) -> 20 | AB36: =VALUE(LEFT(V36,FIND(" ",V36)-1)) -> 35
A37: 36 | B37: =T37&", "&S37 -> Bernard, Théo | C37: March | D37: ="Q"&ROUNDUP(MATCH(C37,Lookups!$L$3:$L$14,0)/3,0) -> Q1 | E37: Electric Skateboard | F37: 58 Boulevard Saint-Germain | G37: Paris | H37: 75005 | I37: =INDEX(Lookups!$B$3:$B$6,MATCH(Y37,Lookups!$A$3:$A$6,0)) -> France | J37: =INDEX(Lookups!$C$3:$C$6,MATCH(Y37,Lookups!$A$3:$A$6,0)) -> Europe | K37: =INDEX(Lookups!$D$3:$D$6,MATCH(Y37,Lookups!$A$3:$A$6,0)) -> EUR | L37: 1050 | M37: =ROUND(L37*INDEX(Lookups!$G$3:$G$5,MATCH(K37,Lookups!$F$3:$F$5,0)),0) -> 1134 | N37: 200 | O37: 0 | P37: =ROUND(N37*M37*(1-O37/100),0) -> 226800 | Q37: =ROUND(AA37*Lookups!$O$3,0)&" - "&ROUND(AB37*Lookups!$O$3,0)&" km/h" -> 29 - 45 km/h | R37: =IF(ISNUMBER(SEARCH("meters",W37)),ROUND(VALUE(SUBSTITUTE(LEFT(W37,FIND(" ",W37)-1),",",""))/Lookups!$O$4,0),ROUND(VALUE(LEFT(W37,FIND(" ",W37)-1))*Lookups!$O$3,0)) -> 40 | S37: Théo | T37: Bernard | U37: 18 mph | V37: 28 mph | W37: 25 miles | X37: 58 Boulevard Saint-Germain, Paris, 75005 | Y37: FR | Z37: €1050 | AA37: =IF(U37="",INDEX(Lookups!$J$3:$J$5,MATCH(E37,Lookups!$I$3:$I$5,0)),VALUE(LEFT(U37,FIND(" ",U37)-1))) -> 18 | AB37: =VALUE(LEFT(V37,FIND(" ",V37)-1)) -> 28
A38: 37 | B38: =T38&", "&S38 -> Joshi, Sanya | C38: April | D38: ="Q"&ROUNDUP(MATCH(C38,Lookups!$L$3:$L$14,0)/3,0) -> Q2 | E38: Electric Unicycle | F38: 456 Brigade Road | G38: Bengaluru | H38: 560001 | I38: =INDEX(Lookups!$B$3:$B$6,MATCH(Y38,Lookups!$A$3:$A$6,0)) -> India | J38: =INDEX(Lookups!$C$3:$C$6,MATCH(Y38,Lookups!$A$3:$A$6,0)) -> Asia | K38: =INDEX(Lookups!$D$3:$D$6,MATCH(Y38,Lookups!$A$3:$A$6,0)) -> INR | L38: 30000 | M38: =ROUND(L38*INDEX(Lookups!$G$3:$G$5,MATCH(K38,Lookups!$F$3:$F$5,0)),0) -> 360 | N38: 200 | O38: 0 | P38: =ROUND(N38*M38*(1-O38/100),0) -> 72000 | Q38: =ROUND(AA38*Lookups!$O$3,0)&" - "&ROUND(AB38*Lookups!$O$3,0)&" km/h" -> 24 - 48 km/h | R38: =IF(ISNUMBER(SEARCH("meters",W38)),ROUND(VALUE(SUBSTITUTE(LEFT(W38,FIND(" ",W38)-1),",",""))/Lookups!$O$4,0),ROUND(VALUE(LEFT(W38,FIND(" ",W38)-1))*Lookups!$O$3,0)) -> 48 | S38: Sanya | T38: Joshi | U38: 15 mph | V38: 30 mph | W38: 30 miles | X38: 456 Brigade Road, Bengaluru, 560001 | Y38: IN | Z38: ₹30,000 | AA38: =IF(U38="",INDEX(Lookups!$J$3:$J$5,MATCH(E38,Lookups!$I$3:$I$5,0)),VALUE(LEFT(U38,FIND(" ",U38)-1))) -> 15 | AB38: =VALUE(LEFT(V38,FIND(" ",V38)-1)) -> 30
A39: 38 | B39: =T39&", "&S39 -> Joshi, Sanya | C39: April | D39: ="Q"&ROUNDUP(MATCH(C39,Lookups!$L$3:$L$14,0)/3,0) -> Q2 | E39: Electric Scooter | F39: 457 Brigade Road | G39: Bengaluru | H39: 560001 | I39: =INDEX(Lookups!$B$3:$B$6,MATCH(Y39,Lookups!$A$3:$A$6,0)) -> India | J39: =INDEX(Lookups!$C$3:$C$6,MATCH(Y39,Lookups!$A$3:$A$6,0)) -> Asia | K39: =INDEX(Lookups!$D$3:$D$6,MATCH(Y39,Lookups!$A$3:$A$6,0)) -> INR | L39: 25000 | M39: =ROUND(L39*INDEX(Lookups!$G$3:$G$5,MATCH(K39,Lookups!$F$3:$F$5,0)),0) -> 300 | N39: 450 | O39: 0 | P39: =ROUND(N39*M39*(1-O39/100),0) -> 135000 | Q39: =ROUND(AA39*Lookups!$O$3,0)&" - "&ROUND(AB39*Lookups!$O$3,0)&" km/h" -> 32 - 56 km/h | R39: =IF(ISNUMBER(SEARCH("meters",W39)),ROUND(VALUE(SUBSTITUTE(LEFT(W39,FIND(" ",W39)-1),",",""))/Lookups!$O$4,0),ROUND(VALUE(LEFT(W39,FIND(" ",W39)-1))*Lookups!$O$3,0)) -> 64 | S39: Sanya | T39: Joshi | U39: 20 mph | V39: 35 mph | W39: 40 miles | X39: 457 Brigade Road, Bengaluru, 560001 | Y39: IN | Z39: ₹25,000 | AA39: =IF(U39="",INDEX(Lookups!$J$3:$J$5,MATCH(E39,Lookups!$I$3:$I$5,0)),VALUE(LEFT(U39,FIND(" ",U39)-1))) -> 20 | AB39: =VALUE(LEFT(V39,FIND(" ",V39)-1)) -> 35
A40: 39 | B40: =T40&", "&S40 -> Joshi, Sanya | C40: April | D40: ="Q"&ROUNDUP(MATCH(C40,Lookups!$L$3:$L$14,0)/3,0) -> Q2 | E40: Electric Skateboard | F40: 458 Brigade Road | G40: Bengaluru | H40: 560001 | I40: =INDEX(Lookups!$B$3:$B$6,MATCH(Y40,Lookups!$A$3:$A$6,0)) -> India | J40: =INDEX(Lookups!$C$3:$C$6,MATCH(Y40,Lookups!$A$3:$A$6,0)) -> Asia | K40: =INDEX(Lookups!$D$3:$D$6,MATCH(Y40,Lookups!$A$3:$A$6,0)) -> INR | L40: 22000 | M40: =ROUND(L40*INDEX(Lookups!$G$3:$G$5,MATCH(K40,Lookups!$F$3:$F$5,0)),0) -> 264 | N40: 300 | O40: 0 | P40: =ROUND(N40*M40*(1-O40/100),0) -> 79200 | Q40: =ROUND(AA40*Lookups!$O$3,0)&" - "&ROUND(AB40*Lookups!$O$3,0)&" km/h" -> 29 - 45 km/h | R40: =IF(ISNUMBER(SEARCH("meters",W40)),ROUND(VALUE(SUBSTITUTE(LEFT(W40,FIND(" ",W40)-1),",",""))/Lookups!$O$4,0),ROUND(VALUE(LEFT(W40,FIND(" ",W40)-1))*Lookups!$O$3,0)) -> 40 | S40: Sanya | T40: Joshi | U40: 18 mph | V40: 28 mph | W40: 25 miles | X40: 458 Brigade Road, Bengaluru, 560001 | Y40: IN | Z40: ₹22,000 | AA40: =IF(U40="",INDEX(Lookups!$J$3:$J$5,MATCH(E40,Lookups!$I$3:$I$5,0)),VALUE(LEFT(U40,FIND(" ",U40)-1))) -> 18 | AB40: =VALUE(LEFT(V40,FIND(" ",V40)-1)) -> 28
A41: 40 | B41: =T41&", "&S41 -> Liu, Fang | C41: April | D41: ="Q"&ROUNDUP(MATCH(C41,Lookups!$L$3:$L$14,0)/3,0) -> Q2 | E41: Electric Unicycle | F41: 99 Nanjing Road | G41: Shanghai | H41: 200001 | I41: =INDEX(Lookups!$B$3:$B$6,MATCH(Y41,Lookups!$A$3:$A$6,0)) -> China | J41: =INDEX(Lookups!$C$3:$C$6,MATCH(Y41,Lookups!$A$3:$A$6,0)) -> Asia | K41: =INDEX(Lookups!$D$3:$D$6,MATCH(Y41,Lookups!$A$3:$A$6,0)) -> CNY | L41: 5000 | M41: =ROUND(L41*INDEX(Lookups!$G$3:$G$5,MATCH(K41,Lookups!$F$3:$F$5,0)),0) -> 700 | N41: 700 | O41: 0 | P41: =ROUND(N41*M41*(1-O41/100),0) -> 490000 | Q41: =ROUND(AA41*Lookups!$O$3,0)&" - "&ROUND(AB41*Lookups!$O$3,0)&" km/h" -> 24 - 48 km/h | R41: =IF(ISNUMBER(SEARCH("meters",W41)),ROUND(VALUE(SUBSTITUTE(LEFT(W41,FIND(" ",W41)-1),",",""))/Lookups!$O$4,0),ROUND(VALUE(LEFT(W41,FIND(" ",W41)-1))*Lookups!$O$3,0)) -> 48 | S41: Fang | T41: Liu | V41: 30 mph | W41: 30 miles | X41: 99 Nanjing Road, Shanghai, 200001 | Y41: CN | Z41: ¥5,000 | AA41: =IF(U41="",INDEX(Lookups!$J$3:$J$5,MATCH(E41,Lookups!$I$3:$I$5,0)),VALUE(LEFT(U41,FIND(" ",U41)-1))) -> 15 | AB41: =VALUE(LEFT(V41,FIND(" ",V41)-1)) -> 30
A42: 41 | B42: =T42&", "&S42 -> Liu, Fang | C42: April | D42: ="Q"&ROUNDUP(MATCH(C42,Lookups!$L$3:$L$14,0)/3,0) -> Q2 | E42: Electric Scooter | F42: 100 Nanjing Road | G42: Shanghai | H42: 200001 | I42: =INDEX(Lookups!$B$3:$B$6,MATCH(Y42,Lookups!$A$3:$A$6,0)) -> China | J42: =INDEX(Lookups!$C$3:$C$6,MATCH(Y42,Lookups!$A$3:$A$6,0)) -> Asia | K42: =INDEX(Lookups!$D$3:$D$6,MATCH(Y42,Lookups!$A$3:$A$6,0)) -> CNY | L42: 3500 | M42: =ROUND(L42*INDEX(Lookups!$G$3:$G$5,MATCH(K42,Lookups!$F$3:$F$5,0)),0) -> 490 | N42: 1600 | O42: 0 | P42: =ROUND(N42*M42*(1-O42/100),0) -> 784000 | Q42: =ROUND(AA42*Lookups!$O$3,0)&" - "&ROUND(AB42*Lookups!$O$3,0)&" km/h" -> 32 - 56 km/h | R42: =IF(ISNUMBER(SEARCH("meters",W42)),ROUND(VALUE(SUBSTITUTE(LEFT(W42,FIND(" ",W42)-1),",",""))/Lookups!$O$4,0),ROUND(VALUE(LEFT(W42,FIND(" ",W42)-1))*Lookups!$O$3,0)) -> 64 | S42: Fang | T42: Liu | U42: 20 mph | V42: 35 mph | W42: 40 miles | X42: 100 Nanjing Road, Shanghai, 200001 | Y42: CN | Z42: ¥3,500 | AA42: =IF(U42="",INDEX(Lookups!$J$3:$J$5,MATCH(E42,Lookups!$I$3:$I$5,0)),VALUE(LEFT(U42,FIND(" ",U42)-1))) -> 20 | AB42: =VALUE(LEFT(V42,FIND(" ",V42)-1)) -> 35
A43: 42 | B43: =T43&", "&S43 -> Liu, Fang | C43: April | D43: ="Q"&ROUNDUP(MATCH(C43,Lookups!$L$3:$L$14,0)/3,0) -> Q2 | E43: Electric Skateboard | F43: 101 Nanjing Road | G43: Shanghai | H43: 200001 | I43: =INDEX(Lookups!$B$3:$B$6,MATCH(Y43,Lookups!$A$3:$A$6,0)) -> China | J43: =INDEX(Lookups!$C$3:$C$6,MATCH(Y43,Lookups!$A$3:$A$6,0)) -> Asia | K43: =INDEX(Lookups!$D$3:$D$6,MATCH(Y43,Lookups!$A$3:$A$6,0)) -> CNY | L43: 4200 | M43: =ROUND(L43*INDEX(Lookups!$G$3:$G$5,MATCH(K43,Lookups!$F$3:$F$5,0)),0) -> 588 | N43: 1000 | O43: 0 | P43: =ROUND(N43*M43*(1-O43/100),0) -> 588000 | Q43: =ROUND(AA43*Lookups!$O$3,0)&" - "&ROUND(AB43*Lookups!$O$3,0)&" km/h" -> 29 - 45 km/h | R43: =IF(ISNUMBER(SEARCH("meters",W43)),ROUND(VALUE(SUBSTITUTE(LEFT(W43,FIND(" ",W43)-1),",",""))/Lookups!$O$4,0),ROUND(VALUE(LEFT(W43,FIND(" ",W43)-1))*Lookups!$O$3,0)) -> 40 | S43: Fang | T43: Liu | U43: 18 mph | V43: 28 mph | W43: 25 miles | X43: 101 Nanjing Road, Shanghai, 200001 | Y43: CN | Z43: ¥4,200 | AA43: =IF(U43="",INDEX(Lookups!$J$3:$J$5,MATCH(E43,Lookups!$I$3:$I$5,0)),VALUE(LEFT(U43,FIND(" ",U43)-1))) -> 18 | AB43: =VALUE(LEFT(V43,FIND(" ",V43)-1)) -> 28
A44: 43 | B44: =T44&", "&S44 -> Fischer, Jonas | C44: April | D44: ="Q"&ROUNDUP(MATCH(C44,Lookups!$L$3:$L$14,0)/3,0) -> Q2 | E44: Electric Unicycle | F44: 303 Ringstraße | G44: Hamburg | H44: 20095 | I44: =INDEX(Lookups!$B$3:$B$6,MATCH(Y44,Lookups!$A$3:$A$6,0)) -> Germany | J44: =INDEX(Lookups!$C$3:$C$6,MATCH(Y44,Lookups!$A$3:$A$6,0)) -> Europe | K44: =INDEX(Lookups!$D$3:$D$6,MATCH(Y44,Lookups!$A$3:$A$6,0)) -> EUR | L44: 1000 | M44: =ROUND(L44*INDEX(Lookups!$G$3:$G$5,MATCH(K44,Lookups!$F$3:$F$5,0)),0) -> 1080 | N44: 160 | O44: 0 | P44: =ROUND(N44*M44*(1-O44/100),0) -> 172800 | Q44: =ROUND(AA44*Lookups!$O$3,0)&" - "&ROUND(AB44*Lookups!$O$3,0)&" km/h" -> 24 - 48 km/h | R44: =IF(ISNUMBER(SEARCH("meters",W44)),ROUND(VALUE(SUBSTITUTE(LEFT(W44,FIND(" ",W44)-1),",",""))/Lookups!$O$4,0),ROUND(VALUE(LEFT(W44,FIND(" ",W44)-1))*Lookups!$O$3,0)) -> 48 | S44: Jonas | T44: Fischer | U44: 15 mph | V44: 30 mph | W44: 48,280 meters | X44: 303 Ringstraße, Hamburg, 20095 | Y44: DE | Z44: €1000 | AA44: =IF(U44="",INDEX(Lookups!$J$3:$J$5,MATCH(E44,Lookups!$I$3:$I$5,0)),VALUE(LEFT(U44,FIND(" ",U44)-1))) -> 15 | AB44: =VALUE(LEFT(V44,FIND(" ",V44)-1)) -> 30
A45: 44 | B45: =T45&", "&S45 -> Fischer, Jonas | C45: April | D45: ="Q"&ROUNDUP(MATCH(C45,Lookups!$L$3:$L$14,0)/3,0) -> Q2 | E45: Electric Scooter | F45: 304 Ringstraße | G45: Hamburg | H45: 20095 | I45: =INDEX(Lookups!$B$3:$B$6,MATCH(Y45,Lookups!$A$3:$A$6,0)) -> Germany | J45: =INDEX(Lookups!$C$3:$C$6,MATCH(Y45,Lookups!$A$3:$A$6,0)) -> Europe | K45: =INDEX(Lookups!$D$3:$D$6,MATCH(Y45,Lookups!$A$3:$A$6,0)) -> EUR | L45: 800 | M45: =ROUND(L45*INDEX(Lookups!$G$3:$G$5,MATCH(K45,Lookups!$F$3:$F$5,0)),0) -> 864 | N45: 280 | O45: 0 | P45: =ROUND(N45*M45*(1-O45/100),0) -> 241920 | Q45: =ROUND(AA45*Lookups!$O$3,0)&" - "&ROUND(AB45*Lookups!$O$3,0)&" km/h" -> 32 - 56 km/h | R45: =IF(ISNUMBER(SEARCH("meters",W45)),ROUND(VALUE(SUBSTITUTE(LEFT(W45,FIND(" ",W45)-1),",",""))/Lookups!$O$4,0),ROUND(VALUE(LEFT(W45,FIND(" ",W45)-1))*Lookups!$O$3,0)) -> 64 | S45: Jonas | T45: Fischer | U45: 20 mph | V45: 35 mph | W45: 40 miles | X45: 304 Ringstraße, Hamburg, 20095 | Y45: DE | Z45: €800 | AA45: =IF(U45="",INDEX(Lookups!$J$3:$J$5,MATCH(E45,Lookups!$I$3:$I$5,0)),VALUE(LEFT(U45,FIND(" ",U45)-1))) -> 20 | AB45: =VALUE(LEFT(V45,FIND(" ",V45)-1)) -> 35
A46: 45 | B46: =T46&", "&S46 -> Fischer, Jonas | C46: April | D46: ="Q"&ROUNDUP(MATCH(C46,Lookups!$L$3:$L$14,0)/3,0) -> Q2 | E46: Electric Skateboard | F46: 305 Ringstraße | G46: Hamburg | H46: 20095 | I46: =INDEX(Lookups!$B$3:$B$6,MATCH(Y46,Lookups!$A$3:$A$6,0)) -> Germany | J46: =INDEX(Lookups!$C$3:$C$6,MATCH(Y46,Lookups!$A$3:$A$6,0)) -> Europe | K46: =INDEX(Lookups!$D$3:$D$6,MATCH(Y46,Lookups!$A$3:$A$6,0)) -> EUR | L46: 950 | M46: =ROUND(L46*INDEX(Lookups!$G$3:$G$5,MATCH(K46,Lookups!$F$3:$F$5,0)),0) -> 1026 | N46: 200 | O46: 0 | P46: =ROUND(N46*M46*(1-O46/100),0) -> 205200 | Q46: =ROUND(AA46*Lookups!$O$3,0)&" - "&ROUND(AB46*Lookups!$O$3,0)&" km/h" -> 29 - 45 km/h | R46: =IF(ISNUMBER(SEARCH("meters",W46)),ROUND(VALUE(SUBSTITUTE(LEFT(W46,FIND(" ",W46)-1),",",""))/Lookups!$O$4,0),ROUND(VALUE(LEFT(W46,FIND(" ",W46)-1))*Lookups!$O$3,0)) -> 40 | S46: Jonas | T46: Fischer | U46: 18 mph | V46: 28 mph | W46: 25 miles | X46: 305 Ringstraße, Hamburg, 20095 | Y46: DE | Z46: €950 | AA46: =IF(U46="",INDEX(Lookups!$J$3:$J$5,MATCH(E46,Lookups!$I$3:$I$5,0)),VALUE(LEFT(U46,FIND(" ",U46)-1))) -> 18 | AB46: =VALUE(LEFT(V46,FIND(" ",V46)-1)) -> 28
A47: 46 | B47: =T47&", "&S47 -> Bernard, Théo | C47: April | D47: ="Q"&ROUNDUP(MATCH(C47,Lookups!$L$3:$L$14,0)/3,0) -> Q2 | E47: Electric Unicycle | F47: 56 Boulevard Saint-Germain | G47: Paris | H47: 75005 | I47: =INDEX(Lookups!$B$3:$B$6,MATCH(Y47,Lookups!$A$3:$A$6,0)) -> France | J47: =INDEX(Lookups!$C$3:$C$6,MATCH(Y47,Lookups!$A$3:$A$6,0)) -> Europe | K47: =INDEX(Lookups!$D$3:$D$6,MATCH(Y47,Lookups!$A$3:$A$6,0)) -> EUR | L47: 1100 | M47: =ROUND(L47*INDEX(Lookups!$G$3:$G$5,MATCH(K47,Lookups!$F$3:$F$5,0)),0) -> 1188 | N47: 130 | O47: 0 | P47: =ROUND(N47*M47*(1-O47/100),0) -> 154440 | Q47: =ROUND(AA47*Lookups!$O$3,0)&" - "&ROUND(AB47*Lookups!$O$3,0)&" km/h" -> 24 - 48 km/h | R47: =IF(ISNUMBER(SEARCH("meters",W47)),ROUND(VALUE(SUBSTITUTE(LEFT(W47,FIND(" ",W47)-1),",",""))/Lookups!$O$4,0),ROUND(VALUE(LEFT(W47,FIND(" ",W47)-1))*Lookups!$O$3,0)) -> 48 | S47: Théo | T47: Bernard | U47: 15 mph | V47: 30 mph | W47: 30 miles | X47: 56 Boulevard Saint-Germain, Paris, 75005 | Y47: FR | Z47: €1100 | AA47: =IF(U47="",INDEX(Lookups!$J$3:$J$5,MATCH(E47,Lookups!$I$3:$I$5,0)),VALUE(LEFT(U47,FIND(" ",U47)-1))) -> 15 | AB47: =VALUE(LEFT(V47,FIND(" ",V47)-1)) -> 30
A48: 47 | B48: =T48&", "&S48 -> Bernard, Théo | C48: April | D48: ="Q"&ROUNDUP(MATCH(C48,Lookups!$L$3:$L$14,0)/3,0) -> Q2 | E48: Electric Scooter | F48: 57 Boulevard Saint-Germain | G48: Paris | H48: 75005 | I48: =INDEX(Lookups!$B$3:$B$6,MATCH(Y48,Lookups!$A$3:$A$6,0)) -> France | J48: =INDEX(Lookups!$C$3:$C$6,MATCH(Y48,Lookups!$A$3:$A$6,0)) -> Europe | K48: =INDEX(Lookups!$D$3:$D$6,MATCH(Y48,Lookups!$A$3:$A$6,0)) -> EUR | L48: 900 | M48: =ROUND(L48*INDEX(Lookups!$G$3:$G$5,MATCH(K48,Lookups!$F$3:$F$5,0)),0) -> 972 | N48: 300 | O48: 0 | P48: =ROUND(N48*M48*(1-O48/100),0) -> 291600 | Q48: =ROUND(AA48*Lookups!$O$3,0)&" - "&ROUND(AB48*Lookups!$O$3,0)&" km/h" -> 32 - 56 km/h | R48: =IF(ISNUMBER(SEARCH("meters",W48)),ROUND(VALUE(SUBSTITUTE(LEFT(W48,FIND(" ",W48)-1),",",""))/Lookups!$O$4,0),ROUND(VALUE(LEFT(W48,FIND(" ",W48)-1))*Lookups!$O$3,0)) -> 64 | S48: Théo | T48: Bernard | U48: 20 mph | V48: 35 mph | W48: 40 miles | X48: 57 Boulevard Saint-Germain, Paris, 75005 | Y48: FR | Z48: €900 | AA48: =IF(U48="",INDEX(Lookups!$J$3:$J$5,MATCH(E48,Lookups!$I$3:$I$5,0)),VALUE(LEFT(U48,FIND(" ",U48)-1))) -> 20 | AB48: =VALUE(LEFT(V48,FIND(" ",V48)-1)) -> 35
A49: 48 | B49: =T49&", "&S49 -> Bernard, Théo | C49: April | D49: ="Q"&ROUNDUP(MATCH(C49,Lookups!$L$3:$L$14,0)/3,0) -> Q2 | E49: Electric Skateboard | F49: 58 Boulevard Saint-Germain | G49: Paris | H49: 75005 | I49: =INDEX(Lookups!$B$3:$B$6,MATCH(Y49,Lookups!$A$3:$A$6,0)) -> France | J49: =INDEX(Lookups!$C$3:$C$6,MATCH(Y49,Lookups!$A$3:$A$6,0)) -> Europe | K49: =INDEX(Lookups!$D$3:$D$6,MATCH(Y49,Lookups!$A$3:$A$6,0)) -> EUR | L49: 1050 | M49: =ROUND(L49*INDEX(Lookups!$G$3:$G$5,MATCH(K49,Lookups!$F$3:$F$5,0)),0) -> 1134 | N49: 230 | O49: 0 | P49: =ROUND(N49*M49*(1-O49/100),0) -> 260820 | Q49: =ROUND(AA49*Lookups!$O$3,0)&" - "&ROUND(AB49*Lookups!$O$3,0)&" km/h" -> 29 - 45 km/h | R49: =IF(ISNUMBER(SEARCH("meters",W49)),ROUND(VALUE(SUBSTITUTE(LEFT(W49,FIND(" ",W49)-1),",",""))/Lookups!$O$4,0),ROUND(VALUE(LEFT(W49,FIND(" ",W49)-1))*Lookups!$O$3,0)) -> 40 | S49: Théo | T49: Bernard | V49: 28 mph | W49: 40,230 meters | X49: 58 Boulevard Saint-Germain, Paris, 75005 | Y49: FR | Z49: €1050 | AA49: =IF(U49="",INDEX(Lookups!$J$3:$J$5,MATCH(E49,Lookups!$I$3:$I$5,0)),VALUE(LEFT(U49,FIND(" ",U49)-1))) -> 18 | AB49: =VALUE(LEFT(V49,FIND(" ",V49)-1)) -> 28
A50: 49 | B50: =T50&", "&S50 -> Joshi, Sanya | C50: May | D50: ="Q"&ROUNDUP(MATCH(C50,Lookups!$L$3:$L$14,0)/3,0) -> Q2 | E50: Electric Unicycle | F50: 456 Brigade Road | G50: Bengaluru | H50: 560001 | I50: =INDEX(Lookups!$B$3:$B$6,MATCH(Y50,Lookups!$A$3:$A$6,0)) -> India | J50: =INDEX(Lookups!$C$3:$C$6,MATCH(Y50,Lookups!$A$3:$A$6,0)) -> Asia | K50: =INDEX(Lookups!$D$3:$D$6,MATCH(Y50,Lookups!$A$3:$A$6,0)) -> INR | L50: 30000 | M50: =ROUND(L50*INDEX(Lookups!$G$3:$G$5,MATCH(K50,Lookups!$F$3:$F$5,0)),0) -> 360 | N50: 200 | O50: 0 | P50: =ROUND(N50*M50*(1-O50/100),0) -> 72000 | Q50: =ROUND(AA50*Lookups!$O$3,0)&" - "&ROUND(AB50*Lookups!$O$3,0)&" km/h" -> 24 - 48 km/h | R50: =IF(ISNUMBER(SEARCH("meters",W50)),ROUND(VALUE(SUBSTITUTE(LEFT(W50,FIND(" ",W50)-1),",",""))/Lookups!$O$4,0),ROUND(VALUE(LEFT(W50,FIND(" ",W50)-1))*Lookups!$O$3,0)) -> 48 | S50: Sanya | T50: Joshi | U50: 15 mph | V50: 30 mph | W50: 30 miles | X50: 456 Brigade Road, Bengaluru, 560001 | Y50: IN | Z50: ₹30,000 | AA50: =IF(U50="",INDEX(Lookups!$J$3:$J$5,MATCH(E50,Lookups!$I$3:$I$5,0)),VALUE(LEFT(U50,FIND(" ",U50)-1))) -> 15 | AB50: =VALUE(LEFT(V50,FIND(" ",V50)-1)) -> 30
A51: 50 | B51: =T51&", "&S51 -> Joshi, Sanya | C51: May | D51: ="Q"&ROUNDUP(MATCH(C51,Lookups!$L$3:$L$14,0)/3,0) -> Q2 | E51: Electric Scooter | F51: 457 Brigade Road | G51: Bengaluru | H51: 560001 | I51: =INDEX(Lookups!$B$3:$B$6,MATCH(Y51,Lookups!$A$3:$A$6,0)) -> India | J51: =INDEX(Lookups!$C$3:$C$6,MATCH(Y51,Lookups!$A$3:$A$6,0)) -> Asia | K51: =INDEX(Lookups!$D$3:$D$6,MATCH(Y51,Lookups!$A$3:$A$6,0)) -> INR | L51: 25000 | M51: =ROUND(L51*INDEX(Lookups!$G$3:$G$5,MATCH(K51,Lookups!$F$3:$F$5,0)),0) -> 300 | N51: 450 | O51: 0 | P51: =ROUND(N51*M51*(1-O51/100),0) -> 135000 | Q51: =ROUND(AA51*Lookups!$O$3,0)&" - "&ROUND(AB51*Lookups!$O$3,0)&" km/h" -> 32 - 56 km/h | R51: =IF(ISNUMBER(SEARCH("meters",W51)),ROUND(VALUE(SUBSTITUTE(LEFT(W51,FIND(" ",W51)-1),",",""))/Lookups!$O$4,0),ROUND(VALUE(LEFT(W51,FIND(" ",W51)-1))*Lookups!$O$3,0)) -> 64 | S51: Sanya | T51: Joshi | U51: 20 mph | V51: 35 mph | W51: 40 miles | X51: 457 Brigade Road, Bengaluru, 560001 | Y51: IN | Z51: ₹25,000 | AA51: =IF(U51="",INDEX(Lookups!$J$3:$J$5,MATCH(E51,Lookups!$I$3:$I$5,0)),VALUE(LEFT(U51,FIND(" ",U51)-1))) -> 20 | AB51: =VALUE(LEFT(V51,FIND(" ",V51)-1)) -> 35
A52: 51 | B52: =T52&", "&S52 -> Joshi, Sanya | C52: May | D52: ="Q"&ROUNDUP(MATCH(C52,Lookups!$L$3:$L$14,0)/3,0) -> Q2 | E52: Electric Skateboard | F52: 458 Brigade Road | G52: Bengaluru | H52: 560001 | I52: =INDEX(Lookups!$B$3:$B$6,MATCH(Y52,Lookups!$A$3:$A$6,0)) -> India | J52: =INDEX(Lookups!$C$3:$C$6,MATCH(Y52,Lookups!$A$3:$A$6,0)) -> Asia | K52: =INDEX(Lookups!$D$3:$D$6,MATCH(Y52,Lookups!$A$3:$A$6,0)) -> INR | L52: 22000 | M52: =ROUND(L52*INDEX(Lookups!$G$3:$G$5,MATCH(K52,Lookups!$F$3:$F$5,0)),0) -> 264 | N52: 350 | O52: 0 | P52: =ROUND(N52*M52*(1-O52/100),0) -> 92400 | Q52: =ROUND(AA52*Lookups!$O$3,0)&" - "&ROUND(AB52*Lookups!$O$3,0)&" km/h" -> 29 - 45 km/h | R52: =IF(ISNUMBER(SEARCH("meters",W52)),ROUND(VALUE(SUBSTITUTE(LEFT(W52,FIND(" ",W52)-1),",",""))/Lookups!$O$4,0),ROUND(VALUE(LEFT(W52,FIND(" ",W52)-1))*Lookups!$O$3,0)) -> 40 | S52: Sanya | T52: Joshi | U52: 18 mph | V52: 28 mph | W52: 25 miles | X52: 458 Brigade Road, Bengaluru, 560001 | Y52: IN | Z52: ₹22,000 | AA52: =IF(U52="",INDEX(Lookups!$J$3:$J$5,MATCH(E52,Lookups!$I$3:$I$5,0)),VALUE(LEFT(U52,FIND(" ",U52)-1))) -> 18 | AB52: =VALUE(LEFT(V52,FIND(" ",V52)-1)) -> 28
A53: 52 | B53: =T53&", "&S53 -> Liu, Fang | C53: May | D53: ="Q"&ROUNDUP(MATCH(C53,Lookups!$L$3:$L$14,0)/3,0) -> Q2 | E53: Electric Unicycle | F53: 99 Nanjing Road | G53: Shanghai | H53: 200001 | I53: =INDEX(Lookups!$B$3:$B$6,MATCH(Y53,Lookups!$A$3:$A$6,0)) -> China | J53: =INDEX(Lookups!$C$3:$C$6,MATCH(Y53,Lookups!$A$3:$A$6,0)) -> Asia | K53: =INDEX(Lookups!$D$3:$D$6,MATCH(Y53,Lookups!$A$3:$A$6,0)) -> CNY | L53: 5000 | M53: =ROUND(L53*INDEX(Lookups!$G$3:$G$5,MATCH(K53,Lookups!$F$3:$F$5,0)),0) -> 700 | N53: 700 | O53: 0 | P53: =ROUND(N53*M53*(1-O53/100),0) -> 490000 | Q53: =ROUND(AA53*Lookups!$O$3,0)&" - "&ROUND(AB53*Lookups!$O$3,0)&" km/h" -> 24 - 48 km/h | R53: =IF(ISNUMBER(SEARCH("meters",W53)),ROUND(VALUE(SUBSTITUTE(LEFT(W53,FIND(" ",W53)-1),",",""))/Lookups!$O$4,0),ROUND(VALUE(LEFT(W53,FIND(" ",W53)-1))*Lookups!$O$3,0)) -> 48 | S53: Fang | T53: Liu | U53: 15 mph | V53: 30 mph | W53: 48,280 meters | X53: 99 Nanjing Road, Shanghai, 200001 | Y53: CN | Z53: ¥5,000 | AA53: =IF(U53="",INDEX(Lookups!$J$3:$J$5,MATCH(E53,Lookups!$I$3:$I$5,0)),VALUE(LEFT(U53,FIND(" ",U53)-1))) -> 15 | AB53: =VALUE(LEFT(V53,FIND(" ",V53)-1)) -> 30
A54: 53 | B54: =T54&", "&S54 -> Liu, Fang | C54: May | D54: ="Q"&ROUNDUP(MATCH(C54,Lookups!$L$3:$L$14,0)/3,0) -> Q2 | E54: Electric Scooter | F54: 100 Nanjing Road | G54: Shanghai | H54: 200001 | I54: =INDEX(Lookups!$B$3:$B$6,MATCH(Y54,Lookups!$A$3:$A$6,0)) -> China | J54: =INDEX(Lookups!$C$3:$C$6,MATCH(Y54,Lookups!$A$3:$A$6,0)) -> Asia | K54: =INDEX(Lookups!$D$3:$D$6,MATCH(Y54,Lookups!$A$3:$A$6,0)) -> CNY | L54: 3500 | M54: =ROUND(L54*INDEX(Lookups!$G$3:$G$5,MATCH(K54,Lookups!$F$3:$F$5,0)),0) -> 490 | N54: 1600 | O54: 0 | P54: =ROUND(N54*M54*(1-O54/100),0) -> 784000 | Q54: =ROUND(AA54*Lookups!$O$3,0)&" - "&ROUND(AB54*Lookups!$O$3,0)&" km/h" -> 32 - 56 km/h | R54: =IF(ISNUMBER(SEARCH("meters",W54)),ROUND(VALUE(SUBSTITUTE(LEFT(W54,FIND(" ",W54)-1),",",""))/Lookups!$O$4,0),ROUND(VALUE(LEFT(W54,FIND(" ",W54)-1))*Lookups!$O$3,0)) -> 64 | S54: Fang | T54: Liu | U54: 20 mph | V54: 35 mph | W54: 40 miles | X54: 100 Nanjing Road, Shanghai, 200001 | Y54: CN | Z54: ¥3,500 | AA54: =IF(U54="",INDEX(Lookups!$J$3:$J$5,MATCH(E54,Lookups!$I$3:$I$5,0)),VALUE(LEFT(U54,FIND(" ",U54)-1))) -> 20 | AB54: =VALUE(LEFT(V54,FIND(" ",V54)-1)) -> 35
A55: 54 | B55: =T55&", "&S55 -> Liu, Fang | C55: May | D55: ="Q"&ROUNDUP(MATCH(C55,Lookups!$L$3:$L$14,0)/3,0) -> Q2 | E55: Electric Skateboard | F55: 101 Nanjing Road | G55: Shanghai | H55: 200001 | I55: =INDEX(Lookups!$B$3:$B$6,MATCH(Y55,Lookups!$A$3:$A$6,0)) -> China | J55: =INDEX(Lookups!$C$3:$C$6,MATCH(Y55,Lookups!$A$3:$A$6,0)) -> Asia | K55: =INDEX(Lookups!$D$3:$D$6,MATCH(Y55,Lookups!$A$3:$A$6,0)) -> CNY | L55: 4200 | M55: =ROUND(L55*INDEX(Lookups!$G$3:$G$5,MATCH(K55,Lookups!$F$3:$F$5,0)),0) -> 588 | N55: 1000 | O55: 0 | P55: =ROUND(N55*M55*(1-O55/100),0) -> 588000 | Q55: =ROUND(AA55*Lookups!$O$3,0)&" - "&ROUND(AB55*Lookups!$O$3,0)&" km/h" -> 29 - 45 km/h | R55: =IF(ISNUMBER(SEARCH("meters",W55)),ROUND(VALUE(SUBSTITUTE(LEFT(W55,FIND(" ",W55)-1),",",""))/Lookups!$O$4,0),ROUND(VALUE(LEFT(W55,FIND(" ",W55)-1))*Lookups!$O$3,0)) -> 40 | S55: Fang | T55: Liu | U55: 18 mph | V55: 28 mph | W55: 25 miles | X55: 101 Nanjing Road, Shanghai, 200001 | Y55: CN | Z55: ¥4,200 | AA55: =IF(U55="",INDEX(Lookups!$J$3:$J$5,MATCH(E55,Lookups!$I$3:$I$5,0)),VALUE(LEFT(U55,FIND(" ",U55)-1))) -> 18 | AB55: =VALUE(LEFT(V55,FIND(" ",V55)-1)) -> 28
A56: 55 | B56: =T56&", "&S56 -> Fischer, Jonas | C56: May | D56: ="Q"&ROUNDUP(MATCH(C56,Lookups!$L$3:$L$14,0)/3,0) -> Q2 | E56: Electric Unicycle | F56: 303 Ringstraße | G56: Hamburg | H56: 20095 | I56: =INDEX(Lookups!$B$3:$B$6,MATCH(Y56,Lookups!$A$3:$A$6,0)) -> Germany | J56: =INDEX(Lookups!$C$3:$C$6,MATCH(Y56,Lookups!$A$3:$A$6,0)) -> Europe | K56: =INDEX(Lookups!$D$3:$D$6,MATCH(Y56,Lookups!$A$3:$A$6,0)) -> EUR | L56: 1000 | M56: =ROUND(L56*INDEX(Lookups!$G$3:$G$5,MATCH(K56,Lookups!$F$3:$F$5,0)),0) -> 1080 | N56: 180 | O56: 0 | P56: =ROUND(N56*M56*(1-O56/100),0) -> 194400 | Q56: =ROUND(AA56*Lookups!$O$3,0)&" - "&ROUND(AB56*Lookups!$O$3,0)&" km/h" -> 24 - 48 km/h | R56: =IF(ISNUMBER(SEARCH("meters",W56)),ROUND(VALUE(SUBSTITUTE(LEFT(W56,FIND(" ",W56)-1),",",""))/Lookups!$O$4,0),ROUND(VALUE(LEFT(W56,FIND(" ",W56)-1))*Lookups!$O$3,0)) -> 48 | S56: Jonas | T56: Fischer | U56: 15 mph | V56: 30 mph | W56: 30 miles | X56: 303 Ringstraße, Hamburg, 20095 | Y56: DE | Z56: €1000 | AA56: =IF(U56="",INDEX(Lookups!$J$3:$J$5,MATCH(E56,Lookups!$I$3:$I$5,0)),VALUE(LEFT(U56,FIND(" ",U56)-1))) -> 15 | AB56: =VALUE(LEFT(V56,FIND(" ",V56)-1)) -> 30
A57: 56 | B57: =T57&", "&S57 -> Fischer, Jonas | C57: May | D57: ="Q"&ROUNDUP(MATCH(C57,Lookups!$L$3:$L$14,0)/3,0) -> Q2 | E57: Electric Scooter | F57: 304 Ringstraße | G57: Hamburg | H57: 20095 | I57: =INDEX(Lookups!$B$3:$B$6,MATCH(Y57,Lookups!$A$3:$A$6,0)) -> Germany | J57: =INDEX(Lookups!$C$3:$C$6,MATCH(Y57,Lookups!$A$3:$A$6,0)) -> Europe | K57: =INDEX(Lookups!$D$3:$D$6,MATCH(Y57,Lookups!$A$3:$A$6,0)) -> EUR | L57: 800 | M57: =ROUND(L57*INDEX(Lookups!$G$3:$G$5,MATCH(K57,Lookups!$F$3:$F$5,0)),0) -> 864 | N57: 320 | O57: 0 | P57: =ROUND(N57*M57*(1-O57/100),0) -> 276480 | Q57: =ROUND(AA57*Lookups!$O$3,0)&" - "&ROUND(AB57*Lookups!$O$3,0)&" km/h" -> 32 - 56 km/h | R57: =IF(ISNUMBER(SEARCH("meters",W57)),ROUND(VALUE(SUBSTITUTE(LEFT(W57,FIND(" ",W57)-1),",",""))/Lookups!$O$4,0),ROUND(VALUE(LEFT(W57,FIND(" ",W57)-1))*Lookups!$O$3,0)) -> 64 | S57: Jonas | T57: Fischer | U57: 20 mph | V57: 35 mph | W57: 40 miles | X57: 304 Ringstraße, Hamburg, 20095 | Y57: DE | Z57: €800 | AA57: =IF(U57="",INDEX(Lookups!$J$3:$J$5,MATCH(E57,Lookups!$I$3:$I$5,0)),VALUE(LEFT(U57,FIND(" ",U57)-1))) -> 20 | AB57: =VALUE(LEFT(V57,FIND(" ",V57)-1)) -> 35
A58: 57 | B58: =T58&", "&S58 -> Fischer, Jonas | C58: May | D58: ="Q"&ROUNDUP(MATCH(C58,Lookups!$L$3:$L$14,0)/3,0) -> Q2 | E58: Electric Skateboard | F58: 305 Ringstraße | G58: Hamburg | H58: 20095 | I58: =INDEX(Lookups!$B$3:$B$6,MATCH(Y58,Lookups!$A$3:$A$6,0)) -> Germany | J58: =INDEX(Lookups!$C$3:$C$6,MATCH(Y58,Lookups!$A$3:$A$6,0)) -> Europe | K58: =INDEX(Lookups!$D$3:$D$6,MATCH(Y58,Lookups!$A$3:$A$6,0)) -> EUR | L58: 950 | M58: =ROUND(L58*INDEX(Lookups!$G$3:$G$5,MATCH(K58,Lookups!$F$3:$F$5,0)),0) -> 1026 | N58: 220 | O58: 0 | P58: =ROUND(N58*M58*(1-O58/100),0) -> 225720 | Q58: =ROUND(AA58*Lookups!$O$3,0)&" - "&ROUND(AB58*Lookups!$O$3,0)&" km/h" -> 29 - 45 km/h | R58: =IF(ISNUMBER(SEARCH("meters",W58)),ROUND(VALUE(SUBSTITUTE(LEFT(W58,FIND(" ",W58)-1),",",""))/Lookups!$O$4,0),ROUND(VALUE(LEFT(W58,FIND(" ",W58)-1))*Lookups!$O$3,0)) -> 40 | S58: Jonas | T58: Fischer | U58: 18 mph | V58: 28 mph | W58: 25 miles | X58: 305 Ringstraße, Hamburg, 20095 | Y58: DE | Z58: €950 | AA58: =IF(U58="",INDEX(Lookups!$J$3:$J$5,MATCH(E58,Lookups!$I$3:$I$5,0)),VALUE(LEFT(U58,FIND(" ",U58)-1))) -> 18 | AB58: =VALUE(LEFT(V58,FIND(" ",V58)-1)) -> 28
A59: 58 | B59: =T59&", "&S59 -> Bernard, Théo | C59: May | D59: ="Q"&ROUNDUP(MATCH(C59,Lookups!$L$3:$L$14,0)/3,0) -> Q2 | E59: Electric Unicycle | F59: 56 Boulevard Saint-Germain | G59: Paris | H59: 75005 | I59: =INDEX(Lookups!$B$3:$B$6,MATCH(Y59,Lookups!$A$3:$A$6,0)) -> France | J59: =INDEX(Lookups!$C$3:$C$6,MATCH(Y59,Lookups!$A$3:$A$6,0)) -> Europe | K59: =INDEX(Lookups!$D$3:$D$6,MATCH(Y59,Lookups!$A$3:$A$6,0)) -> EUR | L59: 1100 | M59: =ROUND(L59*INDEX(Lookups!$G$3:$G$5,MATCH(K59,Lookups!$F$3:$F$5,0)),0) -> 1188 | N59: 140 | O59: 0 | P59: =ROUND(N59*M59*(1-O59/100),0) -> 166320 | Q59: =ROUND(AA59*Lookups!$O$3,0)&" - "&ROUND(AB59*Lookups!$O$3,0)&" km/h" -> 24 - 48 km/h | R59: =IF(ISNUMBER(SEARCH("meters",W59)),ROUND(VALUE(SUBSTITUTE(LEFT(W59,FIND(" ",W59)-1),",",""))/Lookups!$O$4,0),ROUND(VALUE(LEFT(W59,FIND(" ",W59)-1))*Lookups!$O$3,0)) -> 48 | S59: Théo | T59: Bernard | U59: 15 mph | V59: 30 mph | W59: 30 miles | X59: 56 Boulevard Saint-Germain, Paris, 75005 | Y59: FR | Z59: €1100 | AA59: =IF(U59="",INDEX(Lookups!$J$3:$J$5,MATCH(E59,Lookups!$I$3:$I$5,0)),VALUE(LEFT(U59,FIND(" ",U59)-1))) -> 15 | AB59: =VALUE(LEFT(V59,FIND(" ",V59)-1)) -> 30
A60: 59 | B60: =T60&", "&S60 -> Bernard, Théo | C60: May | D60: ="Q"&ROUNDUP(MATCH(C60,Lookups!$L$3:$L$14,0)/3,0) -> Q2 | E60: Electric Scooter | F60: 57 Boulevard Saint-Germain | G60: Paris | H60: 75005 | I60: =INDEX(Lookups!$B$3:$B$6,MATCH(Y60,Lookups!$A$3:$A$6,0)) -> France | J60: =INDEX(Lookups!$C$3:$C$6,MATCH(Y60,Lookups!$A$3:$A$6,0)) -> Europe | K60: =INDEX(Lookups!$D$3:$D$6,MATCH(Y60,Lookups!$A$3:$A$6,0)) -> EUR | L60: 900 | M60: =ROUND(L60*INDEX(Lookups!$G$3:$G$5,MATCH(K60,Lookups!$F$3:$F$5,0)),0) -> 972 | N60: 300 | O60: 0 | P60: =ROUND(N60*M60*(1-O60/100),0) -> 291600 | Q60: =ROUND(AA60*Lookups!$O$3,0)&" - "&ROUND(AB60*Lookups!$O$3,0)&" km/h" -> 32 - 56 km/h | R60: =IF(ISNUMBER(SEARCH("meters",W60)),ROUND(VALUE(SUBSTITUTE(LEFT(W60,FIND(" ",W60)-1),",",""))/Lookups!$O$4,0),ROUND(VALUE(LEFT(W60,FIND(" ",W60)-1))*Lookups!$O$3,0)) -> 64 | S60: Théo | T60: Bernard | U60: 20 mph | V60: 35 mph | W60: 64,370 meters | X60: 57 Boulevard Saint-Germain, Paris, 75005 | Y60: FR | Z60: €900 | AA60: =IF(U60="",INDEX(Lookups!$J$3:$J$5,MATCH(E60,Lookups!$I$3:$I$5,0)),VALUE(LEFT(U60,FIND(" ",U60)-1))) -> 20 | AB60: =VALUE(LEFT(V60,FIND(" ",V60)-1)) -> 35
A61: 60 | B61: =T61&", "&S61 -> Bernard, Théo | C61: May | D61: ="Q"&ROUNDUP(MATCH(C61,Lookups!$L$3:$L$14,0)/3,0) -> Q2 | E61: Electric Skateboard | F61: 58 Boulevard Saint-Germain | G61: Paris | H61: 75005 | I61: =INDEX(Lookups!$B$3:$B$6,MATCH(Y61,Lookups!$A$3:$A$6,0)) -> France | J61: =INDEX(Lookups!$C$3:$C$6,MATCH(Y61,Lookups!$A$3:$A$6,0)) -> Europe | K61: =INDEX(Lookups!$D$3:$D$6,MATCH(Y61,Lookups!$A$3:$A$6,0)) -> EUR | L61: 1050 | M61: =ROUND(L61*INDEX(Lookups!$G$3:$G$5,MATCH(K61,Lookups!$F$3:$F$5,0)),0) -> 1134 | N61: 280 | O61: 0 | P61: =ROUND(N61*M61*(1-O61/100),0) -> 317520 | Q61: =ROUND(AA61*Lookups!$O$3,0)&" - "&ROUND(AB61*Lookups!$O$3,0)&" km/h" -> 29 - 45 km/h | R61: =IF(ISNUMBER(SEARCH("meters",W61)),ROUND(VALUE(SUBSTITUTE(LEFT(W61,FIND(" ",W61)-1),",",""))/Lookups!$O$4,0),ROUND(VALUE(LEFT(W61,FIND(" ",W61)-1))*Lookups!$O$3,0)) -> 40 | S61: Théo | T61: Bernard | U61: 18 mph | V61: 28 mph | W61: 25 miles | X61: 58 Boulevard Saint-Germain, Paris, 75005 | Y61: FR | Z61: €1050 | AA61: =IF(U61="",INDEX(Lookups!$J$3:$J$5,MATCH(E61,Lookups!$I$3:$I$5,0)),VALUE(LEFT(U61,FIND(" ",U61)-1))) -> 18 | AB61: =VALUE(LEFT(V61,FIND(" ",V61)-1)) -> 28
... A63: 62 | B63: =T63&", "&S63 -> Joshi, Sanya | C63: June | D63: ="Q"&ROUNDUP(MATCH(C63,Lookups!$L$3:$L$14,0)/3,0) -> Q2 | E63: Electric Scooter | F63: 457 Brigade Road | G63: Bengaluru | H63: 560001 | I63: =INDEX(Lookups!$B$3:$B$6,MATCH(Y63,Lookups!$A$3:$A$6,0)) -> India | J63: =INDEX(Lookups!$C$3:$C$6,MATCH(Y63,Lookups!$A$3:$A$6,0)) -> Asia | K63: =INDEX(Lookups!$D$3:$D$6,MATCH(Y63,Lookups!$A$3:$A$6,0)) -> INR | L63: 25000 | M63: =ROUND(L63*INDEX(Lookups!$G$3:$G$5,MATCH(K63,Lookups!$F$3:$F$5,0)),0) -> 300 | N63: 500 | O63: 0 | P63: =ROUND(N63*M63*(1-O63/100),0) -> 150000 | Q63: =ROUND(AA63*Lookups!$O$3,0)&" - "&ROUND(AB63*Lookups!$O$3,0)&" km/h" -> 32 - 56 km/h | R63: =IF(ISNUMBER(SEARCH("meters",W63)),ROUND(VALUE(SUBSTITUTE(LEFT(W63,FIND(" ",W63)-1),",",""))/Lookups!$O$4,0),ROUND(VALUE(LEFT(W63,FIND(" ",W63)-1))*Lookups!$O$3,0)) -> 64 | S63: Sanya | T63: Joshi | U63: 20 mph | V63: 35 mph | W63: 40 miles | X63: 457 Brigade Road, Bengaluru, 560001 | Y63: IN | Z63: ₹25,000 | AA63: =IF(U63="",INDEX(Lookups!$J$3:$J$5,MATCH(E63,Lookups!$I$3:$I$5,0)),VALUE(LEFT(U63,FIND(" ",U63)-1))) -> 20 | AB63: =VALUE(LEFT(V63,FIND(" ",V63)-1)) -> 35
A64: 63 | B64: =T64&", "&S64 -> Joshi, Sanya | C64: June | D64: ="Q"&ROUNDUP(MATCH(C64,Lookups!$L$3:$L$14,0)/3,0) -> Q2 | E64: Electric Skateboard | F64: 458 Brigade Road | G64: Bengaluru | H64: 560001 | I64: =INDEX(Lookups!$B$3:$B$6,MATCH(Y64,Lookups!$A$3:$A$6,0)) -> India | J64: =INDEX(Lookups!$C$3:$C$6,MATCH(Y64,Lookups!$A$3:$A$6,0)) -> Asia | K64: =INDEX(Lookups!$D$3:$D$6,MATCH(Y64,Lookups!$A$3:$A$6,0)) -> INR | L64: 22000 | M64: =ROUND(L64*INDEX(Lookups!$G$3:$G$5,MATCH(K64,Lookups!$F$3:$F$5,0)),0) -> 264 | N64: 400 | O64: 0 | P64: =ROUND(N64*M64*(1-O64/100),0) -> 105600 | Q64: =ROUND(AA64*Lookups!$O$3,0)&" - "&ROUND(AB64*Lookups!$O$3,0)&" km/h" -> 29 - 45 km/h | R64: =IF(ISNUMBER(SEARCH("meters",W64)),ROUND(VALUE(SUBSTITUTE(LEFT(W64,FIND(" ",W64)-1),",",""))/Lookups!$O$4,0),ROUND(VALUE(LEFT(W64,FIND(" ",W64)-1))*Lookups!$O$3,0)) -> 40 | S64: Sanya | T64: Joshi | V64: 28 mph | W64: 25 miles | X64: 458 Brigade Road, Bengaluru, 560001 | Y64: IN | Z64: ₹22,000 | AA64: =IF(U64="",INDEX(Lookups!$J$3:$J$5,MATCH(E64,Lookups!$I$3:$I$5,0)),VALUE(LEFT(U64,FIND(" ",U64)-1))) -> 18 | AB64: =VALUE(LEFT(V64,FIND(" ",V64)-1)) -> 28
A65: 64 | B65: =T65&", "&S65 -> Liu, Fang | C65: June | D65: ="Q"&ROUNDUP(MATCH(C65,Lookups!$L$3:$L$14,0)/3,0) -> Q2 | E65: Electric Unicycle | F65: 99 Nanjing Road | G65: Shanghai | H65: 200001 | I65: =INDEX(Lookups!$B$3:$B$6,MATCH(Y65,Lookups!$A$3:$A$6,0)) -> China | J65: =INDEX(Lookups!$C$3:$C$6,MATCH(Y65,Lookups!$A$3:$A$6,0)) -> Asia | K65: =INDEX(Lookups!$D$3:$D$6,MATCH(Y65,Lookups!$A$3:$A$6,0)) -> CNY | L65: 5000 | M65: =ROUND(L65*INDEX(Lookups!$G$3:$G$5,MATCH(K65,Lookups!$F$3:$F$5,0)),0) -> 700 | N65: 800 | O65: 0 | P65: =ROUND(N65*M65*(1-O65/100),0) -> 560000 | Q65: =ROUND(AA65*Lookups!$O$3,0)&" - "&ROUND(AB65*Lookups!$O$3,0)&" km/h" -> 24 - 48 km/h | R65: =IF(ISNUMBER(SEARCH("meters",W65)),ROUND(VALUE(SUBSTITUTE(LEFT(W65,FIND(" ",W65)-1),",",""))/Lookups!$O$4,0),ROUND(VALUE(LEFT(W65,FIND(" ",W65)-1))*Lookups!$O$3,0)) -> 48 | S65: Fang | T65: Liu | U65: 15 mph | V65: 30 mph | W65: 30 miles | X65: 99 Nanjing Road, Shanghai, 200001 | Y65: CN | Z65: ¥5,000 | AA65: =IF(U65="",INDEX(Lookups!$J$3:$J$5,MATCH(E65,Lookups!$I$3:$I$5,0)),VALUE(LEFT(U65,FIND(" ",U65)-1))) -> 15 | AB65: =VALUE(LEFT(V65,FIND(" ",V65)-1)) -> 30
A66: 65 | B66: =T66&", "&S66 -> Liu, Fang | C66: June | D66: ="Q"&ROUNDUP(MATCH(C66,Lookups!$L$3:$L$14,0)/3,0) -> Q2 | E66: Electric Scooter | F66: 100 Nanjing Road | G66: Shanghai | H66: 200001 | I66: =INDEX(Lookups!$B$3:$B$6,MATCH(Y66,Lookups!$A$3:$A$6,0)) -> China | J66: =INDEX(Lookups!$C$3:$C$6,MATCH(Y66,Lookups!$A$3:$A$6,0)) -> Asia | K66: =INDEX(Lookups!$D$3:$D$6,MATCH(Y66,Lookups!$A$3:$A$6,0)) -> CNY | L66: 3500 | M66: =ROUND(L66*INDEX(Lookups!$G$3:$G$5,MATCH(K66,Lookups!$F$3:$F$5,0)),0) -> 490 | N66: 1900 | O66: 0 | P66: =ROUND(N66*M66*(1-O66/100),0) -> 931000 | Q66: =ROUND(AA66*Lookups!$O$3,0)&" - "&ROUND(AB66*Lookups!$O$3,0)&" km/h" -> 32 - 56 km/h | R66: =IF(ISNUMBER(SEARCH("meters",W66)),ROUND(VALUE(SUBSTITUTE(LEFT(W66,FIND(" ",W66)-1),",",""))/Lookups!$O$4,0),ROUND(VALUE(LEFT(W66,FIND(" ",W66)-1))*Lookups!$O$3,0)) -> 64 | S66: Fang | T66: Liu | U66: 20 mph | V66: 35 mph | W66: 40 miles | X66: 100 Nanjing Road, Shanghai, 200001 | Y66: CN | Z66: ¥3,500 | AA66: =IF(U66="",INDEX(Lookups!$J$3:$J$5,MATCH(E66,Lookups!$I$3:$I$5,0)),VALUE(LEFT(U66,FIND(" ",U66)-1))) -> 20 | AB66: =VALUE(LEFT(V66,FIND(" ",V66)-1)) -> 35
A67: 66 | B67: =T67&", "&S67 -> Liu, Fang | C67: June | D67: ="Q"&ROUNDUP(MATCH(C67,Lookups!$L$3:$L$14,0)/3,0) -> Q2 | E67: Electric Skateboard | F67: 101 Nanjing Road | G67: Shanghai | H67: 200001 | I67: =INDEX(Lookups!$B$3:$B$6,MATCH(Y67,Lookups!$A$3:$A$6,0)) -> China | J67: =INDEX(Lookups!$C$3:$C$6,MATCH(Y67,Lookups!$A$3:$A$6,0)) -> Asia | K67: =INDEX(Lookups!$D$3:$D$6,MATCH(Y67,Lookups!$A$3:$A$6,0)) -> CNY | L67: 4200 | M67: =ROUND(L67*INDEX(Lookups!$G$3:$G$5,MATCH(K67,Lookups!$F$3:$F$5,0)),0) -> 588 | N67: 1200 | O67: 0 | P67: =ROUND(N67*M67*(1-O67/100),0) -> 705600 | Q67: =ROUND(AA67*Lookups!$O$3,0)&" - "&ROUND(AB67*Lookups!$O$3,0)&" km/h" -> 29 - 45 km/h | R67: =IF(ISNUMBER(SEARCH("meters",W67)),ROUND(VALUE(SUBSTITUTE(LEFT(W67,FIND(" ",W67)-1),",",""))/Lookups!$O$4,0),ROUND(VALUE(LEFT(W67,FIND(" ",W67)-1))*Lookups!$O$3,0)) -> 40 | S67: Fang | T67: Liu | U67: 18 mph | V67: 28 mph | W67: 25 miles | X67: 101 Nanjing Road, Shanghai, 200001 | Y67: CN | Z67: ¥4,200 | AA67: =IF(U67="",INDEX(Lookups!$J$3:$J$5,MATCH(E67,Lookups!$I$3:$I$5,0)),VALUE(LEFT(U67,FIND(" ",U67)-1))) -> 18 | AB67: =VALUE(LEFT(V67,FIND(" ",V67)-1)) -> 28
A68: 67 | B68: =T68&", "&S68 -> Fischer, Jonas | C68: June | D68: ="Q"&ROUNDUP(MATCH(C68,Lookups!$L$3:$L$14,0)/3,0) -> Q2 | E68: Electric Unicycle | F68: 303 Ringstraße | G68: Hamburg | H68: 20095 | I68: =INDEX(Lookups!$B$3:$B$6,MATCH(Y68,Lookups!$A$3:$A$6,0)) -> Germany | J68: =INDEX(Lookups!$C$3:$C$6,MATCH(Y68,Lookups!$A$3:$A$6,0)) -> Europe | K68: =INDEX(Lookups!$D$3:$D$6,MATCH(Y68,Lookups!$A$3:$A$6,0)) -> EUR | L68: 1000 | M68: =ROUND(L68*INDEX(Lookups!$G$3:$G$5,MATCH(K68,Lookups!$F$3:$F$5,0)),0) -> 1080 | N68: 200 | O68: 0 | P68: =ROUND(N68*M68*(1-O68/100),0) -> 216000 | Q68: =ROUND(AA68*Lookups!$O$3,0)&" - "&ROUND(AB68*Lookups!$O$3,0)&" km/h" -> 24 - 48 km/h | R68: =IF(ISNUMBER(SEARCH("meters",W68)),ROUND(VALUE(SUBSTITUTE(LEFT(W68,FIND(" ",W68)-1),",",""))/Lookups!$O$4,0),ROUND(VALUE(LEFT(W68,FIND(" ",W68)-1))*Lookups!$O$3,0)) -> 48 | S68: Jonas | T68: Fischer | U68: 15 mph | V68: 30 mph | W68: 30 miles | X68: 303 Ringstraße, Hamburg, 20095 | Y68: DE | Z68: €1000 | AA68: =IF(U68="",INDEX(Lookups!$J$3:$J$5,MATCH(E68,Lookups!$I$3:$I$5,0)),VALUE(LEFT(U68,FIND(" ",U68)-1))) -> 15 | AB68: =VALUE(LEFT(V68,FIND(" ",V68)-1)) -> 30
A69: 68 | B69: =T69&", "&S69 -> Fischer, Jonas | C69: June | D69: ="Q"&ROUNDUP(MATCH(C69,Lookups!$L$3:$L$14,0)/3,0) -> Q2 | E69: Electric Scooter | F69: 304 Ringstraße | G69: Hamburg | H69: 20095 | I69: =INDEX(Lookups!$B$3:$B$6,MATCH(Y69,Lookups!$A$3:$A$6,0)) -> Germany | J69: =INDEX(Lookups!$C$3:$C$6,MATCH(Y69,Lookups!$A$3:$A$6,0)) -> Europe | K69: =INDEX(Lookups!$D$3:$D$6,MATCH(Y69,Lookups!$A$3:$A$6,0)) -> EUR | L69: 800 | M69: =ROUND(L69*INDEX(Lookups!$G$3:$G$5,MATCH(K69,Lookups!$F$3:$F$5,0)),0) -> 864 | N69: 350 | O69: 0 | P69: =ROUND(N69*M69*(1-O69/100),0) -> 302400 | Q69: =ROUND(AA69*Lookups!$O$3,0)&" - "&ROUND(AB69*Lookups!$O$3,0)&" km/h" -> 32 - 56 km/h | R69: =IF(ISNUMBER(SEARCH("meters",W69)),ROUND(VALUE(SUBSTITUTE(LEFT(W69,FIND(" ",W69)-1),",",""))/Lookups!$O$4,0),ROUND(VALUE(LEFT(W69,FIND(" ",W69)-1))*Lookups!$O$3,0)) -> 64 | S69: Jonas | T69: Fischer | U69: 20 mph | V69: 35 mph | W69: 64,370 meters | X69: 304 Ringstraße, Hamburg, 20095 | Y69: DE | Z69: €800 | AA69: =IF(U69="",INDEX(Lookups!$J$3:$J$5,MATCH(E69,Lookups!$I$3:$I$5,0)),VALUE(LEFT(U69,FIND(" ",U69)-1))) -> 20 | AB69: =VALUE(LEFT(V69,FIND(" ",V69)-1)) -> 35
A70: 69 | B70: =T70&", "&S70 -> Fischer, Jonas | C70: June | D70: ="Q"&ROUNDUP(MATCH(C70,Lookups!$L$3:$L$14,0)/3,0) -> Q2 | E70: Electric Skateboard | F70: 305 Ringstraße | G70: Hamburg | H70: 20095 | I70: =INDEX(Lookups!$B$3:$B$6,MATCH(Y70,Lookups!$A$3:$A$6,0)) -> Germany | J70: =INDEX(Lookups!$C$3:$C$6,MATCH(Y70,Lookups!$A$3:$A$6,0)) -> Europe | K70: =INDEX(Lookups!$D$3:$D$6,MATCH(Y70,Lookups!$A$3:$A$6,0)) -> EUR | L70: 950 | M70: =ROUND(L70*INDEX(Lookups!$G$3:$G$5,MATCH(K70,Lookups!$F$3:$F$5,0)),0) -> 1026 | N70: 250 | O70: 0 | P70: =ROUND(N70*M70*(1-O70/100),0) -> 256500 | Q70: =ROUND(AA70*Lookups!$O$3,0)&" - "&ROUND(AB70*Lookups!$O$3,0)&" km/h" -> 29 - 45 km/h | R70: =IF(ISNUMBER(SEARCH("meters",W70)),ROUND(VALUE(SUBSTITUTE(LEFT(W70,FIND(" ",W70)-1),",",""))/Lookups!$O$4,0),ROUND(VALUE(LEFT(W70,FIND(" ",W70)-1))*Lookups!$O$3,0)) -> 40 | S70: Jonas | T70: Fischer | U70: 18 mph | V70: 28 mph | W70: 40,230 meters | X70: 305 Ringstraße, Hamburg, 20095 | Y70: DE | Z70: €950 | AA70: =IF(U70="",INDEX(Lookups!$J$3:$J$5,MATCH(E70,Lookups!$I$3:$I$5,0)),VALUE(LEFT(U70,FIND(" ",U70)-1))) -> 18 | AB70: =VALUE(LEFT(V70,FIND(" ",V70)-1)) -> 28
A71: 70 | B71: =T71&", "&S71 -> Bernard, Théo | C71: June | D71: ="Q"&ROUNDUP(MATCH(C71,Lookups!$L$3:$L$14,0)/3,0) -> Q2 | E71: Electric Unicycle | F71: 56 Boulevard Saint-Germain | G71: Paris | H71: 75005 | I71: =INDEX(Lookups!$B$3:$B$6,MATCH(Y71,Lookups!$A$3:$A$6,0)) -> France | J71: =INDEX(Lookups!$C$3:$C$6,MATCH(Y71,Lookups!$A$3:$A$6,0)) -> Europe | K71: =INDEX(Lookups!$D$3:$D$6,MATCH(Y71,Lookups!$A$3:$A$6,0)) -> EUR | L71: 1100 | M71: =ROUND(L71*INDEX(Lookups!$G$3:$G$5,MATCH(K71,Lookups!$F$3:$F$5,0)),0) -> 1188 | N71: 150 | O71: 0 | P71: =ROUND(N71*M71*(1-O71/100),0) -> 178200 | Q71: =ROUND(AA71*Lookups!$O$3,0)&" - "&ROUND(AB71*Lookups!$O$3,0)&" km/h" -> 24 - 48 km/h | R71: =IF(ISNUMBER(SEARCH("meters",W71)),ROUND(VALUE(SUBSTITUTE(LEFT(W71,FIND(" ",W71)-1),",",""))/Lookups!$O$4,0),ROUND(VALUE(LEFT(W71,FIND(" ",W71)-1))*Lookups!$O$3,0)) -> 48 | S71: Théo | T71: Bernard | V71: 30 mph | W71: 30 miles | X71: 56 Boulevard Saint-Germain, Paris, 75005 | Y71: FR | Z71: €1100 | AA71: =IF(U71="",INDEX(Lookups!$J$3:$J$5,MATCH(E71,Lookups!$I$3:$I$5,0)),VALUE(LEFT(U71,FIND(" ",U71)-1))) -> 15 | AB71: =VALUE(LEFT(V71,FIND(" ",V71)-1)) -> 30
A72: 71 | B72: =T72&", "&S72 -> Bernard, Théo | C72: June | D72: ="Q"&ROUNDUP(MATCH(C72,Lookups!$L$3:$L$14,0)/3,0) -> Q2 | E72: Electric Scooter | F72: 57 Boulevard Saint-Germain | G72: Paris | H72: 75005 | I72: =INDEX(Lookups!$B$3:$B$6,MATCH(Y72,Lookups!$A$3:$A$6,0)) -> France | J72: =INDEX(Lookups!$C$3:$C$6,MATCH(Y72,Lookups!$A$3:$A$6,0)) -> Europe | K72: =INDEX(Lookups!$D$3:$D$6,MATCH(Y72,Lookups!$A$3:$A$6,0)) -> EUR | L72: 900 | M72: =ROUND(L72*INDEX(Lookups!$G$3:$G$5,MATCH(K72,Lookups!$F$3:$F$5,0)),0) -> 972 | N72: 350 | O72: 0 | P72: =ROUND(N72*M72*(1-O72/100),0) -> 340200 | Q72: =ROUND(AA72*Lookups!$O$3,0)&" - "&ROUND(AB72*Lookups!$O$3,0)&" km/h" -> 32 - 56 km/h | R72: =IF(ISNUMBER(SEARCH("meters",W72)),ROUND(VALUE(SUBSTITUTE(LEFT(W72,FIND(" ",W72)-1),",",""))/Lookups!$O$4,0),ROUND(VALUE(LEFT(W72,FIND(" ",W72)-1))*Lookups!$O$3,0)) -> 64 | S72: Théo | T72: Bernard | U72: 20 mph | V72: 35 mph | W72: 40 miles | X72: 57 Boulevard Saint-Germain, Paris, 75005 | Y72: FR | Z72: €900 | AA72: =IF(U72="",INDEX(Lookups!$J$3:$J$5,MATCH(E72,Lookups!$I$3:$I$5,0)),VALUE(LEFT(U72,FIND(" ",U72)-1))) -> 20 | AB72: =VALUE(LEFT(V72,FIND(" ",V72)-1)) -> 35
A73: 72 | B73: =T73&", "&S73 -> Bernard, Théo | C73: June | D73: ="Q"&ROUNDUP(MATCH(C73,Lookups!$L$3:$L$14,0)/3,0) -> Q2 | E73: Electric Skateboard | F73: 58 Boulevard Saint-Germain | G73: Paris | H73: 75005 | I73: =INDEX(Lookups!$B$3:$B$6,MATCH(Y73,Lookups!$A$3:$A$6,0)) -> France | J73: =INDEX(Lookups!$C$3:$C$6,MATCH(Y73,Lookups!$A$3:$A$6,0)) -> Europe | K73: =INDEX(Lookups!$D$3:$D$6,MATCH(Y73,Lookups!$A$3:$A$6,0)) -> EUR | L73: 1050 | M73: =ROUND(L73*INDEX(Lookups!$G$3:$G$5,MATCH(K73,Lookups!$F$3:$F$5,0)),0) -> 1134 | N73: 300 | O73: 0 | P73: =ROUND(N73*M73*(1-O73/100),0) -> 340200 | Q73: =ROUND(AA73*Lookups!$O$3,0)&" - "&ROUND(AB73*Lookups!$O$3,0)&" km/h" -> 29 - 45 km/h | R73: =IF(ISNUMBER(SEARCH("meters",W73)),ROUND(VALUE(SUBSTITUTE(LEFT(W73,FIND(" ",W73)-1),",",""))/Lookups!$O$4,0),ROUND(VALUE(LEFT(W73,FIND(" ",W73)-1))*Lookups!$O$3,0)) -> 40 | S73: Théo | T73: Bernard | U73: 18 mph | V73: 28 mph | W73: 25 miles | X73: 58 Boulevard Saint-Germain, Paris, 75005 | Y73: FR | Z73: €1050 | AA73: =IF(U73="",INDEX(Lookups!$J$3:$J$5,MATCH(E73,Lookups!$I$3:$I$5,0)),VALUE(LEFT(U73,FIND(" ",U73)-1))) -> 18 | AB73: =VALUE(LEFT(V73,FIND(" ",V73)-1)) -> 28
A74: 73 | B74: =T74&", "&S74 -> Joshi, Sanya | C74: July | D74: ="Q"&ROUNDUP(MATCH(C74,Lookups!$L$3:$L$14,0)/3,0) -> Q3 | E74: Electric Unicycle | F74: 456 Brigade Road | G74: Bengaluru | H74: 560001 | I74: =INDEX(Lookups!$B$3:$B$6,MATCH(Y74,Lookups!$A$3:$A$6,0)) -> India | J74: =INDEX(Lookups!$C$3:$C$6,MATCH(Y74,Lookups!$A$3:$A$6,0)) -> Asia | K74: =INDEX(Lookups!$D$3:$D$6,MATCH(Y74,Lookups!$A$3:$A$6,0)) -> INR | L74: 30000 | M74: =ROUND(L74*INDEX(Lookups!$G$3:$G$5,MATCH(K74,Lookups!$F$3:$F$5,0)),0) -> 360 | N74: 250 | O74: 0 | P74: =ROUND(N74*M74*(1-O74/100),0) -> 90000 | Q74: =ROUND(AA74*Lookups!$O$3,0)&" - "&ROUND(AB74*Lookups!$O$3,0)&" km/h" -> 24 - 48 km/h | R74: =IF(ISNUMBER(SEARCH("meters",W74)),ROUND(VALUE(SUBSTITUTE(LEFT(W74,FIND(" ",W74)-1),",",""))/Lookups!$O$4,0),ROUND(VALUE(LEFT(W74,FIND(" ",W74)-1))*Lookups!$O$3,0)) -> 48 | S74: Sanya | T74: Joshi | U74: 15 mph | V74: 30 mph | W74: 30 miles | X74: 456 Brigade Road, Bengaluru, 560001 | Y74: IN | Z74: ₹30,000 | AA74: =IF(U74="",INDEX(Lookups!$J$3:$J$5,MATCH(E74,Lookups!$I$3:$I$5,0)),VALUE(LEFT(U74,FIND(" ",U74)-1))) -> 15 | AB74: =VALUE(LEFT(V74,FIND(" ",V74)-1)) -> 30
A75: 74 | B75: =T75&", "&S75 -> Joshi, Sanya | C75: July | D75: ="Q"&ROUNDUP(MATCH(C75,Lookups!$L$3:$L$14,0)/3,0) -> Q3 | E75: Electric Scooter | F75: 457 Brigade Road | G75: Bengaluru | H75: 560001 | I75: =INDEX(Lookups!$B$3:$B$6,MATCH(Y75,Lookups!$A$3:$A$6,0)) -> India | J75: =INDEX(Lookups!$C$3:$C$6,MATCH(Y75,Lookups!$A$3:$A$6,0)) -> Asia | K75: =INDEX(Lookups!$D$3:$D$6,MATCH(Y75,Lookups!$A$3:$A$6,0)) -> INR | L75: 25000 | M75: =ROUND(L75*INDEX(Lookups!$G$3:$G$5,MATCH(K75,Lookups!$F$3:$F$5,0)),0) -> 300 | N75: 500 | O75: 0 | P75: =ROUND(N75*M75*(1-O75/100),0) -> 150000 | Q75: =ROUND(AA75*Lookups!$O$3,0)&" - "&ROUND(AB75*Lookups!$O$3,0)&" km/h" -> 32 - 56 km/h | R75: =IF(ISNUMBER(SEARCH("meters",W75)),ROUND(VALUE(SUBSTITUTE(LEFT(W75,FIND(" ",W75)-1),",",""))/Lookups!$O$4,0),ROUND(VALUE(LEFT(W75,FIND(" ",W75)-1))*Lookups!$O$3,0)) -> 64 | S75: Sanya | T75: Joshi | U75: 20 mph | V75: 35 mph | W75: 40 miles | X75: 457 Brigade Road, Bengaluru, 560001 | Y75: IN | Z75: ₹25,000 | AA75: =IF(U75="",INDEX(Lookups!$J$3:$J$5,MATCH(E75,Lookups!$I$3:$I$5,0)),VALUE(LEFT(U75,FIND(" ",U75)-1))) -> 20 | AB75: =VALUE(LEFT(V75,FIND(" ",V75)-1)) -> 35
A76: 75 | B76: =T76&", "&S76 -> Joshi, Sanya | C76: July | D76: ="Q"&ROUNDUP(MATCH(C76,Lookups!$L$3:$L$14,0)/3,0) -> Q3 | E76: Electric Skateboard | F76: 458 Brigade Road | G76: Bengaluru | H76: 560001 | I76: =INDEX(Lookups!$B$3:$B$6,MATCH(Y76,Lookups!$A$3:$A$6,0)) -> India | J76: =INDEX(Lookups!$C$3:$C$6,MATCH(Y76,Lookups!$A$3:$A$6,0)) -> Asia | K76: =INDEX(Lookups!$D$3:$D$6,MATCH(Y76,Lookups!$A$3:$A$6,0)) -> INR | L76: 22000 | M76: =ROUND(L76*INDEX(Lookups!$G$3:$G$5,MATCH(K76,Lookups!$F$3:$F$5,0)),0) -> 264 | N76: 400 | O76: 0 | P76: =ROUND(N76*M76*(1-O76/100),0) -> 105600 | Q76: =ROUND(AA76*Lookups!$O$3,0)&" - "&ROUND(AB76*Lookups!$O$3,0)&" km/h" -> 29 - 45 km/h | R76: =IF(ISNUMBER(SEARCH("meters",W76)),ROUND(VALUE(SUBSTITUTE(LEFT(W76,FIND(" ",W76)-1),",",""))/Lookups!$O$4,0),ROUND(VALUE(LEFT(W76,FIND(" ",W76)-1))*Lookups!$O$3,0)) -> 40 | S76: Sanya | T76: Joshi | U76: 18 mph | V76: 28 mph | W76: 25 miles | X76: 458 Brigade Road, Bengaluru, 560001 | Y76: IN | Z76: ₹22,000 | AA76: =IF(U76="",INDEX(Lookups!$J$3:$J$5,MATCH(E76,Lookups!$I$3:$I$5,0)),VALUE(LEFT(U76,FIND(" ",U76)-1))) -> 18 | AB76: =VALUE(LEFT(V76,FIND(" ",V76)-1)) -> 28
A77: 76 | B77: =T77&", "&S77 -> Liu, Fang | C77: July | D77: ="Q"&ROUNDUP(MATCH(C77,Lookups!$L$3:$L$14,0)/3,0) -> Q3 | E77: Electric Unicycle | F77: 99 Nanjing Road | G77: Shanghai | H77: 200001 | I77: =INDEX(Lookups!$B$3:$B$6,MATCH(Y77,Lookups!$A$3:$A$6,0)) -> China | J77: =INDEX(Lookups!$C$3:$C$6,MATCH(Y77,Lookups!$A$3:$A$6,0)) -> Asia | K77: =INDEX(Lookups!$D$3:$D$6,MATCH(Y77,Lookups!$A$3:$A$6,0)) -> CNY | L77: 5000 | M77: =ROUND(L77*INDEX(Lookups!$G$3:$G$5,MATCH(K77,Lookups!$F$3:$F$5,0)),0) -> 700 | N77: 800 | O77: 0 | P77: =ROUND(N77*M77*(1-O77/100),0) -> 560000 | Q77: =ROUND(AA77*Lookups!$O$3,0)&" - "&ROUND(AB77*Lookups!$O$3,0)&" km/h" -> 24 - 48 km/h | R77: =IF(ISNUMBER(SEARCH("meters",W77)),ROUND(VALUE(SUBSTITUTE(LEFT(W77,FIND(" ",W77)-1),",",""))/Lookups!$O$4,0),ROUND(VALUE(LEFT(W77,FIND(" ",W77)-1))*Lookups!$O$3,0)) -> 48 | S77: Fang | T77: Liu | U77: 15 mph | V77: 30 mph | W77: 48,280 meters | X77: 99 Nanjing Road, Shanghai, 200001 | Y77: CN | Z77: ¥5,000 | AA77: =IF(U77="",INDEX(Lookups!$J$3:$J$5,MATCH(E77,Lookups!$I$3:$I$5,0)),VALUE(LEFT(U77,FIND(" ",U77)-1))) -> 15 | AB77: =VALUE(LEFT(V77,FIND(" ",V77)-1)) -> 30
A78: 77 | B78: =T78&", "&S78 -> Liu, Fang | C78: July | D78: ="Q"&ROUNDUP(MATCH(C78,Lookups!$L$3:$L$14,0)/3,0) -> Q3 | E78: Electric Scooter | F78: 100 Nanjing Road | G78: Shanghai | H78: 200001 | I78: =INDEX(Lookups!$B$3:$B$6,MATCH(Y78,Lookups!$A$3:$A$6,0)) -> China | J78: =INDEX(Lookups!$C$3:$C$6,MATCH(Y78,Lookups!$A$3:$A$6,0)) -> Asia | K78: =INDEX(Lookups!$D$3:$D$6,MATCH(Y78,Lookups!$A$3:$A$6,0)) -> CNY | L78: 3500 | M78: =ROUND(L78*INDEX(Lookups!$G$3:$G$5,MATCH(K78,Lookups!$F$3:$F$5,0)),0) -> 490 | N78: 1800 | O78: 0 | P78: =ROUND(N78*M78*(1-O78/100),0) -> 882000 | Q78: =ROUND(AA78*Lookups!$O$3,0)&" - "&ROUND(AB78*Lookups!$O$3,0)&" km/h" -> 32 - 56 km/h | R78: =IF(ISNUMBER(SEARCH("meters",W78)),ROUND(VALUE(SUBSTITUTE(LEFT(W78,FIND(" ",W78)-1),",",""))/Lookups!$O$4,0),ROUND(VALUE(LEFT(W78,FIND(" ",W78)-1))*Lookups!$O$3,0)) -> 64 | S78: Fang | T78: Liu | U78: 20 mph | V78: 35 mph | W78: 40 miles | X78: 100 Nanjing Road, Shanghai, 200001 | Y78: CN | Z78: ¥3,500 | AA78: =IF(U78="",INDEX(Lookups!$J$3:$J$5,MATCH(E78,Lookups!$I$3:$I$5,0)),VALUE(LEFT(U78,FIND(" ",U78)-1))) -> 20 | AB78: =VALUE(LEFT(V78,FIND(" ",V78)-1)) -> 35
A79: 78 | B79: =T79&", "&S79 -> Liu, Fang | C79: July | D79: ="Q"&ROUNDUP(MATCH(C79,Lookups!$L$3:$L$14,0)/3,0) -> Q3 | E79: Electric Skateboard | F79: 101 Nanjing Road | G79: Shanghai | H79: 200001 | I79: =INDEX(Lookups!$B$3:$B$6,MATCH(Y79,Lookups!$A$3:$A$6,0)) -> China | J79: =INDEX(Lookups!$C$3:$C$6,MATCH(Y79,Lookups!$A$3:$A$6,0)) -> Asia | K79: =INDEX(Lookups!$D$3:$D$6,MATCH(Y79,Lookups!$A$3:$A$6,0)) -> CNY | L79: 4200 | M79: =ROUND(L79*INDEX(Lookups!$G$3:$G$5,MATCH(K79,Lookups!$F$3:$F$5,0)),0) -> 588 | N79: 1200 | O79: 0 | P79: =ROUND(N79*M79*(1-O79/100),0) -> 705600 | Q79: =ROUND(AA79*Lookups!$O$3,0)&" - "&ROUND(AB79*Lookups!$O$3,0)&" km/h" -> 29 - 45 km/h | R79: =IF(ISNUMBER(SEARCH("meters",W79)),ROUND(VALUE(SUBSTITUTE(LEFT(W79,FIND(" ",W79)-1),",",""))/Lookups!$O$4,0),ROUND(VALUE(LEFT(W79,FIND(" ",W79)-1))*Lookups!$O$3,0)) -> 40 | S79: Fang | T79: Liu | U79: 18 mph | V79: 28 mph | W79: 25 miles | X79: 101 Nanjing Road, Shanghai, 200001 | Y79: CN | Z79: ¥4,200 | AA79: =IF(U79="",INDEX(Lookups!$J$3:$J$5,MATCH(E79,Lookups!$I$3:$I$5,0)),VALUE(LEFT(U79,FIND(" ",U79)-1))) -> 18 | AB79: =VALUE(LEFT(V79,FIND(" ",V79)-1)) -> 28
A80: 79 | B80: =T80&", "&S80 -> Fischer, Jonas | C80: July | D80: ="Q"&ROUNDUP(MATCH(C80,Lookups!$L$3:$L$14,0)/3,0) -> Q3 | E80: Electric Unicycle | F80: 303 Ringstraße | G80: Hamburg | H80: 20095 | I80: =INDEX(Lookups!$B$3:$B$6,MATCH(Y80,Lookups!$A$3:$A$6,0)) -> Germany | J80: =INDEX(Lookups!$C$3:$C$6,MATCH(Y80,Lookups!$A$3:$A$6,0)) -> Europe | K80: =INDEX(Lookups!$D$3:$D$6,MATCH(Y80,Lookups!$A$3:$A$6,0)) -> EUR | L80: 1000 | M80: =ROUND(L80*INDEX(Lookups!$G$3:$G$5,MATCH(K80,Lookups!$F$3:$F$5,0)),0) -> 1080 | N80: 200 | O80: 0 | P80: =ROUND(N80*M80*(1-O80/100),0) -> 216000 | Q80: =ROUND(AA80*Lookups!$O$3,0)&" - "&ROUND(AB80*Lookups!$O$3,0)&" km/h" -> 24 - 48 km/h | R80: =IF(ISNUMBER(SEARCH("meters",W80)),ROUND(VALUE(SUBSTITUTE(LEFT(W80,FIND(" ",W80)-1),",",""))/Lookups!$O$4,0),ROUND(VALUE(LEFT(W80,FIND(" ",W80)-1))*Lookups!$O$3,0)) -> 48 | S80: Jonas | T80: Fischer | U80: 15 mph | V80: 30 mph | W80: 30 miles | X80: 303 Ringstraße, Hamburg, 20095 | Y80: DE | Z80: €1000 | AA80: =IF(U80="",INDEX(Lookups!$J$3:$J$5,MATCH(E80,Lookups!$I$3:$I$5,0)),VALUE(LEFT(U80,FIND(" ",U80)-1))) -> 15 | AB80: =VALUE(LEFT(V80,FIND(" ",V80)-1)) -> 30
A81: 80 | B81: =T81&", "&S81 -> Fischer, Jonas | C81: July | D81: ="Q"&ROUNDUP(MATCH(C81,Lookups!$L$3:$L$14,0)/3,0) -> Q3 | E81: Electric Scooter | F81: 304 Ringstraße | G81: Hamburg | H81: 20095 | I81: =INDEX(Lookups!$B$3:$B$6,MATCH(Y81,Lookups!$A$3:$A$6,0)) -> Germany | J81: =INDEX(Lookups!$C$3:$C$6,MATCH(Y81,Lookups!$A$3:$A$6,0)) -> Europe | K81: =INDEX(Lookups!$D$3:$D$6,MATCH(Y81,Lookups!$A$3:$A$6,0)) -> EUR | L81: 800 | M81: =ROUND(L81*INDEX(Lookups!$G$3:$G$5,MATCH(K81,Lookups!$F$3:$F$5,0)),0) -> 864 | N81: 350 | O81: 0 | P81: =ROUND(N81*M81*(1-O81/100),0) -> 302400 | Q81: =ROUND(AA81*Lookups!$O$3,0)&" - "&ROUND(AB81*Lookups!$O$3,0)&" km/h" -> 32 - 56 km/h | R81: =IF(ISNUMBER(SEARCH("meters",W81)),ROUND(VALUE(SUBSTITUTE(LEFT(W81,FIND(" ",W81)-1),",",""))/Lookups!$O$4,0),ROUND(VALUE(LEFT(W81,FIND(" ",W81)-1))*Lookups!$O$3,0)) -> 64 | S81: Jonas | T81: Fischer | U81: 20 mph | V81: 35 mph | W81: 40 miles | X81: 304 Ringstraße, Hamburg, 20095 | Y81: DE | Z81: €800 | AA81: =IF(U81="",INDEX(Lookups!$J$3:$J$5,MATCH(E81,Lookups!$I$3:$I$5,0)),VALUE(LEFT(U81,FIND(" ",U81)-1))) -> 20 | AB81: =VALUE(LEFT(V81,FIND(" ",V81)-1)) -> 35
A82: 81 | B82: =T82&", "&S82 -> Fischer, Jonas | C82: July | D82: ="Q"&ROUNDUP(MATCH(C82,Lookups!$L$3:$L$14,0)/3,0) -> Q3 | E82: Electric Skateboard | F82: 305 Ringstraße | G82: Hamburg | H82: 20095 | I82: =INDEX(Lookups!$B$3:$B$6,MATCH(Y82,Lookups!$A$3:$A$6,0)) -> Germany | J82: =INDEX(Lookups!$C$3:$C$6,MATCH(Y82,Lookups!$A$3:$A$6,0)) -> Europe | K82: =INDEX(Lookups!$D$3:$D$6,MATCH(Y82,Lookups!$A$3:$A$6,0)) -> EUR | L82: 950 | M82: =ROUND(L82*INDEX(Lookups!$G$3:$G$5,MATCH(K82,Lookups!$F$3:$F$5,0)),0) -> 1026 | N82: 250 | O82: 0 | P82: =ROUND(N82*M82*(1-O82/100),0) -> 256500 | Q82: =ROUND(AA82*Lookups!$O$3,0)&" - "&ROUND(AB82*Lookups!$O$3,0)&" km/h" -> 29 - 45 km/h | R82: =IF(ISNUMBER(SEARCH("meters",W82)),ROUND(VALUE(SUBSTITUTE(LEFT(W82,FIND(" ",W82)-1),",",""))/Lookups!$O$4,0),ROUND(VALUE(LEFT(W82,FIND(" ",W82)-1))*Lookups!$O$3,0)) -> 40 | S82: Jonas | T82: Fischer | U82: 18 mph | V82: 28 mph | W82: 25 miles | X82: 305 Ringstraße, Hamburg, 20095 | Y82: DE | Z82: €950 | AA82: =IF(U82="",INDEX(Lookups!$J$3:$J$5,MATCH(E82,Lookups!$I$3:$I$5,0)),VALUE(LEFT(U82,FIND(" ",U82)-1))) -> 18 | AB82: =VALUE(LEFT(V82,FIND(" ",V82)-1)) -> 28
A83: 82 | B83: =T83&", "&S83 -> Bernard, Théo | C83: July | D83: ="Q"&ROUNDUP(MATCH(C83,Lookups!$L$3:$L$14,0)/3,0) -> Q3 | E83: Electric Unicycle | F83: 56 Boulevard Saint-Germain | G83: Paris | H83: 75005 | I83: =INDEX(Lookups!$B$3:$B$6,MATCH(Y83,Lookups!$A$3:$A$6,0)) -> France | J83: =INDEX(Lookups!$C$3:$C$6,MATCH(Y83,Lookups!$A$3:$A$6,0)) -> Europe | K83: =INDEX(Lookups!$D$3:$D$6,MATCH(Y83,Lookups!$A$3:$A$6,0)) -> EUR | L83: 1100 | M83: =ROUND(L83*INDEX(Lookups!$G$3:$G$5,MATCH(K83,Lookups!$F$3:$F$5,0)),0) -> 1188 | N83: 160 | O83: 0 | P83: =ROUND(N83*M83*(1-O83/100),0) -> 190080 | Q83: =ROUND(AA83*Lookups!$O$3,0)&" - "&ROUND(AB83*Lookups!$O$3,0)&" km/h" -> 24 - 48 km/h | R83: =IF(ISNUMBER(SEARCH("meters",W83)),ROUND(VALUE(SUBSTITUTE(LEFT(W83,FIND(" ",W83)-1),",",""))/Lookups!$O$4,0),ROUND(VALUE(LEFT(W83,FIND(" ",W83)-1))*Lookups!$O$3,0)) -> 48 | S83: Théo | T83: Bernard | U83: 15 mph | V83: 30 mph | W83: 30 miles | X83: 56 Boulevard Saint-Germain, Paris, 75005 | Y83: FR | Z83: €1100 | AA83: =IF(U83="",INDEX(Lookups!$J$3:$J$5,MATCH(E83,Lookups!$I$3:$I$5,0)),VALUE(LEFT(U83,FIND(" ",U83)-1))) -> 15 | AB83: =VALUE(LEFT(V83,FIND(" ",V83)-1)) -> 30
... A88: 87 | B88: =T88&", "&S88 -> Joshi, Sanya | C88: August | D88: ="Q"&ROUNDUP(MATCH(C88,Lookups!$L$3:$L$14,0)/3,0) -> Q3 | E88: Electric Skateboard | F88: 458 Brigade Road | G88: Bengaluru | H88: 560001 | I88: =INDEX(Lookups!$B$3:$B$6,MATCH(Y88,Lookups!$A$3:$A$6,0)) -> India | J88: =INDEX(Lookups!$C$3:$C$6,MATCH(Y88,Lookups!$A$3:$A$6,0)) -> Asia | K88: =INDEX(Lookups!$D$3:$D$6,MATCH(Y88,Lookups!$A$3:$A$6,0)) -> INR | L88: 22000 | M88: =ROUND(L88*INDEX(Lookups!$G$3:$G$5,MATCH(K88,Lookups!$F$3:$F$5,0)),0) -> 264 | N88: 350 | O88: 0 | P88: =ROUND(N88*M88*(1-O88/100),0) -> 92400 | Q88: =ROUND(AA88*Lookups!$O$3,0)&" - "&ROUND(AB88*Lookups!$O$3,0)&" km/h" -> 29 - 45 km/h | R88: =IF(ISNUMBER(SEARCH("meters",W88)),ROUND(VALUE(SUBSTITUTE(LEFT(W88,FIND(" ",W88)-1),",",""))/Lookups!$O$4,0),ROUND(VALUE(LEFT(W88,FIND(" ",W88)-1))*Lookups!$O$3,0)) -> 40 | S88: Sanya | T88: Joshi | U88: 18 mph | V88: 28 mph | W88: 40,230 meters | X88: 458 Brigade Road, Bengaluru, 560001 | Y88: IN | Z88: ₹22,000 | AA88: =IF(U88="",INDEX(Lookups!$J$3:$J$5,MATCH(E88,Lookups!$I$3:$I$5,0)),VALUE(LEFT(U88,FIND(" ",U88)-1))) -> 18 | AB88: =VALUE(LEFT(V88,FIND(" ",V88)-1)) -> 28
A89: 88 | B89: =T89&", "&S89 -> Liu, Fang | C89: August | D89: ="Q"&ROUNDUP(MATCH(C89,Lookups!$L$3:$L$14,0)/3,0) -> Q3 | E89: Electric Unicycle | F89: 99 Nanjing Road | G89: Shanghai | H89: 200001 | I89: =INDEX(Lookups!$B$3:$B$6,MATCH(Y89,Lookups!$A$3:$A$6,0)) -> China | J89: =INDEX(Lookups!$C$3:$C$6,MATCH(Y89,Lookups!$A$3:$A$6,0)) -> Asia | K89: =INDEX(Lookups!$D$3:$D$6,MATCH(Y89,Lookups!$A$3:$A$6,0)) -> CNY | L89: 5000 | M89: =ROUND(L89*INDEX(Lookups!$G$3:$G$5,MATCH(K89,Lookups!$F$3:$F$5,0)),0) -> 700 | N89: 700 | O89: 0 | P89: =ROUND(N89*M89*(1-O89/100),0) -> 490000 | Q89: =ROUND(AA89*Lookups!$O$3,0)&" - "&ROUND(AB89*Lookups!$O$3,0)&" km/h" -> 24 - 48 km/h | R89: =IF(ISNUMBER(SEARCH("meters",W89)),ROUND(VALUE(SUBSTITUTE(LEFT(W89,FIND(" ",W89)-1),",",""))/Lookups!$O$4,0),ROUND(VALUE(LEFT(W89,FIND(" ",W89)-1))*Lookups!$O$3,0)) -> 48 | S89: Fang | T89: Liu | V89: 30 mph | W89: 30 miles | X89: 99 Nanjing Road, Shanghai, 200001 | Y89: CN | Z89: ¥5,000 | AA89: =IF(U89="",INDEX(Lookups!$J$3:$J$5,MATCH(E89,Lookups!$I$3:$I$5,0)),VALUE(LEFT(U89,FIND(" ",U89)-1))) -> 15 | AB89: =VALUE(LEFT(V89,FIND(" ",V89)-1)) -> 30
A90: 89 | B90: =T90&", "&S90 -> Liu, Fang | C90: August | D90: ="Q"&ROUNDUP(MATCH(C90,Lookups!$L$3:$L$14,0)/3,0) -> Q3 | E90: Electric Scooter | F90: 100 Nanjing Road | G90: Shanghai | H90: 200001 | I90: =INDEX(Lookups!$B$3:$B$6,MATCH(Y90,Lookups!$A$3:$A$6,0)) -> China | J90: =INDEX(Lookups!$C$3:$C$6,MATCH(Y90,Lookups!$A$3:$A$6,0)) -> Asia | K90: =INDEX(Lookups!$D$3:$D$6,MATCH(Y90,Lookups!$A$3:$A$6,0)) -> CNY | L90: 3500 | M90: =ROUND(L90*INDEX(Lookups!$G$3:$G$5,MATCH(K90,Lookups!$F$3:$F$5,0)),0) -> 490 | N90: 1600 | O90: 0 | P90: =ROUND(N90*M90*(1-O90/100),0) -> 784000 | Q90: =ROUND(AA90*Lookups!$O$3,0)&" - "&ROUND(AB90*Lookups!$O$3,0)&" km/h" -> 32 - 56 km/h | R90: =IF(ISNUMBER(SEARCH("meters",W90)),ROUND(VALUE(SUBSTITUTE(LEFT(W90,FIND(" ",W90)-1),",",""))/Lookups!$O$4,0),ROUND(VALUE(LEFT(W90,FIND(" ",W90)-1))*Lookups!$O$3,0)) -> 64 | S90: Fang | T90: Liu | U90: 20 mph | V90: 35 mph | W90: 40 miles | X90: 100 Nanjing Road, Shanghai, 200001 | Y90: CN | Z90: ¥3,500 | AA90: =IF(U90="",INDEX(Lookups!$J$3:$J$5,MATCH(E90,Lookups!$I$3:$I$5,0)),VALUE(LEFT(U90,FIND(" ",U90)-1))) -> 20 | AB90: =VALUE(LEFT(V90,FIND(" ",V90)-1)) -> 35
A91: 90 | B91: =T91&", "&S91 -> Liu, Fang | C91: August | D91: ="Q"&ROUNDUP(MATCH(C91,Lookups!$L$3:$L$14,0)/3,0) -> Q3 | E91: Electric Skateboard | F91: 101 Nanjing Road | G91: Shanghai | H91: 200001 | I91: =INDEX(Lookups!$B$3:$B$6,MATCH(Y91,Lookups!$A$3:$A$6,0)) -> China | J91: =INDEX(Lookups!$C$3:$C$6,MATCH(Y91,Lookups!$A$3:$A$6,0)) -> Asia | K91: =INDEX(Lookups!$D$3:$D$6,MATCH(Y91,Lookups!$A$3:$A$6,0)) -> CNY | L91: 4200 | M91: =ROUND(L91*INDEX(Lookups!$G$3:$G$5,MATCH(K91,Lookups!$F$3:$F$5,0)),0) -> 588 | N91: 1000 | O91: 0 | P91: =ROUND(N91*M91*(1-O91/100),0) -> 588000 | Q91: =ROUND(AA91*Lookups!$O$3,0)&" - "&ROUND(AB91*Lookups!$O$3,0)&" km/h" -> 29 - 45 km/h | R91: =IF(ISNUMBER(SEARCH("meters",W91)),ROUND(VALUE(SUBSTITUTE(LEFT(W91,FIND(" ",W91)-1),",",""))/Lookups!$O$4,0),ROUND(VALUE(LEFT(W91,FIND(" ",W91)-1))*Lookups!$O$3,0)) -> 40 | S91: Fang | T91: Liu | U91: 18 mph | V91: 28 mph | W91: 25 miles | X91: 101 Nanjing Road, Shanghai, 200001 | Y91: CN | Z91: ¥4,200 | AA91: =IF(U91="",INDEX(Lookups!$J$3:$J$5,MATCH(E91,Lookups!$I$3:$I$5,0)),VALUE(LEFT(U91,FIND(" ",U91)-1))) -> 18 | AB91: =VALUE(LEFT(V91,FIND(" ",V91)-1)) -> 28
A92: 91 | B92: =T92&", "&S92 -> Fischer, Jonas | C92: August | D92: ="Q"&ROUNDUP(MATCH(C92,Lookups!$L$3:$L$14,0)/3,0) -> Q3 | E92: Electric Unicycle | F92: 303 Ringstraße | G92: Hamburg | H92: 20095 | I92: =INDEX(Lookups!$B$3:$B$6,MATCH(Y92,Lookups!$A$3:$A$6,0)) -> Germany | J92: =INDEX(Lookups!$C$3:$C$6,MATCH(Y92,Lookups!$A$3:$A$6,0)) -> Europe | K92: =INDEX(Lookups!$D$3:$D$6,MATCH(Y92,Lookups!$A$3:$A$6,0)) -> EUR | L92: 1000 | M92: =ROUND(L92*INDEX(Lookups!$G$3:$G$5,MATCH(K92,Lookups!$F$3:$F$5,0)),0) -> 1080 | N92: 180 | O92: 0 | P92: =ROUND(N92*M92*(1-O92/100),0) -> 194400 | Q92: =ROUND(AA92*Lookups!$O$3,0)&" - "&ROUND(AB92*Lookups!$O$3,0)&" km/h" -> 24 - 48 km/h | R92: =IF(ISNUMBER(SEARCH("meters",W92)),ROUND(VALUE(SUBSTITUTE(LEFT(W92,FIND(" ",W92)-1),",",""))/Lookups!$O$4,0),ROUND(VALUE(LEFT(W92,FIND(" ",W92)-1))*Lookups!$O$3,0)) -> 48 | S92: Jonas | T92: Fischer | U92: 15 mph | V92: 30 mph | W92: 30 miles | X92: 303 Ringstraße, Hamburg, 20095 | Y92: DE | Z92: €1000 | AA92: =IF(U92="",INDEX(Lookups!$J$3:$J$5,MATCH(E92,Lookups!$I$3:$I$5,0)),VALUE(LEFT(U92,FIND(" ",U92)-1))) -> 15 | AB92: =VALUE(LEFT(V92,FIND(" ",V92)-1)) -> 30
A93: 92 | B93: =T93&", "&S93 -> Fischer, Jonas | C93: August | D93: ="Q"&ROUNDUP(MATCH(C93,Lookups!$L$3:$L$14,0)/3,0) -> Q3 | E93: Electric Scooter | F93: 304 Ringstraße | G93: Hamburg | H93: 20095 | I93: =INDEX(Lookups!$B$3:$B$6,MATCH(Y93,Lookups!$A$3:$A$6,0)) -> Germany | J93: =INDEX(Lookups!$C$3:$C$6,MATCH(Y93,Lookups!$A$3:$A$6,0)) -> Europe | K93: =INDEX(Lookups!$D$3:$D$6,MATCH(Y93,Lookups!$A$3:$A$6,0)) -> EUR | L93: 800 | M93: =ROUND(L93*INDEX(Lookups!$G$3:$G$5,MATCH(K93,Lookups!$F$3:$F$5,0)),0) -> 864 | N93: 300 | O93: 0 | P93: =ROUND(N93*M93*(1-O93/100),0) -> 259200 | Q93: =ROUND(AA93*Lookups!$O$3,0)&" - "&ROUND(AB93*Lookups!$O$3,0)&" km/h" -> 32 - 56 km/h | R93: =IF(ISNUMBER(SEARCH("meters",W93)),ROUND(VALUE(SUBSTITUTE(LEFT(W93,FIND(" ",W93)-1),",",""))/Lookups!$O$4,0),ROUND(VALUE(LEFT(W93,FIND(" ",W93)-1))*Lookups!$O$3,0)) -> 64 | S93: Jonas | T93: Fischer | U93: 20 mph | V93: 35 mph | W93: 64,370 meters | X93: 304 Ringstraße, Hamburg, 20095 | Y93: DE | Z93: €800 | AA93: =IF(U93="",INDEX(Lookups!$J$3:$J$5,MATCH(E93,Lookups!$I$3:$I$5,0)),VALUE(LEFT(U93,FIND(" ",U93)-1))) -> 20 | AB93: =VALUE(LEFT(V93,FIND(" ",V93)-1)) -> 35
A94: 93 | B94: =T94&", "&S94 -> Fischer, Jonas | C94: August | D94: ="Q"&ROUNDUP(MATCH(C94,Lookups!$L$3:$L$14,0)/3,0) -> Q3 | E94: Electric Skateboard | F94: 305 Ringstraße | G94: Hamburg | H94: 20095 | I94: =INDEX(Lookups!$B$3:$B$6,MATCH(Y94,Lookups!$A$3:$A$6,0)) -> Germany | J94: =INDEX(Lookups!$C$3:$C$6,MATCH(Y94,Lookups!$A$3:$A$6,0)) -> Europe | K94: =INDEX(Lookups!$D$3:$D$6,MATCH(Y94,Lookups!$A$3:$A$6,0)) -> EUR | L94: 950 | M94: =ROUND(L94*INDEX(Lookups!$G$3:$G$5,MATCH(K94,Lookups!$F$3:$F$5,0)),0) -> 1026 | N94: 230 | O94: 0 | P94: =ROUND(N94*M94*(1-O94/100),0) -> 235980 | Q94: =ROUND(AA94*Lookups!$O$3,0)&" - "&ROUND(AB94*Lookups!$O$3,0)&" km/h" -> 29 - 45 km/h | R94: =IF(ISNUMBER(SEARCH("meters",W94)),ROUND(VALUE(SUBSTITUTE(LEFT(W94,FIND(" ",W94)-1),",",""))/Lookups!$O$4,0),ROUND(VALUE(LEFT(W94,FIND(" ",W94)-1))*Lookups!$O$3,0)) -> 40 | S94: Jonas | T94: Fischer | U94: 18 mph | V94: 28 mph | W94: 25 miles | X94: 305 Ringstraße, Hamburg, 20095 | Y94: DE | Z94: €950 | AA94: =IF(U94="",INDEX(Lookups!$J$3:$J$5,MATCH(E94,Lookups!$I$3:$I$5,0)),VALUE(LEFT(U94,FIND(" ",U94)-1))) -> 18 | AB94: =VALUE(LEFT(V94,FIND(" ",V94)-1)) -> 28
A95: 94 | B95: =T95&", "&S95 -> Bernard, Théo | C95: August | D95: ="Q"&ROUNDUP(MATCH(C95,Lookups!$L$3:$L$14,0)/3,0) -> Q3 | E95: Electric Unicycle | F95: 56 Boulevard Saint-Germain | G95: Paris | H95: 75005 | I95: =INDEX(Lookups!$B$3:$B$6,MATCH(Y95,Lookups!$A$3:$A$6,0)) -> France | J95: =INDEX(Lookups!$C$3:$C$6,MATCH(Y95,Lookups!$A$3:$A$6,0)) -> Europe | K95: =INDEX(Lookups!$D$3:$D$6,MATCH(Y95,Lookups!$A$3:$A$6,0)) -> EUR | L95: 1100 | M95: =ROUND(L95*INDEX(Lookups!$G$3:$G$5,MATCH(K95,Lookups!$F$3:$F$5,0)),0) -> 1188 | N95: 150 | O95: 0 | P95: =ROUND(N95*M95*(1-O95/100),0) -> 178200 | Q95: =ROUND(AA95*Lookups!$O$3,0)&" - "&ROUND(AB95*Lookups!$O$3,0)&" km/h" -> 24 - 48 km/h | R95: =IF(ISNUMBER(SEARCH("meters",W95)),ROUND(VALUE(SUBSTITUTE(LEFT(W95,FIND(" ",W95)-1),",",""))/Lookups!$O$4,0),ROUND(VALUE(LEFT(W95,FIND(" ",W95)-1))*Lookups!$O$3,0)) -> 48 | S95: Théo | T95: Bernard | U95: 15 mph | V95: 30 mph | W95: 30 miles | X95: 56 Boulevard Saint-Germain, Paris, 75005 | Y95: FR | Z95: €1100 | AA95: =IF(U95="",INDEX(Lookups!$J$3:$J$5,MATCH(E95,Lookups!$I$3:$I$5,0)),VALUE(LEFT(U95,FIND(" ",U95)-1))) -> 15 | AB95: =VALUE(LEFT(V95,FIND(" ",V95)-1)) -> 30
A96: 95 | B96: =T96&", "&S96 -> Bernard, Théo | C96: August | D96: ="Q"&ROUNDUP(MATCH(C96,Lookups!$L$3:$L$14,0)/3,0) -> Q3 | E96: Electric Scooter | F96: 57 Boulevard Saint-Germain | G96: Paris | H96: 75005 | I96: =INDEX(Lookups!$B$3:$B$6,MATCH(Y96,Lookups!$A$3:$A$6,0)) -> France | J96: =INDEX(Lookups!$C$3:$C$6,MATCH(Y96,Lookups!$A$3:$A$6,0)) -> Europe | K96: =INDEX(Lookups!$D$3:$D$6,MATCH(Y96,Lookups!$A$3:$A$6,0)) -> EUR | L96: 900 | M96: =ROUND(L96*INDEX(Lookups!$G$3:$G$5,MATCH(K96,Lookups!$F$3:$F$5,0)),0) -> 972 | N96: 280 | O96: 0 | P96: =ROUND(N96*M96*(1-O96/100),0) -> 272160 | Q96: =ROUND(AA96*Lookups!$O$3,0)&" - "&ROUND(AB96*Lookups!$O$3,0)&" km/h" -> 32 - 56 km/h | R96: =IF(ISNUMBER(SEARCH("meters",W96)),ROUND(VALUE(SUBSTITUTE(LEFT(W96,FIND(" ",W96)-1),",",""))/Lookups!$O$4,0),ROUND(VALUE(LEFT(W96,FIND(" ",W96)-1))*Lookups!$O$3,0)) -> 64 | S96: Théo | T96: Bernard | U96: 20 mph | V96: 35 mph | W96: 40 miles | X96: 57 Boulevard Saint-Germain, Paris, 75005 | Y96: FR | Z96: €900 | AA96: =IF(U96="",INDEX(Lookups!$J$3:$J$5,MATCH(E96,Lookups!$I$3:$I$5,0)),VALUE(LEFT(U96,FIND(" ",U96)-1))) -> 20 | AB96: =VALUE(LEFT(V96,FIND(" ",V96)-1)) -> 35
A97: 96 | B97: =T97&", "&S97 -> Bernard, Théo | C97: August | D97: ="Q"&ROUNDUP(MATCH(C97,Lookups!$L$3:$L$14,0)/3,0) -> Q3 | E97: Electric Skateboard | F97: 58 Boulevard Saint-Germain | G97: Paris | H97: 75005 | I97: =INDEX(Lookups!$B$3:$B$6,MATCH(Y97,Lookups!$A$3:$A$6,0)) -> France | J97: =INDEX(Lookups!$C$3:$C$6,MATCH(Y97,Lookups!$A$3:$A$6,0)) -> Europe | K97: =INDEX(Lookups!$D$3:$D$6,MATCH(Y97,Lookups!$A$3:$A$6,0)) -> EUR | L97: 1050 | M97: =ROUND(L97*INDEX(Lookups!$G$3:$G$5,MATCH(K97,Lookups!$F$3:$F$5,0)),0) -> 1134 | N97: 290 | O97: 0 | P97: =ROUND(N97*M97*(1-O97/100),0) -> 328860 | Q97: =ROUND(AA97*Lookups!$O$3,0)&" - "&ROUND(AB97*Lookups!$O$3,0)&" km/h" -> 29 - 45 km/h | R97: =IF(ISNUMBER(SEARCH("meters",W97)),ROUND(VALUE(SUBSTITUTE(LEFT(W97,FIND(" ",W97)-1),",",""))/Lookups!$O$4,0),ROUND(VALUE(LEFT(W97,FIND(" ",W97)-1))*Lookups!$O$3,0)) -> 40 | S97: Théo | T97: Bernard | U97: 18 mph | V97: 28 mph | W97: 25 miles | X97: 58 Boulevard Saint-Germain, Paris, 75005 | Y97: FR | Z97: €1050 | AA97: =IF(U97="",INDEX(Lookups!$J$3:$J$5,MATCH(E97,Lookups!$I$3:$I$5,0)),VALUE(LEFT(U97,FIND(" ",U97)-1))) -> 18 | AB97: =VALUE(LEFT(V97,FIND(" ",V97)-1)) -> 28
A98: 97 | B98: =T98&", "&S98 -> Joshi, Sanya | C98: September | D98: ="Q"&ROUNDUP(MATCH(C98,Lookups!$L$3:$L$14,0)/3,0) -> Q3 | E98: Electric Unicycle | F98: 456 Brigade Road | G98: Bengaluru | H98: 560001 | I98: =INDEX(Lookups!$B$3:$B$6,MATCH(Y98,Lookups!$A$3:$A$6,0)) -> India | J98: =INDEX(Lookups!$C$3:$C$6,MATCH(Y98,Lookups!$A$3:$A$6,0)) -> Asia | K98: =INDEX(Lookups!$D$3:$D$6,MATCH(Y98,Lookups!$A$3:$A$6,0)) -> INR | L98: 30000 | M98: =ROUND(L98*INDEX(Lookups!$G$3:$G$5,MATCH(K98,Lookups!$F$3:$F$5,0)),0) -> 360 | N98: 180 | O98: 0 | P98: =ROUND(N98*M98*(1-O98/100),0) -> 64800 | Q98: =ROUND(AA98*Lookups!$O$3,0)&" - "&ROUND(AB98*Lookups!$O$3,0)&" km/h" -> 24 - 48 km/h | R98: =IF(ISNUMBER(SEARCH("meters",W98)),ROUND(VALUE(SUBSTITUTE(LEFT(W98,FIND(" ",W98)-1),",",""))/Lookups!$O$4,0),ROUND(VALUE(LEFT(W98,FIND(" ",W98)-1))*Lookups!$O$3,0)) -> 48 | S98: Sanya | T98: Joshi | U98: 15 mph | V98: 30 mph | W98: 30 miles | X98: 456 Brigade Road, Bengaluru, 560001 | Y98: IN | Z98: ₹30,000 | AA98: =IF(U98="",INDEX(Lookups!$J$3:$J$5,MATCH(E98,Lookups!$I$3:$I$5,0)),VALUE(LEFT(U98,FIND(" ",U98)-1))) -> 15 | AB98: =VALUE(LEFT(V98,FIND(" ",V98)-1)) -> 30
A99: 98 | B99: =T99&", "&S99 -> Joshi, Sanya | C99: September | D99: ="Q"&ROUNDUP(MATCH(C99,Lookups!$L$3:$L$14,0)/3,0) -> Q3 | E99: Electric Scooter | F99: 457 Brigade Road | G99: Bengaluru | H99: 560001 | I99: =INDEX(Lookups!$B$3:$B$6,MATCH(Y99,Lookups!$A$3:$A$6,0)) -> India | J99: =INDEX(Lookups!$C$3:$C$6,MATCH(Y99,Lookups!$A$3:$A$6,0)) -> Asia | K99: =INDEX(Lookups!$D$3:$D$6,MATCH(Y99,Lookups!$A$3:$A$6,0)) -> INR | L99: 25000 | M99: =ROUND(L99*INDEX(Lookups!$G$3:$G$5,MATCH(K99,Lookups!$F$3:$F$5,0)),0) -> 300 | N99: 500 | O99: 0 | P99: =ROUND(N99*M99*(1-O99/100),0) -> 150000 | Q99: =ROUND(AA99*Lookups!$O$3,0)&" - "&ROUND(AB99*Lookups!$O$3,0)&" km/h" -> 32 - 56 km/h | R99: =IF(ISNUMBER(SEARCH("meters",W99)),ROUND(VALUE(SUBSTITUTE(LEFT(W99,FIND(" ",W99)-1),",",""))/Lookups!$O$4,0),ROUND(VALUE(LEFT(W99,FIND(" ",W99)-1))*Lookups!$O$3,0)) -> 64 | S99: Sanya | T99: Joshi | U99: 20 mph | V99: 35 mph | W99: 40 miles | X99: 457 Brigade Road, Bengaluru, 560001 | Y99: IN | Z99: ₹25,000 | AA99: =IF(U99="",INDEX(Lookups!$J$3:$J$5,MATCH(E99,Lookups!$I$3:$I$5,0)),VALUE(LEFT(U99,FIND(" ",U99)-1))) -> 20 | AB99: =VALUE(LEFT(V99,FIND(" ",V99)-1)) -> 35
A100: 99 | B100: =T100&", "&S100 -> Joshi, Sanya | C100: September | D100: ="Q"&ROUNDUP(MATCH(C100,Lookups!$L$3:$L$14,0)/3,0) -> Q3 | E100: Electric Skateboard | F100: 458 Brigade Road | G100: Bengaluru | H100: 560001 | I100: =INDEX(Lookups!$B$3:$B$6,MATCH(Y100,Lookups!$A$3:$A$6,0)) -> India | J100: =INDEX(Lookups!$C$3:$C$6,MATCH(Y100,Lookups!$A$3:$A$6,0)) -> Asia | K100: =INDEX(Lookups!$D$3:$D$6,MATCH(Y100,Lookups!$A$3:$A$6,0)) -> INR | L100: 22000 | M100: =ROUND(L100*INDEX(Lookups!$G$3:$G$5,MATCH(K100,Lookups!$F$3:$F$5,0)),0) -> 264 | N100: 300 | O100: 0 | P100: =ROUND(N100*M100*(1-O100/100),0) -> 79200 | Q100: =ROUND(AA100*Lookups!$O$3,0)&" - "&ROUND(AB100*Lookups!$O$3,0)&" km/h" -> 29 - 45 km/h | R100: =IF(ISNUMBER(SEARCH("meters",W100)),ROUND(VALUE(SUBSTITUTE(LEFT(W100,FIND(" ",W100)-1),",",""))/Lookups!$O$4,0),ROUND(VALUE(LEFT(W100,FIND(" ",W100)-1))*Lookups!$O$3,0)) -> 40 | S100: Sanya | T100: Joshi | U100: 18 mph | V100: 28 mph | W100: 25 miles | X100: 458 Brigade Road, Bengaluru, 560001 | Y100: IN | Z100: ₹22,000 | AA100: =IF(U100="",INDEX(Lookups!$J$3:$J$5,MATCH(E100,Lookups!$I$3:$I$5,0)),VALUE(LEFT(U100,FIND(" ",U100)-1))) -> 18 | AB100: =VALUE(LEFT(V100,FIND(" ",V100)-1)) -> 28
A101: 100 | B101: =T101&", "&S101 -> Liu, Fang | C101: September | D101: ="Q"&ROUNDUP(MATCH(C101,Lookups!$L$3:$L$14,0)/3,0) -> Q3 | E101: Electric Unicycle | F101: 99 Nanjing Road | G101: Shanghai | H101: 200001 | I101: =INDEX(Lookups!$B$3:$B$6,MATCH(Y101,Lookups!$A$3:$A$6,0)) -> China | J101: =INDEX(Lookups!$C$3:$C$6,MATCH(Y101,Lookups!$A$3:$A$6,0)) -> Asia | K101: =INDEX(Lookups!$D$3:$D$6,MATCH(Y101,Lookups!$A$3:$A$6,0)) -> CNY | L101: 5000 | M101: =ROUND(L101*INDEX(Lookups!$G$3:$G$5,MATCH(K101,Lookups!$F$3:$F$5,0)),0) -> 700 | N101: 600 | O101: 0 | P101: =ROUND(N101*M101*(1-O101/100),0) -> 420000 | Q101: =ROUND(AA101*Lookups!$O$3,0)&" - "&ROUND(AB101*Lookups!$O$3,0)&" km/h" -> 24 - 48 km/h | R101: =IF(ISNUMBER(SEARCH("meters",W101)),ROUND(VALUE(SUBSTITUTE(LEFT(W101,FIND(" ",W101)-1),",",""))/Lookups!$O$4,0),ROUND(VALUE(LEFT(W101,FIND(" ",W101)-1))*Lookups!$O$3,0)) -> 48 | S101: Fang | T101: Liu | U101: 15 mph | V101: 30 mph | W101: 30 miles | X101: 99 Nanjing Road, Shanghai, 200001 | Y101: CN | Z101: ¥5,000 | AA101: =IF(U101="",INDEX(Lookups!$J$3:$J$5,MATCH(E101,Lookups!$I$3:$I$5,0)),VALUE(LEFT(U101,FIND(" ",U101)-1))) -> 15 | AB101: =VALUE(LEFT(V101,FIND(" ",V101)-1)) -> 30
... A116: 115 | B116: =T116&", "&S116 -> Fischer, Jonas | C116: October | D116: ="Q"&ROUNDUP(MATCH(C116,Lookups!$L$3:$L$14,0)/3,0) -> Q4 | E116: Electric Unicycle | F116: 303 Ringstraße | G116: Hamburg | H116: 20095 | I116: =INDEX(Lookups!$B$3:$B$6,MATCH(Y116,Lookups!$A$3:$A$6,0)) -> Germany | J116: =INDEX(Lookups!$C$3:$C$6,MATCH(Y116,Lookups!$A$3:$A$6,0)) -> Europe | K116: =INDEX(Lookups!$D$3:$D$6,MATCH(Y116,Lookups!$A$3:$A$6,0)) -> EUR | L116: 1000 | M116: =ROUND(L116*INDEX(Lookups!$G$3:$G$5,MATCH(K116,Lookups!$F$3:$F$5,0)),0) -> 1080 | N116: 140 | O116: 0 | P116: =ROUND(N116*M116*(1-O116/100),0) -> 151200 | Q116: =ROUND(AA116*Lookups!$O$3,0)&" - "&ROUND(AB116*Lookups!$O$3,0)&" km/h" -> 24 - 48 km/h | R116: =IF(ISNUMBER(SEARCH("meters",W116)),ROUND(VALUE(SUBSTITUTE(LEFT(W116,FIND(" ",W116)-1),",",""))/Lookups!$O$4,0),ROUND(VALUE(LEFT(W116,FIND(" ",W116)-1))*Lookups!$O$3,0)) -> 48 | S116: Jonas | T116: Fischer | U116: 15 mph | V116: 30 mph | W116: 30 miles | X116: 303 Ringstraße, Hamburg, 20095 | Y116: DE | Z116: €1000 | AA116: =IF(U116="",INDEX(Lookups!$J$3:$J$5,MATCH(E116,Lookups!$I$3:$I$5,0)),VALUE(LEFT(U116,FIND(" ",U116)-1))) -> 15 | AB116: =VALUE(LEFT(V116,FIND(" ",V116)-1)) -> 30
A117: 116 | B117: =T117&", "&S117 -> Fischer, Jonas | C117: October | D117: ="Q"&ROUNDUP(MATCH(C117,Lookups!$L$3:$L$14,0)/3,0) -> Q4 | E117: Electric Scooter | F117: 304 Ringstraße | G117: Hamburg | H117: 20095 | I117: =INDEX(Lookups!$B$3:$B$6,MATCH(Y117,Lookups!$A$3:$A$6,0)) -> Germany | J117: =INDEX(Lookups!$C$3:$C$6,MATCH(Y117,Lookups!$A$3:$A$6,0)) -> Europe | K117: =INDEX(Lookups!$D$3:$D$6,MATCH(Y117,Lookups!$A$3:$A$6,0)) -> EUR | L117: 800 | M117: =ROUND(L117*INDEX(Lookups!$G$3:$G$5,MATCH(K117,Lookups!$F$3:$F$5,0)),0) -> 864 | N117: 300 | O117: 0 | P117: =ROUND(N117*M117*(1-O117/100),0) -> 259200 | Q117: =ROUND(AA117*Lookups!$O$3,0)&" - "&ROUND(AB117*Lookups!$O$3,0)&" km/h" -> 32 - 56 km/h | R117: =IF(ISNUMBER(SEARCH("meters",W117)),ROUND(VALUE(SUBSTITUTE(LEFT(W117,FIND(" ",W117)-1),",",""))/Lookups!$O$4,0),ROUND(VALUE(LEFT(W117,FIND(" ",W117)-1))*Lookups!$O$3,0)) -> 64 | S117: Jonas | T117: Fischer | V117: 35 mph | W117: 40 miles | X117: 304 Ringstraße, Hamburg, 20095 | Y117: DE | Z117: €800 | AA117: =IF(U117="",INDEX(Lookups!$J$3:$J$5,MATCH(E117,Lookups!$I$3:$I$5,0)),VALUE(LEFT(U117,FIND(" ",U117)-1))) -> 20 | AB117: =VALUE(LEFT(V117,FIND(" ",V117)-1)) -> 35
A118: 117 | B118: =T118&", "&S118 -> Fischer, Jonas | C118: October | D118: ="Q"&ROUNDUP(MATCH(C118,Lookups!$L$3:$L$14,0)/3,0) -> Q4 | E118: Electric Skateboard | F118: 305 Ringstraße | G118: Hamburg | H118: 20095 | I118: =INDEX(Lookups!$B$3:$B$6,MATCH(Y118,Lookups!$A$3:$A$6,0)) -> Germany | J118: =INDEX(Lookups!$C$3:$C$6,MATCH(Y118,Lookups!$A$3:$A$6,0)) -> Europe | K118: =INDEX(Lookups!$D$3:$D$6,MATCH(Y118,Lookups!$A$3:$A$6,0)) -> EUR | L118: 950 | M118: =ROUND(L118*INDEX(Lookups!$G$3:$G$5,MATCH(K118,Lookups!$F$3:$F$5,0)),0) -> 1026 | N118: 220 | O118: 0 | P118: =ROUND(N118*M118*(1-O118/100),0) -> 225720 | Q118: =ROUND(AA118*Lookups!$O$3,0)&" - "&ROUND(AB118*Lookups!$O$3,0)&" km/h" -> 29 - 45 km/h | R118: =IF(ISNUMBER(SEARCH("meters",W118)),ROUND(VALUE(SUBSTITUTE(LEFT(W118,FIND(" ",W118)-1),",",""))/Lookups!$O$4,0),ROUND(VALUE(LEFT(W118,FIND(" ",W118)-1))*Lookups!$O$3,0)) -> 40 | S118: Jonas | T118: Fischer | U118: 18 mph | V118: 28 mph | W118: 25 miles | X118: 305 Ringstraße, Hamburg, 20095 | Y118: DE | Z118: €950 | AA118: =IF(U118="",INDEX(Lookups!$J$3:$J$5,MATCH(E118,Lookups!$I$3:$I$5,0)),VALUE(LEFT(U118,FIND(" ",U118)-1))) -> 18 | AB118: =VALUE(LEFT(V118,FIND(" ",V118)-1)) -> 28
A119: 118 | B119: =T119&", "&S119 -> Bernard, Théo | C119: October | D119: ="Q"&ROUNDUP(MATCH(C119,Lookups!$L$3:$L$14,0)/3,0) -> Q4 | E119: Electric Unicycle | F119: 56 Boulevard Saint-Germain | G119: Paris | H119: 75005 | I119: =INDEX(Lookups!$B$3:$B$6,MATCH(Y119,Lookups!$A$3:$A$6,0)) -> France | J119: =INDEX(Lookups!$C$3:$C$6,MATCH(Y119,Lookups!$A$3:$A$6,0)) -> Europe | K119: =INDEX(Lookups!$D$3:$D$6,MATCH(Y119,Lookups!$A$3:$A$6,0)) -> EUR | L119: 1100 | M119: =ROUND(L119*INDEX(Lookups!$G$3:$G$5,MATCH(K119,Lookups!$F$3:$F$5,0)),0) -> 1188 | N119: 130 | O119: 0 | P119: =ROUND(N119*M119*(1-O119/100),0) -> 154440 | Q119: =ROUND(AA119*Lookups!$O$3,0)&" - "&ROUND(AB119*Lookups!$O$3,0)&" km/h" -> 24 - 48 km/h | R119: =IF(ISNUMBER(SEARCH("meters",W119)),ROUND(VALUE(SUBSTITUTE(LEFT(W119,FIND(" ",W119)-1),",",""))/Lookups!$O$4,0),ROUND(VALUE(LEFT(W119,FIND(" ",W119)-1))*Lookups!$O$3,0)) -> 48 | S119: Théo | T119: Bernard | U119: 15 mph | V119: 30 mph | W119: 30 miles | X119: 56 Boulevard Saint-Germain, Paris, 75005 | Y119: FR | Z119: €1100 | AA119: =IF(U119="",INDEX(Lookups!$J$3:$J$5,MATCH(E119,Lookups!$I$3:$I$5,0)),VALUE(LEFT(U119,FIND(" ",U119)-1))) -> 15 | AB119: =VALUE(LEFT(V119,FIND(" ",V119)-1)) -> 30
...

Sheet Original Data
A1: Sales Rep ID | B1: Rep First Name | C1: Rep Last Name | D1: Month | E1: Product Type | F1: Min Speed | G1: Speed | H1: Distance | I1: Shipping Address | J1: Country Code | K1: Unit Price | L1: Units Sold | M1: Discount (%)
A2: 1 | B2: Sanya | C2: Joshi | D2: January | E2: Electric Unicycle | F2: 15 mph | G2: 30 mph | H2: 30 miles | I2: 456 Brigade Road, Bengaluru, 560001 | J2: IN | K2: ₹30,000 | L2: 150 | M2: 10
A3: 2 | B3: Sanya | C3: Joshi | D3: January | E3: Electric Scooter | F3: 20 mph | G3: 35 mph | H3: 40 miles | I3: 457 Brigade Road, Bengaluru, 560001 | J3: IN | K3: ₹25,000 | L3: 300 | M3: 10
A4: 2 | B4: Sanya | C4: Joshi | D4: January | E4: Electric Scooter | F4: 20 mph | G4: 35 mph | H4: 40 miles | I4: 457 Brigade Road, Bengaluru, 560001 | J4: IN | K4: ₹25,000 | L4: 300 | M4: 10
A5: 3 | B5: Sanya | C5: Joshi | D5: January | E5: Electric Skateboard | F5: 18 mph | G5: 28 mph | H5: 25 miles | I5: 458 Brigade Road, Bengaluru, 560001 | J5: IN | K5: ₹22,000 | L5: 200 | M5: 10
A6: 4 | B6: Fang | C6: Liu | D6: January | E6: Electric Unicycle | F6: 15 mph | G6: 30 mph | H6: 30 miles | I6: 99 Nanjing Road, Shanghai, 200001 | J6: CN | K6: ¥5,000 | L6: 500 | M6: 10
A7: 5 | B7: Fang | C7: Liu | D7: January | E7: Electric Scooter | F7: 20 mph | G7: 35 mph | H7: 40 miles | I7: 100 Nanjing Road, Shanghai, 200001 | J7: CN | K7: ¥3,500 | L7: 1000 | M7: 10
A8: 6 | B8: Fang | C8: Liu | D8: January | E8: Electric Skateboard | G8: 28 mph | H8: 40,230 meters | I8: 101 Nanjing Road, Shanghai, 200001 | J8: CN | K8: ¥4,200 | L8: 800 | M8: 10
A9: 7 | B9: Jonas | C9: Fischer | D9: January | E9: Electric Unicycle | F9: 15 mph | G9: 30 mph | H9: 48,280 meters | I9: 303 Ringstraße, Hamburg, 20095 | J9: DE | K9: €1000 | L9: 120 | M9: 10
A10: 8 | B10: Jonas | C10: Fischer | D10: January | E10: Electric Scooter | F10: 20 mph | G10: 35 mph | H10: 40 miles | I10: 304 Ringstraße, Hamburg, 20095 | J10: DE | K10: €800 | L10: 200 | M10: 10
A11: 8 | B11: Jonas | C11: Fischer | D11: January | E11: Electric Scooter | F11: 20 mph | G11: 35 mph | H11: 40 miles | I11: 304 Ringstraße, Hamburg, 20095 | J11: DE | K11: €800 | L11: 200 | M11: 10
A12: 9 | B12: Jonas | C12: Fischer | D12: January | E12: Electric Skateboard | F12: 18 mph | G12: 28 mph | H12: 25 miles | I12: 305 Ringstraße, Hamburg, 20095 | J12: DE | K12: €950 | L12: 150 | M12: 10
A13: 10 | B13: Théo | C13: Bernard | D13: January | E13: Electric Unicycle | F13: 15 mph | G13: 30 mph | H13: 30 miles | I13: 56 Boulevard Saint-Germain, Paris, 75005 | J13: FR | K13: €1100 | L13: 100 | M13: 10
A14: 11 | B14: Théo | C14: Bernard | D14: January | E14: Electric Scooter | F14: 20 mph | G14: 35 mph | H14: 64,370 meters | I14: 57 Boulevard Saint-Germain, Paris, 75005 | J14: FR | K14: €900 | L14: 250 | M14: 10
A15: 12 | B15: Théo | C15: Bernard | D15: January | E15: Electric Skateboard | F15: 18 mph | G15: 28 mph | H15: 25 miles | I15: 58 Boulevard Saint-Germain, Paris, 75005 | J15: FR | K15: €1050 | L15: 180 | M15: 10
A16: 13 | B16: Sanya | C16: Joshi | D16: February | E16: Electric Unicycle | F16: 15 mph | G16: 30 mph | H16: 30 miles | I16: 456 Brigade Road, Bengaluru, 560001 | J16: IN | K16: ₹30,000 | L16: 160 | M16: 0
A17: 14 | B17: Sanya | C17: Joshi | D17: February | E17: Electric Scooter | G17: 35 mph | H17: 40 miles | I17: 457 Brigade Road, Bengaluru, 560001 | J17: IN | K17: ₹25,000 | L17: 350 | M17: 0
A18: 15 | B18: Sanya | C18: Joshi | D18: February | E18: Electric Skateboard | F18: 18 mph | G18: 28 mph | H18: 25 miles | I18: 458 Brigade Road, Bengaluru, 560001 | J18: IN | K18: ₹22,000 | L18: 220 | M18: 0
A19: 16 | B19: Fang | C19: Liu | D19: February | E19: Electric Unicycle | F19: 15 mph | G19: 30 mph | H19: 48,280 meters | I19: 99 Nanjing Road, Shanghai, 200001 | J19: CN | K19: ¥5,000 | L19: 550 | M19: 0
A20: 17 | B20: Fang | C20: Liu | D20: February | E20: Electric Scooter | F20: 20 mph | G20: 35 mph | H20: 40 miles | I20: 100 Nanjing Road, Shanghai, 200001 | J20: CN | K20: ¥3,500 | L20: 1200 | M20: 0
A21: 17 | B21: Fang | C21: Liu | D21: February | E21: Electric Scooter | F21: 20 mph | G21: 35 mph | H21: 40 miles | I21: 100 Nanjing Road, Shanghai, 200001 | J21: CN | K21: ¥3,500 | L21: 1200 | M21: 0
A22: 18 | B22: Fang | C22: Liu | D22: February | E22: Electric Skateboard | F22: 18 mph | G22: 28 mph | H22: 25 miles | I22: 101 Nanjing Road, Shanghai, 200001 | J22: CN | K22: ¥4,200 | L22: 850 | M22: 0
A23: 19 | B23: Jonas | C23: Fischer | D23: February | E23: Electric Unicycle | F23: 15 mph | G23: 30 mph | H23: 30 miles | I23: 303 Ringstraße, Hamburg, 20095 | J23: DE | K23: €1000 | L23: 130 | M23: 0
A24: 20 | B24: Jonas | C24: Fischer | D24: February | E24: Electric Scooter | F24: 20 mph | G24: 35 mph | H24: 40 miles | I24: 304 Ringstraße, Hamburg, 20095 | J24: DE | K24: €800 | L24: 220 | M24: 0
A25: 21 | B25: Jonas | C25: Fischer | D25: February | E25: Electric Skateboard | F25: 18 mph | G25: 28 mph | H25: 25 miles | I25: 305 Ringstraße, Hamburg, 20095 | J25: DE | K25: €950 | L25: 160 | M25: 0
A26: 22 | B26: Théo | C26: Bernard | D26: February | E26: Electric Unicycle | F26: 15 mph | G26: 30 mph | H26: 30 miles | I26: 56 Boulevard Saint-Germain, Paris, 75005 | J26: FR | K26: €1100 | L26: 110 | M26: 0
A27: 23 | B27: Théo | C27: Bernard | D27: February | E27: Electric Scooter | F27: 20 mph | G27: 35 mph | H27: 40 miles | I27: 57 Boulevard Saint-Germain, Paris, 75005 | J27: FR | K27: €900 | L27: 260 | M27: 0
A28: 23 | B28: Théo | C28: Bernard | D28: February | E28: Electric Scooter | F28: 20 mph | G28: 35 mph | H28: 40 miles | I28: 57 Boulevard Saint-Germain, Paris, 75005 | J28: FR | K28: €900 | L28: 260 | M28: 0
A29: 24 | B29: Théo | C29: Bernard | D29: February | E29: Electric Skateboard | F29: 18 mph | G29: 28 mph | H29: 40,230 meters | I29: 58 Boulevard Saint-Germain, Paris, 75005 | J29: FR | K29: €1050 | L29: 200 | M29: 0
A30: 25 | B30: Sanya | C30: Joshi | D30: March | E30: Electric Unicycle | F30: 15 mph | G30: 30 mph | H30: 30 miles | I30: 456 Brigade Road, Bengaluru, 560001 | J30: IN | K30: ₹30,000 | L30: 160 | M30: 0
A31: 26 | B31: Sanya | C31: Joshi | D31: March | E31: Electric Scooter | G31: 35 mph | H31: 40 miles | I31: 457 Brigade Road, Bengaluru, 560001 | J31: IN | K31: ₹25,000 | L31: 350 | M31: 0
A32: 27 | B32: Sanya | C32: Joshi | D32: March | E32: Electric Skateboard | F32: 18 mph | G32: 28 mph | H32: 25 miles | I32: 458 Brigade Road, Bengaluru, 560001 | J32: IN | K32: ₹22,000 | L32: 220 | M32: 0
A33: 28 | B33: Fang | C33: Liu | D33: March | E33: Electric Unicycle | F33: 15 mph | G33: 30 mph | H33: 30 miles | I33: 99 Nanjing Road, Shanghai, 200001 | J33: CN | K33: ¥5,000 | L33: 550 | M33: 0
A34: 29 | B34: Fang | C34: Liu | D34: March | E34: Electric Scooter | F34: 20 mph | G34: 35 mph | H34: 64,370 meters | I34: 100 Nanjing Road, Shanghai, 200001 | J34: CN | K34: ¥3,500 | L34: 1200 | M34: 0
A35: 30 | B35: Fang | C35: Liu | D35: March | E35: Electric Skateboard | F35: 18 mph | G35: 28 mph | H35: 25 miles | I35: 101 Nanjing Road, Shanghai, 200001 | J35: CN | K35: ¥4,200 | L35: 850 | M35: 0
A36: 30 | B36: Fang | C36: Liu | D36: March | E36: Electric Skateboard | F36: 18 mph | G36: 28 mph | H36: 25 miles | I36: 101 Nanjing Road, Shanghai, 200001 | J36: CN | K36: ¥4,200 | L36: 850 | M36: 0
A37: 31 | B37: Jonas | C37: Fischer | D37: March | E37: Electric Unicycle | F37: 15 mph | G37: 30 mph | H37: 30 miles | I37: 303 Ringstraße, Hamburg, 20095 | J37: DE | K37: €1000 | L37: 130 | M37: 0
A38: 32 | B38: Jonas | C38: Fischer | D38: March | E38: Electric Scooter | F38: 20 mph | G38: 35 mph | H38: 40 miles | I38: 304 Ringstraße, Hamburg, 20095 | J38: DE | K38: €800 | L38: 220 | M38: 0
A39: 33 | B39: Jonas | C39: Fischer | D39: March | E39: Electric Skateboard | F39: 18 mph | G39: 28 mph | H39: 25 miles | I39: 305 Ringstraße, Hamburg, 20095 | J39: DE | K39: €950 | L39: 160 | M39: 0
A40: 34 | B40: Théo | C40: Bernard | D40: March | E40: Electric Unicycle | F40: 15 mph | G40: 30 mph | H40: 48,280 meters | I40: 56 Boulevard Saint-Germain, Paris, 75005 | J40: FR | K40: €1100 | L40: 110 | M40: 0
A41: 35 | B41: Théo | C41: Bernard | D41: March | E41: Electric Scooter | F41: 20 mph | G41: 35 mph | H41: 40 miles | I41: 57 Boulevard Saint-Germain, Paris, 75005 | J41: FR | K41: €900 | L41: 260 | M41: 0
A42: 36 | B42: Théo | C42: Bernard | D42: March | E42: Electric Skateboard | F42: 18 mph | G42: 28 mph | H42: 25 miles | I42: 58 Boulevard Saint-Germain, Paris, 75005 | J42: FR | K42: €1050 | L42: 200 | M42: 0
A43: 37 | B43: Sanya | C43: Joshi | D43: April | E43: Electric Unicycle | F43: 15 mph | G43: 30 mph | H43: 30 miles | I43: 456 Brigade Road, Bengaluru, 560001 | J43: IN | K43: ₹30,000 | L43: 200 | M43: 0
... A45: 39 | B45: Sanya | C45: Joshi | D45: April | E45: Electric Skateboard | F45: 18 mph | G45: 28 mph | H45: 25 miles | I45: 458 Brigade Road, Bengaluru, 560001 | J45: IN | K45: ₹22,000 | L45: 300 | M45: 0
A46: 40 | B46: Fang | C46: Liu | D46: April | E46: Electric Unicycle | G46: 30 mph | H46: 30 miles | I46: 99 Nanjing Road, Shanghai, 200001 | J46: CN | K46: ¥5,000 | L46: 700 | M46: 0
A47: 41 | B47: Fang | C47: Liu | D47: April | E47: Electric Scooter | F47: 20 mph | G47: 35 mph | H47: 40 miles | I47: 100 Nanjing Road, Shanghai, 200001 | J47: CN | K47: ¥3,500 | L47: 1600 | M47: 0
A48: 42 | B48: Fang | C48: Liu | D48: April | E48: Electric Skateboard | F48: 18 mph | G48: 28 mph | H48: 25 miles | I48: 101 Nanjing Road, Shanghai, 200001 | J48: CN | K48: ¥4,200 | L48: 1000 | M48: 0
A49: 43 | B49: Jonas | C49: Fischer | D49: April | E49: Electric Unicycle | F49: 15 mph | G49: 30 mph | H49: 48,280 meters | I49: 303 Ringstraße, Hamburg, 20095 | J49: DE | K49: €1000 | L49: 160 | M49: 0
A50: 43 | B50: Jonas | C50: Fischer | D50: April | E50: Electric Unicycle | F50: 15 mph | G50: 30 mph | H50: 48,280 meters | I50: 303 Ringstraße, Hamburg, 20095 | J50: DE | K50: €1000 | L50: 160 | M50: 0
A51: 44 | B51: Jonas | C51: Fischer | D51: April | E51: Electric Scooter | F51: 20 mph | G51: 35 mph | H51: 40 miles | I51: 304 Ringstraße, Hamburg, 20095 | J51: DE | K51: €800 | L51: 280 | M51: 0
A52: 45 | B52: Jonas | C52: Fischer | D52: April | E52: Electric Skateboard | F52: 18 mph | G52: 28 mph | H52: 25 miles | I52: 305 Ringstraße, Hamburg, 20095 | J52: DE | K52: €950 | L52: 200 | M52: 0
A53: 46 | B53: Théo | C53: Bernard | D53: April | E53: Electric Unicycle | F53: 15 mph | G53: 30 mph | H53: 30 miles | I53: 56 Boulevard Saint-Germain, Paris, 75005 | J53: FR | K53: €1100 | L53: 130 | M53: 0
A54: 47 | B54: Théo | C54: Bernard | D54: April | E54: Electric Scooter | F54: 20 mph | G54: 35 mph | H54: 40 miles | I54: 57 Boulevard Saint-Germain, Paris, 75005 | J54: FR | K54: €900 | L54: 300 | M54: 0
A55: 48 | B55: Théo | C55: Bernard | D55: April | E55: Electric Skateboard | G55: 28 mph | H55: 40,230 meters | I55: 58 Boulevard Saint-Germain, Paris, 75005 | J55: FR | K55: €1050 | L55: 230 | M55: 0
A56: 49 | B56: Sanya | C56: Joshi | D56: May | E56: Electric Unicycle | F56: 15 mph | G56: 30 mph | H56: 30 miles | I56: 456 Brigade Road, Bengaluru, 560001 | J56: IN | K56: ₹30,000 | L56: 200 | M56: 0
A57: 50 | B57: Sanya | C57: Joshi | D57: May | E57: Electric Scooter | F57: 20 mph | G57: 35 mph | H57: 40 miles | I57: 457 Brigade Road, Bengaluru, 560001 | J57: IN | K57: ₹25,000 | L57: 450 | M57: 0
A58: 51 | B58: Sanya | C58: Joshi | D58: May | E58: Electric Skateboard | F58: 18 mph | G58: 28 mph | H58: 25 miles | I58: 458 Brigade Road, Bengaluru, 560001 | J58: IN | K58: ₹22,000 | L58: 350 | M58: 0
A59: 52 | B59: Fang | C59: Liu | D59: May | E59: Electric Unicycle | F59: 15 mph | G59: 30 mph | H59: 48,280 meters | I59: 99 Nanjing Road, Shanghai, 200001 | J59: CN | K59: ¥5,000 | L59: 700 | M59: 0
A60: 53 | B60: Fang | C60: Liu | D60: May | E60: Electric Scooter | F60: 20 mph | G60: 35 mph | H60: 40 miles | I60: 100 Nanjing Road, Shanghai, 200001 | J60: CN | K60: ¥3,500 | L60: 1600 | M60: 0
A61: 53 | B61: Fang | C61: Liu | D61: May | E61: Electric Scooter | F61: 20 mph | G61: 35 mph | H61: 40 miles | I61: 100 Nanjing Road, Shanghai, 200001 | J61: CN | K61: ¥3,500 | L61: 1600 | M61: 0
A62: 54 | B62: Fang | C62: Liu | D62: May | E62: Electric Skateboard | F62: 18 mph | G62: 28 mph | H62: 25 miles | I62: 101 Nanjing Road, Shanghai, 200001 | J62: CN | K62: ¥4,200 | L62: 1000 | M62: 0
A63: 55 | B63: Jonas | C63: Fischer | D63: May | E63: Electric Unicycle | F63: 15 mph | G63: 30 mph | H63: 30 miles | I63: 303 Ringstraße, Hamburg, 20095 | J63: DE | K63: €1000 | L63: 180 | M63: 0
A64: 56 | B64: Jonas | C64: Fischer | D64: May | E64: Electric Scooter | F64: 20 mph | G64: 35 mph | H64: 40 miles | I64: 304 Ringstraße, Hamburg, 20095 | J64: DE | K64: €800 | L64: 320 | M64: 0
A65: 57 | B65: Jonas | C65: Fischer | D65: May | E65: Electric Skateboard | F65: 18 mph | G65: 28 mph | H65: 25 miles | I65: 305 Ringstraße, Hamburg, 20095 | J65: DE | K65: €950 | L65: 220 | M65: 0
A66: 58 | B66: Théo | C66: Bernard | D66: May | E66: Electric Unicycle | F66: 15 mph | G66: 30 mph | H66: 30 miles | I66: 56 Boulevard Saint-Germain, Paris, 75005 | J66: FR | K66: €1100 | L66: 140 | M66: 0
A67: 59 | B67: Théo | C67: Bernard | D67: May | E67: Electric Scooter | F67: 20 mph | G67: 35 mph | H67: 64,370 meters | I67: 57 Boulevard Saint-Germain, Paris, 75005 | J67: FR | K67: €900 | L67: 300 | M67: 0
... A70: 62 | B70: Sanya | C70: Joshi | D70: June | E70: Electric Scooter | F70: 20 mph | G70: 35 mph | H70: 40 miles | I70: 457 Brigade Road, Bengaluru, 560001 | J70: IN | K70: ₹25,000 | L70: 500 | M70: 0
A71: 63 | B71: Sanya | C71: Joshi | D71: June | E71: Electric Skateboard | G71: 28 mph | H71: 25 miles | I71: 458 Brigade Road, Bengaluru, 560001 | J71: IN | K71: ₹22,000 | L71: 400 | M71: 0
A72: 64 | B72: Fang | C72: Liu | D72: June | E72: Electric Unicycle | F72: 15 mph | G72: 30 mph | H72: 30 miles | I72: 99 Nanjing Road, Shanghai, 200001 | J72: CN | K72: ¥5,000 | L72: 800 | M72: 0
A73: 65 | B73: Fang | C73: Liu | D73: June | E73: Electric Scooter | F73: 20 mph | G73: 35 mph | H73: 40 miles | I73: 100 Nanjing Road, Shanghai, 200001 | J73: CN | K73: ¥3,500 | L73: 1900 | M73: 0
A74: 66 | B74: Fang | C74: Liu | D74: June | E74: Electric Skateboard | F74: 18 mph | G74: 28 mph | H74: 25 miles | I74: 101 Nanjing Road, Shanghai, 200001 | J74: CN | K74: ¥4,200 | L74: 1200 | M74: 0
A75: 67 | B75: Jonas | C75: Fischer | D75: June | E75: Electric Unicycle | F75: 15 mph | G75: 30 mph | H75: 30 miles | I75: 303 Ringstraße, Hamburg, 20095 | J75: DE | K75: €1000 | L75: 200 | M75: 0
A76: 68 | B76: Jonas | C76: Fischer | D76: June | E76: Electric Scooter | F76: 20 mph | G76: 35 mph | H76: 64,370 meters | I76: 304 Ringstraße, Hamburg, 20095 | J76: DE | K76: €800 | L76: 350 | M76: 0
A77: 69 | B77: Jonas | C77: Fischer | D77: June | E77: Electric Skateboard | F77: 18 mph | G77: 28 mph | H77: 40,230 meters | I77: 305 Ringstraße, Hamburg, 20095 | J77: DE | K77: €950 | L77: 250 | M77: 0
A78: 70 | B78: Théo | C78: Bernard | D78: June | E78: Electric Unicycle | G78: 30 mph | H78: 30 miles | I78: 56 Boulevard Saint-Germain, Paris, 75005 | J78: FR | K78: €1100 | L78: 150 | M78: 0
A79: 70 | B79: Théo | C79: Bernard | D79: June | E79: Electric Unicycle | G79: 30 mph | H79: 30 miles | I79: 56 Boulevard Saint-Germain, Paris, 75005 | J79: FR | K79: €1100 | L79: 150 | M79: 0
A80: 71 | B80: Théo | C80: Bernard | D80: June | E80: Electric Scooter | F80: 20 mph | G80: 35 mph | H80: 40 miles | I80: 57 Boulevard Saint-Germain, Paris, 75005 | J80: FR | K80: €900 | L80: 350 | M80: 0
A81: 72 | B81: Théo | C81: Bernard | D81: June | E81: Electric Skateboard | F81: 18 mph | G81: 28 mph | H81: 25 miles | I81: 58 Boulevard Saint-Germain, Paris, 75005 | J81: FR | K81: €1050 | L81: 300 | M81: 0
A82: 72 | B82: Théo | C82: Bernard | D82: June | E82: Electric Skateboard | F82: 18 mph | G82: 28 mph | H82: 25 miles | I82: 58 Boulevard Saint-Germain, Paris, 75005 | J82: FR | K82: €1050 | L82: 300 | M82: 0
A83: 73 | B83: Sanya | C83: Joshi | D83: July | E83: Electric Unicycle | F83: 15 mph | G83: 30 mph | H83: 30 miles | I83: 456 Brigade Road, Bengaluru, 560001 | J83: IN | K83: ₹30,000 | L83: 250 | M83: 0
A84: 74 | B84: Sanya | C84: Joshi | D84: July | E84: Electric Scooter | F84: 20 mph | G84: 35 mph | H84: 40 miles | I84: 457 Brigade Road, Bengaluru, 560001 | J84: IN | K84: ₹25,000 | L84: 500 | M84: 0
A85: 75 | B85: Sanya | C85: Joshi | D85: July | E85: Electric Skateboard | F85: 18 mph | G85: 28 mph | H85: 25 miles | I85: 458 Brigade Road, Bengaluru, 560001 | J85: IN | K85: ₹22,000 | L85: 400 | M85: 0
A86: 76 | B86: Fang | C86: Liu | D86: July | E86: Electric Unicycle | F86: 15 mph | G86: 30 mph | H86: 48,280 meters | I86: 99 Nanjing Road, Shanghai, 200001 | J86: CN | K86: ¥5,000 | L86: 800 | M86: 0
A87: 77 | B87: Fang | C87: Liu | D87: July | E87: Electric Scooter | F87: 20 mph | G87: 35 mph | H87: 40 miles | I87: 100 Nanjing Road, Shanghai, 200001 | J87: CN | K87: ¥3,500 | L87: 1800 | M87: 0
A88: 78 | B88: Fang | C88: Liu | D88: July | E88: Electric Skateboard | F88: 18 mph | G88: 28 mph | H88: 25 miles | I88: 101 Nanjing Road, Shanghai, 200001 | J88: CN | K88: ¥4,200 | L88: 1200 | M88: 0
A89: 79 | B89: Jonas | C89: Fischer | D89: July | E89: Electric Unicycle | F89: 15 mph | G89: 30 mph | H89: 30 miles | I89: 303 Ringstraße, Hamburg, 20095 | J89: DE | K89: €1000 | L89: 200 | M89: 0
A90: 80 | B90: Jonas | C90: Fischer | D90: July | E90: Electric Scooter | F90: 20 mph | G90: 35 mph | H90: 40 miles | I90: 304 Ringstraße, Hamburg, 20095 | J90: DE | K90: €800 | L90: 350 | M90: 0
A91: 81 | B91: Jonas | C91: Fischer | D91: July | E91: Electric Skateboard | F91: 18 mph | G91: 28 mph | H91: 25 miles | I91: 305 Ringstraße, Hamburg, 20095 | J91: DE | K91: €950 | L91: 250 | M91: 0
... A98: 87 | B98: Sanya | C98: Joshi | D98: August | E98: Electric Skateboard | F98: 18 mph | G98: 28 mph | H98: 40,230 meters | I98: 458 Brigade Road, Bengaluru, 560001 | J98: IN | K98: ₹22,000 | L98: 350 | M98: 0
A99: 88 | B99: Fang | C99: Liu | D99: August | E99: Electric Unicycle | G99: 30 mph | H99: 30 miles | I99: 99 Nanjing Road, Shanghai, 200001 | J99: CN | K99: ¥5,000 | L99: 700 | M99: 0
A100: 89 | B100: Fang | C100: Liu | D100: August | E100: Electric Scooter | F100: 20 mph | G100: 35 mph | H100: 40 miles | I100: 100 Nanjing Road, Shanghai, 200001 | J100: CN | K100: ¥3,500 | L100: 1600 | M100: 0
A101: 90 | B101: Fang | C101: Liu | D101: August | E101: Electric Skateboard | F101: 18 mph | G101: 28 mph | H101: 25 miles | I101: 101 Nanjing Road, Shanghai, 200001 | J101: CN | K101: ¥4,200 | L101: 1000 | M101: 0
A102: 91 | B102: Jonas | C102: Fischer | D102: August | E102: Electric Unicycle | F102: 15 mph | G102: 30 mph | H102: 30 miles | I102: 303 Ringstraße, Hamburg, 20095 | J102: DE | K102: €1000 | L102: 180 | M102: 0
A103: 92 | B103: Jonas | C103: Fischer | D103: August | E103: Electric Scooter | F103: 20 mph | G103: 35 mph | H103: 64,370 meters | I103: 304 Ringstraße, Hamburg, 20095 | J103: DE | K103: €800 | L103: 300 | M103: 0
A104: 93 | B104: Jonas | C104: Fischer | D104: August | E104: Electric Skateboard | F104: 18 mph | G104: 28 mph | H104: 25 miles | I104: 305 Ringstraße, Hamburg, 20095 | J104: DE | K104: €950 | L104: 230 | M104: 0
A105: 93 | B105: Jonas | C105: Fischer | D105: August | E105: Electric Skateboard | F105: 18 mph | G105: 28 mph | H105: 25 miles | I105: 305 Ringstraße, Hamburg, 20095 | J105: DE | K105: €950 | L105: 230 | M105: 0
A106: 94 | B106: Théo | C106: Bernard | D106: August | E106: Electric Unicycle | F106: 15 mph | G106: 30 mph | H106: 30 miles | I106: 56 Boulevard Saint-Germain, Paris, 75005 | J106: FR | K106: €1100 | L106: 150 | M106: 0
A107: 95 | B107: Théo | C107: Bernard | D107: August | E107: Electric Scooter | F107: 20 mph | G107: 35 mph | H107: 40 miles | I107: 57 Boulevard Saint-Germain, Paris, 75005 | J107: FR | K107: €900 | L107: 280 | M107: 0
A108: 96 | B108: Théo | C108: Bernard | D108: August | E108: Electric Skateboard | F108: 18 mph | G108: 28 mph | H108: 25 miles | I108: 58 Boulevard Saint-Germain, Paris, 75005 | J108: FR | K108: €1050 | L108: 290 | M108: 0
A109: 97 | B109: Sanya | C109: Joshi | D109: September | E109: Electric Unicycle | F109: 15 mph | G109: 30 mph | H109: 30 miles | I109: 456 Brigade Road, Bengaluru, 560001 | J109: IN | K109: ₹30,000 | L109: 180 | M109: 0
...

Sheet Lookups
A1: Reference tables and assumptions (blue = editable input)
A2: Country Code | B2: Country | C2: Continent | D2: Currency | F2: Currency | G2: USD per 1 unit | I2: Product Type | J2: Standard Min Speed (mph) | L2: Month (calendar order) | N2: Conversion | O2: Value
A3: IN | B3: India | C3: Asia | D3: INR | F3: INR | G3: 0.012 | I3: Electric Unicycle | J3: 15 | L3: January | N3: km per mile | O3: 1.60934
A4: CN | B4: China | C4: Asia | D4: CNY | F4: CNY | G4: 0.14 | I4: Electric Scooter | J4: 20 | L4: February | N4: metres per km | O4: 1000
A5: FR | B5: France | C5: Europe | D5: EUR | F5: EUR | G5: 1.08 | I5: Electric Skateboard | J5: 18 | L5: March
A6: DE | B6: Germany | C6: Europe | D6: EUR | L6: April
F7: Assumption: fixed illustrative exchange rates (not live). Edit G3:G5 and all USD figures update. | I7: Basis: every non-blank record of a product type has the same Min Speed; used to fill the 12 blanks. | L7: May
L8: June
L9: July
L10: August
L11: September
L12: October
L13: November
L14: December
